Workbook
Name \0: #REF!
Name \a: #REF!
Name \b: #REF!
Name \c: #REF!
Name \D: #REF!
Name \E: #REF!
Name \F: #REF!
Name \G: #REF!
Name \H: #REF!
Name \I: #REF!
Name \J: #REF!
Name \K: #REF!
Name \L: #REF!
Name \M: #REF!
Name \N: #REF!
Name \P: #REF!
Name \q: #REF!
Name \r: #REF!
Name \S: #REF!
Name \t: #REF!
Name \U: #REF!
Name \V: #REF!
Name \w: #REF!
Name \x: #REF!
Name \y: #REF!
Name \Z: #REF!
Name ___________________________________top50: #REF!
Name _________________________________top50: #REF!
Name _______________________________top50: #REF!
Name ______________________________AB113812: #REF!
Name _____________________________AB113812: #REF!
Name ____________________________AB113812: #REF!
Name _________________________top50: #REF!
Name _______________________AB113812: #REF!
Name _____________________top50: #REF!
Name ___________________top50: #REF!
Name __________________AB113812: #REF!
Name __________________top50: #REF!
Name ________________AB113812: #REF!
Name ______________AB113812: #REF!
Name ______________top50: #REF!
Name _____________AB113812: #REF!
Name ____________AB113812: #REF!
Name ____________top50: #REF!
Name ___________AB113812: #REF!
Name ___________top50: #REF!
Name __________AB113812: #REF!
Name __________top50: #REF!
Name _________AB113812: #REF!
Name _________top50: #REF!
Name ________AB113812: #REF!
Name ________top50: #REF!
Name _______AB113812: #REF!
Name _______top50: #REF!
Name ______AB113812: #REF!
Name ______top50: #REF!
Name ___DAT10: #REF!
Name ___DAT15: #REF!
Name ___DAT16: #REF!
Name ___DAT17: #REF!

Sheet Summary Rollforward
A1: Treya Partners
A2: Accounts Receivable Rollforward
A3: February 28, 2024
E5: 45535 | I5: September Activity | L5: 45565 | P5: October Activity | S5: 45596 | W5: November Activity | Z5: 45626 | AD5: December Activity | AI5: 45657 | AM5: January Activity | AQ5: 45688 | AU5: February Activity | AY5: 45716 | BC5: March Activity | BG5: 45747 | BK5: April Activity | BO5: 45777 | BS5: May Activity | BX5: 45808 | CB5: June Activity | CG5: 45838 | CK5: July Activity | CP5: 45869 | CT5: August Activity | CY5: 45900 | DC5: September Activity | DH5: 45930 | DL5: October Activity | DQ5: 45961 | DU5: November Activity | DZ5: 45991 | ED5: December Activity | EI5: 46022
B6: Client | C6: PE Sponsor | E6: Billed AR | F6: Unbilled AR | G6: Total AR | I6: Service Revenue Recorded | J6: Cash Collections | L6: Billed AR | M6: Unbilled AR | N6: Total AR | P6: Service Revenue Recorded | Q6: Cash Collections | S6: Billed AR | T6: Unbilled AR | U6: Total AR | W6: Revenue Recorded | X6: Cash Collections | Z6: Billed AR | AA6: Unbilled AR | AB6: Total AR | AD6: Revenue - Unbilled | AE6: Revenue Invoiced | AF6: Adjustments | AG6: Cash Collections | AI6: Billed AR | AJ6: Unbilled AR | AK6: Total AR | AM6: Revenue - Unbilled | AN6: Revenue Invoiced | AO6: Cash Collections | AQ6: Billed AR | AR6: Unbilled AR | AS6: Total AR | AU6: Revenue - Unbilled | AV6: Revenue Invoiced | AW6: Cash Collections | AY6: Billed AR | AZ6: Unbilled AR | BA6: Total AR | BC6: Revenue - Unbilled | BD6: Revenue Invoiced | BE6: Cash Collections | BG6: Billed AR | BH6: Unbilled AR | BI6: Total AR | BK6: Revenue - Unbilled | BL6: Revenue Invoiced | BM6: Cash Collections | BO6: Billed AR | BP6: Unbilled AR | BQ6: Total AR | BS6: Revenue - Unbilled | BT6: Revenue Invoiced | BU6: Cash Collections | BV6: Current Month Revenue | BX6: Billed AR | BY6: Unbilled AR | BZ6: Total AR | CB6: Revenue - Unbilled | CC6: Revenue Invoiced | CD6: Cash Collections | CE6: Current Month Revenue | CG6: Billed AR | CH6: Unbilled AR | CI6: Total AR | CK6: Revenue - Unbilled | CL6: Revenue Invoiced | CM6: Cash Collections | CN6: Current Month Revenue | CP6: Billed AR | CQ6: Unbilled AR | CR6: Total AR | CT6: Revenue - Unbilled | CU6: Revenue Invoiced | CV6: Cash Collections | CW6: Current Month Revenue | CY6: Billed AR | CZ6: Unbilled AR | DA6: Total AR | DC6: Revenue - Unbilled | DD6: Revenue Invoiced | DE6: Cash Collections | DF6: Current Month Revenue | DH6: Billed AR | DI6: Unbilled AR | DJ6: Total AR | DL6: Revenue - Unbilled | DM6: Revenue Invoiced | DN6: Cash Collections | DO6: Current Month Revenue | DQ6: Billed AR | DR6: Unbilled AR | DS6: Total AR | DU6: Revenue - Unbilled | DV6: Revenue Invoiced | DW6: Cash Collections | DX6: Current Month Revenue | DZ6: Billed AR | EA6: Unbilled AR | EB6: Total AR | ED6: Revenue - Unbilled | EE6: Revenue Invoiced | EF6: Cash Collections | EG6: Current Month Revenue | EI6: Billed AR | EJ6: Unbilled AR | EK6: Total AR
A7: Service Contracts
B8: Artisant Lane | C8: HWP | E8: 0 | F8: =+G8-E8 -> 146395.26 | G8: =+'AR Calculation - Service'!AM33 -> 146395.26 | L8: =+'Sep 30'!G6 -> 121395.26 | M8: =+N8-L8 -> 25000 | N8: =+G8+I8+J8 -> 146395.26 | Q8: =-'Oct Collections'!J8-'Oct Collections'!J9 -> -121395.26 | S8: 0 | T8: =+U8-S8 -> 25000 | U8: =+N8+P8+Q8 -> 25000 | W8: 0 | X8: =-'Oct Collections'!Q8-'Oct Collections'!Q9 -> 0 | Z8: 0 | AA8: =+AB8-Z8 -> 25000 | AB8: =+U8+W8+X8 -> 25000 | AD8: 0 | AF8: -25000 | AG8: =-'Oct Collections'!X8-'Oct Collections'!X9 -> 0 | AI8: 0 | AJ8: =+AK8-AI8 -> 1.4551915e-11 | AK8: =+AB8+AD8+AG8+AF8+AE8 -> 1.4551915e-11 | AM8: 0 | AO8: =-'Oct Collections'!AF8-'Oct Collections'!AF9 -> 0 | AQ8: =+AI8+AN8+AO8 -> 0 | AR8: =+AS8-AQ8 -> 1.4551915e-11 | AS8: =+AK8+AM8+AO8+AN8 -> 1.4551915e-11 | AU8: 0 | AW8: =-'Oct Collections'!AN8-'Oct Collections'!AN9 -> 0 | AY8: =+AQ8+AV8+AW8 -> 0 | AZ8: =+BA8-AY8 -> 1.4551915e-11 | BA8: =+AS8+AU8+AW8+AV8 -> 1.4551915e-11 | BC8: 0 | BG8: =+AY8+BD8+BE8 -> 0 | BH8: =+BI8-BG8 -> 1.4551915e-11 | BI8: =+BA8+BC8+BE8+BD8 -> 1.4551915e-11 | BO8: =+BG8+BL8+BM8 -> 0 | BP8: =+BQ8-BO8 -> 1.4551915e-11 | BQ8: =+BI8+BK8+BM8+BL8 -> 1.4551915e-11 | BS8: =BV8-BT8 -> 0 | BT8: 0 | BU8: 0 | BV8: =SUMIFS('Contract Data'!IP:IP,'Contract Data'!$C:$C,'Summary Rollforward'!$B8) -> 0 | BX8: =+BO8+BT8+BU8 -> 0 | BY8: =+BZ8-BX8 -> 1.4551915e-11 | BZ8: =+BQ8+BS8+BU8+BT8 -> 1.4551915e-11 | CB8: =CE8-CC8 -> 0 | CC8: =SUMIFS('June 25 Inv'!G:G,'June 25 Inv'!D:D,'Summary Rollforward'!$B8) -> 0 | CD8: =-SUMIFS('Jun25 Dep'!I:I,'Jun25 Dep'!F:F,'Summary Rollforward'!$B8) -> 0 | CE8: =SUMIFS('Contract Data'!IQ:IQ,'Contract Data'!$C:$C,'Summary Rollforward'!$B8) -> 0 | CG8: =+BX8+CC8+CD8 -> 0 | CH8: =+CI8-CG8 -> 1.4551915e-11 | CI8: =+BZ8+CB8+CD8+CC8 -> 1.4551915e-11 | CK8: =CN8-CL8 -> 0 | CL8: =SUMIFS('Jul 25 Inv'!H:H,'Jul 25 Inv'!E:E,'Summary Rollforward'!$B8) -> 0 | CM8: =-SUMIFS('Jul25 Dep'!J:J,'Jul25 Dep'!F:F,'Summary Rollforward'!$B8) -> 0 | CN8: =SUMIFS('Contract Data'!IR:IR,'Contract Data'!$C:$C,'Summary Rollforward'!$B8) -> 0 | CP8: =+CG8+CL8+CM8 -> 0 | CQ8: =+CR8-CP8 -> 1.4551915e-11 | CR8: =+CI8+CK8+CM8+CL8 -> 1.4551915e-11 | CT8: =CW8-CU8 -> 0 | CU8: =SUMIFS('Aug 25 Inv'!H:H,'Aug 25 Inv'!E:E,'Summary Rollforward'!$B8) -> 0 | CV8: =-SUMIFS('Aug25 Dep'!J:J,'Aug25 Dep'!F:F,'Summary Rollforward'!$B8) -> 0 | CW8: =SUMIFS('Contract Data'!IS:IS,'Contract Data'!$C:$C,'Summary Rollforward'!$B8) -> 0 | CY8: =+CP8+CU8+CV8 -> 0 | CZ8: =+DA8-CY8 -> 1.4551915e-11 | DA8: =+CR8+CT8+CV8+CU8 -> 1.4551915e-11 | DC8: =DF8-DD8 -> 0 | DD8: =SUMIFS('Sep 25 Inv'!H:H,'Sep 25 Inv'!E:E,'Summary Rollforward'!$B8) -> 0 | DE8: =-SUMIFS('Sep25 Dep'!J:J,'Sep25 Dep'!F:F,'Summary Rollforward'!$B8) -> 0 | DF8: =SUMIFS('Contract Data'!IT:IT,'Contract Data'!$C:$C,'Summary Rollforward'!$B8) -> 0 | DH8: =+CY8+DD8+DE8 -> 0 | DI8: =+DJ8-DH8 -> 1.4551915e-11 | DJ8: =+DA8+DC8+DE8+DD8 -> 1.4551915e-11 | DL8: =DO8-DM8 -> 0 | DM8: =SUMIFS('Oct 25 Inv'!H:H,'Oct 25 Inv'!E:E,'Summary Rollforward'!$B8) -> 0 | DN8: =-SUMIFS('Oct25 Dep'!J:J,'Oct25 Dep'!F:F,'Summary Rollforward'!$B8) -> 0 | DO8: =SUMIFS('Contract Data'!IU:IU,'Contract Data'!$C:$C,'Summary Rollforward'!$B8) -> 0 | DQ8: =+DH8+DM8+DN8 -> 0 | DR8: =+DS8-DQ8 -> 1.4551915e-11 | DS8: =+DJ8+DL8+DN8+DM8 -> 1.4551915e-11 | DU8: =DX8-DV8 -> 0 | DV8: =SUMIFS('Nov 25 Inv'!H:H,'Nov 25 Inv'!E:E,'Summary Rollforward'!$B8) -> 0 | DW8: =-SUMIFS('Nov25 Dep'!J:J,'Nov25 Dep'!F:F,'Summary Rollforward'!$B8) -> 0 | DX8: =SUMIFS('Contract Data'!IV:IV,'Contract Data'!$C:$C,'Summary Rollforward'!$B8) -> 0 | DZ8: =+DQ8+DV8+DW8 -> 0 | EA8: =+EB8-DZ8 -> 1.4551915e-11 | EB8: =+DS8+DU8+DW8+DV8 -> 1.4551915e-11 | ED8: =EG8-EE8 -> 0 | EE8: =SUMIFS('Dec 25 Inv'!H:H,'Dec 25 Inv'!E:E,'Summary Rollforward'!$B8) -> 0 | EF8: =-SUMIFS('Dec25 Dep'!I:I,'Dec25 Dep'!F:F,'Summary Rollforward'!$B8) -> 0 | EG8: =SUMIFS('Contract Data'!IW:IW,'Contract Data'!$C:$C,'Summary Rollforward'!$B8) -> 0 | EI8: =+DZ8+EE8+EF8 -> 0 | EJ8: =+EK8-EI8 -> 1.4551915e-11 | EK8: =+EB8+ED8+EF8+EE8 -> 1.4551915e-11
B9: Belt Power | C9: Platte River Equity | DL9: =DO9-DM9 -> -37000 | DM9: =SUMIFS('Oct 25 Inv'!H:H,'Oct 25 Inv'!E:E,'Summary Rollforward'!$B9) -> 52500 | DN9: =-SUMIFS('Oct25 Dep'!J:J,'Oct25 Dep'!F:F,'Summary Rollforward'!$B9) -> 0 | DO9: =SUMIFS('Contract Data'!IU:IU,'Contract Data'!$C:$C,'Summary Rollforward'!$B9) -> 15500 | DQ9: =+DH9+DM9+DN9 -> 52500 | DR9: =+DS9-DQ9 -> -37000 | DS9: =+DJ9+DL9+DN9+DM9 -> 15500 | DU9: =DX9-DV9 -> -21500 | DV9: =SUMIFS('Nov 25 Inv'!H:H,'Nov 25 Inv'!E:E,'Summary Rollforward'!$B9) -> 52500 | DW9: =-SUMIFS('Nov25 Dep'!J:J,'Nov25 Dep'!F:F,'Summary Rollforward'!$B9) -> -52500 | DX9: =SUMIFS('Contract Data'!IV:IV,'Contract Data'!$C:$C,'Summary Rollforward'!$B9) -> 31000 | DZ9: =+DQ9+DV9+DW9 -> 52500 | EA9: =+EB9-DZ9 -> -58500 | EB9: =+DS9+DU9+DW9+DV9 -> -6000 | ED9: =EG9-EE9 -> -21500 | EE9: =SUMIFS('Dec 25 Inv'!H:H,'Dec 25 Inv'!E:E,'Summary Rollforward'!$B9) -> 52500 | EF9: =-SUMIFS('Dec25 Dep'!I:I,'Dec25 Dep'!F:F,'Summary Rollforward'!$B9) -> -52500 | EG9: =SUMIFS('Contract Data'!IW:IW,'Contract Data'!$C:$C,'Summary Rollforward'!$B9) -> 31000 | EI9: =+DZ9+EE9+EF9 -> 52500 | EJ9: =+EK9-EI9 -> -80000 | EK9: =+EB9+ED9+EF9+EE9 -> -27500
B10: Bluum USA | C10: HIG Capital | BS10: =BV10-BT10 -> -107812.5 | BT10: 156250 | BU10: 0 | BV10: =SUMIFS('Contract Data'!IP:IP,'Contract Data'!C:C,'Summary Rollforward'!B10) -> 48437.5 | BX10: =+BO10+BT10+BU10 -> 156250 | BY10: =+BZ10-BX10 -> -107812.5 | BZ10: =+BQ10+BS10+BU10+BT10 -> 48437.5 | CB10: =CE10-CC10 -> 96875 | CC10: =SUMIFS('June 25 Inv'!G:G,'June 25 Inv'!D:D,'Summary Rollforward'!$B10) -> 0 | CD10: =-SUMIFS('Jun25 Dep'!I:I,'Jun25 Dep'!F:F,'Summary Rollforward'!$B10) -> 0 | CE10: =SUMIFS('Contract Data'!IQ:IQ,'Contract Data'!$C:$C,'Summary Rollforward'!$B10) -> 96875 | CG10: =+BX10+CC10+CD10 -> 156250 | CH10: =+CI10-CG10 -> -10937.5 | CI10: =+BZ10+CB10+CD10+CC10 -> 145312.5 | CK10: =CN10-CL10 -> 96875 | CL10: =SUMIFS('Jul 25 Inv'!H:H,'Jul 25 Inv'!E:E,'Summary Rollforward'!$B10) -> 0 | CM10: =-SUMIFS('Jul25 Dep'!J:J,'Jul25 Dep'!F:F,'Summary Rollforward'!$B10) -> -156250 | CN10: =SUMIFS('Contract Data'!IR:IR,'Contract Data'!$C:$C,'Summary Rollforward'!$B10) -> 96875 | CP10: =+CG10+CL10+CM10 -> 0 | CQ10: =+CR10-CP10 -> 85937.5 | CR10: =+CI10+CK10+CM10+CL10 -> 85937.5 | CT10: =CW10-CU10 -> 96875 | CU10: =SUMIFS('Aug 25 Inv'!H:H,'Aug 25 Inv'!E:E,'Summary Rollforward'!$B10) -> 0 | CV10: =-SUMIFS('Aug25 Dep'!J:J,'Aug25 Dep'!F:F,'Summary Rollforward'!$B10) -> 0 | CW10: =SUMIFS('Contract Data'!IS:IS,'Contract Data'!$C:$C,'Summary Rollforward'!$B10) -> 96875 | CY10: =+CP10+CU10+CV10 -> 0 | CZ10: =+DA10-CY10 -> 182812.5 | DA10: =+CR10+CT10+CV10+CU10 -> 182812.5 | DC10: =DF10-DD10 -> -59375 | DD10: =SUMIFS('Sep 25 Inv'!H:H,'Sep 25 Inv'!E:E,'Summary Rollforward'!$B10) -> 156250 | DE10: =-SUMIFS('Sep25 Dep'!J:J,'Sep25 Dep'!F:F,'Summary Rollforward'!$B10) -> -156250 | DF10: =SUMIFS('Contract Data'!IT:IT,'Contract Data'!$C:$C,'Summary Rollforward'!$B10) -> 96875 | DH10: =+CY10+DD10+DE10 -> 0 | DI10: =+DJ10-DH10 -> 123437.5 | DJ10: =+DA10+DC10+DE10+DD10 -> 123437.5 | DL10: =DO10-DM10 -> 40000 | DM10: =SUMIFS('Oct 25 Inv'!H:H,'Oct 25 Inv'!E:E,'Summary Rollforward'!$B10) -> 0 | DN10: =-SUMIFS('Oct25 Dep'!J:J,'Oct25 Dep'!F:F,'Summary Rollforward'!$B10) -> 0 | DO10: =SUMIFS('Contract Data'!IU:IU,'Contract Data'!$C:$C,'Summary Rollforward'!$B10) -> 40000 | DQ10: =+DH10+DM10+DN10 -> 0 | DR10: =+DS10-DQ10 -> 163437.5 | DS10: =+DJ10+DL10+DN10+DM10 -> 163437.5 | DU10: =DX10-DV10 -> 30000 | DV10: =SUMIFS('Nov 25 Inv'!H:H,'Nov 25 Inv'!E:E,'Summary Rollforward'!$B10) -> 0 | DW10: =-SUMIFS('Nov25 Dep'!J:J,'Nov25 Dep'!F:F,'Summary Rollforward'!$B10) -> 0 | DX10: =SUMIFS('Contract Data'!IV:IV,'Contract Data'!$C:$C,'Summary Rollforward'!$B10) -> 30000 | DZ10: =+DQ10+DV10+DW10 -> 0 | EA10: =+EB10-DZ10 -> 193437.5 | EB10: =+DS10+DU10+DW10+DV10 -> 193437.5 | ED10: =EG10-EE10 -> -126250 | EE10: =SUMIFS('Dec 25 Inv'!H:H,'Dec 25 Inv'!E:E,'Summary Rollforward'!$B10) -> 156250 | EF10: =-SUMIFS('Dec25 Dep'!I:I,'Dec25 Dep'!F:F,'Summary Rollforward'!$B10) -> 0 | EG10: =SUMIFS('Contract Data'!IW:IW,'Contract Data'!$C:$C,'Summary Rollforward'!$B10) -> 30000 | EI10: =+DZ10+EE10+EF10 -> 156250 | EJ10: =+EK10-EI10 -> 67187.5 | EK10: =+EB10+ED10+EF10+EE10 -> 223437.5
B11: Breg | C11: HPS Investment Partners | AD11: =+'AR Calculation - Service'!AQ273-AE11 -> 250843 | AJ11: =+AK11-AI11 -> 250843 | AK11: =+AB11+AD11+AG11+AF11+AE11 -> 250843 | AM11: 0 | AO11: =-'Oct Collections'!AF10-'Oct Collections'!AF11 -> 0 | AQ11: =+AI11+AN11+AO11 -> 0 | AR11: =+AS11-AQ11 -> 250843 | AS11: =+AK11+AM11+AO11+AN11 -> 250843 | AU11: 0 | AW11: =-'Oct Collections'!AN10-'Oct Collections'!AN11 -> 0 | AY11: =+AQ11+AV11+AW11 -> 0 | AZ11: =+BA11-AY11 -> 250843 | BA11: =+AS11+AU11+AW11+AV11 -> 250843 | BC11: 0 | BG11: =+AY11+BD11+BE11 -> 0 | BH11: =+BI11-BG11 -> 250843 | BI11: =+BA11+BC11+BE11+BD11 -> 250843 | BO11: =+BG11+BL11+BM11 -> 0 | BP11: =+BQ11-BO11 -> 250843 | BQ11: =+BI11+BK11+BM11+BL11 -> 250843 | BS11: =BV11-BT11 -> -62866 | BT11: 62866 | BU11: 0 | BV11: =SUMIFS('Contract Data'!IP:IP,'Contract Data'!C:C,'Summary Rollforward'!B11) -> 0 | BX11: =+BO11+BT11+BU11 -> 62866 | BY11: =+BZ11-BX11 -> 187977 | BZ11: =+BQ11+BS11+BU11+BT11 -> 250843 | CB11: =CE11-CC11 -> 38500 | CC11: =SUMIFS('June 25 Inv'!G:G,'June 25 Inv'!D:D,'Summary Rollforward'!$B11) -> 0 | CD11: =-SUMIFS('Jun25 Dep'!I:I,'Jun25 Dep'!F:F,'Summary Rollforward'!$B11) -> 0 | CE11: =SUMIFS('Contract Data'!IQ:IQ,'Contract Data'!$C:$C,'Summary Rollforward'!$B11) -> 38500 | CG11: =+BX11+CC11+CD11 -> 62866 | CH11: =+CI11-CG11 -> 226477 | CI11: =+BZ11+CB11+CD11+CC11 -> 289343 | CK11: =CN11-CL11 -> 0 | CL11: =SUMIFS('Jul 25 Inv'!H:H,'Jul 25 Inv'!E:E,'Summary Rollforward'!$B11) -> 0 | CM11: =-SUMIFS('Jul25 Dep'!J:J,'Jul25 Dep'!F:F,'Summary Rollforward'!$B11) -> 0 | CN11: =SUMIFS('Contract Data'!IR:IR,'Contract Data'!$C:$C,'Summary Rollforward'!$B11) -> 0 | CP11: =+CG11+CL11+CM11 -> 62866 | CQ11: =+CR11-CP11 -> 226477 | CR11: =+CI11+CK11+CM11+CL11 -> 289343 | CT11: =CW11-CU11 -> 20895 | CU11: =SUMIFS('Aug 25 Inv'!H:H,'Aug 25 Inv'!E:E,'Summary Rollforward'!$B11) -> 0 | CV11: =-SUMIFS('Aug25 Dep'!J:J,'Aug25 Dep'!F:F,'Summary Rollforward'!$B11) -> 0 | CW11: =SUMIFS('Contract Data'!IS:IS,'Contract Data'!$C:$C,'Summary Rollforward'!$B11) -> 20895 | CY11: =+CP11+CU11+CV11 -> 62866 | CZ11: =+DA11-CY11 -> 247372 | DA11: =+CR11+CT11+CV11+CU11 -> 310238 | DC11: =DF11-DD11 -> 30151.25 | DD11: =SUMIFS('Sep 25 Inv'!H:H,'Sep 25 Inv'!E:E,'Summary Rollforward'!$B11) -> 0 | DE11: =-SUMIFS('Sep25 Dep'!J:J,'Sep25 Dep'!F:F,'Summary Rollforward'!$B11) -> -62866 | DF11: =SUMIFS('Contract Data'!IT:IT,'Contract Data'!$C:$C,'Summary Rollforward'!$B11) -> 30151.25 | DH11: =+CY11+DD11+DE11 -> 0 | DI11: =+DJ11-DH11 -> 277523.25 | DJ11: =+DA11+DC11+DE11+DD11 -> 277523.25 | DL11: =DO11-DM11 -> 30151.25 | DM11: =SUMIFS('Oct 25 Inv'!H:H,'Oct 25 Inv'!E:E,'Summary Rollforward'!$B11) -> 0 | DN11: =-SUMIFS('Oct25 Dep'!J:J,'Oct25 Dep'!F:F,'Summary Rollforward'!$B11) -> 0 | DO11: =SUMIFS('Contract Data'!IU:IU,'Contract Data'!$C:$C,'Summary Rollforward'!$B11) -> 30151.25 | DQ11: =+DH11+DM11+DN11 -> 0 | DR11: =+DS11-DQ11 -> 307674.5 | DS11: =+DJ11+DL11+DN11+DM11 -> 307674.5 | DU11: =DX11-DV11 -> 50000 | DV11: =SUMIFS('Nov 25 Inv'!H:H,'Nov 25 Inv'!E:E,'Summary Rollforward'!$B11) -> 0 | DW11: =-SUMIFS('Nov25 Dep'!J:J,'Nov25 Dep'!F:F,'Summary Rollforward'!$B11) -> 0 | DX11: =SUMIFS('Contract Data'!IV:IV,'Contract Data'!$C:$C,'Summary Rollforward'!$B11) -> 50000 | DZ11: =+DQ11+DV11+DW11 -> 0 | EA11: =+EB11-DZ11 -> 357674.5 | EB11: =+DS11+DU11+DW11+DV11 -> 357674.5 | ED11: =EG11-EE11 -> 60000 | EE11: =SUMIFS('Dec 25 Inv'!H:H,'Dec 25 Inv'!E:E,'Summary Rollforward'!$B11) -> 0 | EF11: =-SUMIFS('Dec25 Dep'!I:I,'Dec25 Dep'!F:F,'Summary Rollforward'!$B11) -> 0 | EG11: =SUMIFS('Contract Data'!IW:IW,'Contract Data'!$C:$C,'Summary Rollforward'!$B11) -> 60000 | EI11: =+DZ11+EE11+EF11 -> 0 | EJ11: =+EK11-EI11 -> 417674.5 | EK11: =+EB11+ED11+EF11+EE11 -> 417674.5
B12: Bright Event Rentals | C12: Trivest | BS12: =BV12-BT12 -> -18375 | BT12: 30000 | BU12: 0 | BV12: =SUMIFS('Contract Data'!IP:IP,'Contract Data'!C:C,'Summary Rollforward'!B12) -> 11625 | BX12: =+BO12+BT12+BU12 -> 30000 | BY12: =+BZ12-BX12 -> -18375 | BZ12: =+BQ12+BS12+BU12+BT12 -> 11625 | CB12: =CE12-CC12 -> -6750 | CC12: =SUMIFS('June 25 Inv'!G:G,'June 25 Inv'!D:D,'Summary Rollforward'!$B12) -> 30000 | CD12: =-SUMIFS('Jun25 Dep'!I:I,'Jun25 Dep'!F:F,'Summary Rollforward'!$B12) -> 0 | CE12: =SUMIFS('Contract Data'!IQ:IQ,'Contract Data'!$C:$C,'Summary Rollforward'!$B12) -> 23250 | CG12: =+BX12+CC12+CD12 -> 60000 | CH12: =+CI12-CG12 -> -25125 | CI12: =+BZ12+CB12+CD12+CC12 -> 34875 | CK12: =CN12-CL12 -> -6750 | CL12: =SUMIFS('Jul 25 Inv'!H:H,'Jul 25 Inv'!E:E,'Summary Rollforward'!$B12) -> 30000 | CM12: =-SUMIFS('Jul25 Dep'!J:J,'Jul25 Dep'!F:F,'Summary Rollforward'!$B12) -> 0 | CN12: =SUMIFS('Contract Data'!IR:IR,'Contract Data'!$C:$C,'Summary Rollforward'!$B12) -> 23250 | CP12: =+CG12+CL12+CM12 -> 90000 | CQ12: =+CR12-CP12 -> -31875 | CR12: =+CI12+CK12+CM12+CL12 -> 58125 | CT12: =CW12-CU12 -> 24750 | CU12: =SUMIFS('Aug 25 Inv'!H:H,'Aug 25 Inv'!E:E,'Summary Rollforward'!$B12) -> 30000 | CV12: =-SUMIFS('Aug25 Dep'!J:J,'Aug25 Dep'!F:F,'Summary Rollforward'!$B12) -> -30000 | CW12: =SUMIFS('Contract Data'!IS:IS,'Contract Data'!$C:$C,'Summary Rollforward'!$B12) -> 54750 | CY12: =+CP12+CU12+CV12 -> 90000 | CZ12: =+DA12-CY12 -> -7125 | DA12: =+CR12+CT12+CV12+CU12 -> 82875 | DC12: =DF12-DD12 -> 59250 | DD12: =SUMIFS('Sep 25 Inv'!H:H,'Sep 25 Inv'!E:E,'Summary Rollforward'!$B12) -> 30000 | DE12: =-SUMIFS('Sep25 Dep'!J:J,'Sep25 Dep'!F:F,'Summary Rollforward'!$B12) -> -60000 | DF12: =SUMIFS('Contract Data'!IT:IT,'Contract Data'!$C:$C,'Summary Rollforward'!$B12) -> 89250 | DH12: =+CY12+DD12+DE12 -> 60000 | DI12: =+DJ12-DH12 -> 52125 | DJ12: =+DA12+DC12+DE12+DD12 -> 112125 | DL12: =DO12-DM12 -> 89250 | DM12: =SUMIFS('Oct 25 Inv'!H:H,'Oct 25 Inv'!E:E,'Summary Rollforward'!$B12) -> 0 | DN12: =-SUMIFS('Oct25 Dep'!J:J,'Oct25 Dep'!F:F,'Summary Rollforward'!$B12) -> -30000 | DO12: =SUMIFS('Contract Data'!IU:IU,'Contract Data'!$C:$C,'Summary Rollforward'!$B12) -> 89250 | DQ12: =+DH12+DM12+DN12 -> 30000 | DR12: =+DS12-DQ12 -> 141375 | DS12: =+DJ12+DL12+DN12+DM12 -> 171375 | DU12: =DX12-DV12 -> 71500 | DV12: =SUMIFS('Nov 25 Inv'!H:H,'Nov 25 Inv'!E:E,'Summary Rollforward'!$B12) -> 0 | DW12: =-SUMIFS('Nov25 Dep'!J:J,'Nov25 Dep'!F:F,'Summary Rollforward'!$B12) -> -30000 | DX12: =SUMIFS('Contract Data'!IV:IV,'Contract Data'!$C:$C,'Summary Rollforward'!$B12) -> 71500 | DZ12: =+DQ12+DV12+DW12 -> 0 | EA12: =+EB12-DZ12 -> 212875 | EB12: =+DS12+DU12+DW12+DV12 -> 212875 | ED12: =EG12-EE12 -> 71500 | EE12: =SUMIFS('Dec 25 Inv'!H:H,'Dec 25 Inv'!E:E,'Summary Rollforward'!$B12) -> 0 | EF12: =-SUMIFS('Dec25 Dep'!I:I,'Dec25 Dep'!F:F,'Summary Rollforward'!$B12) -> 0 | EG12: =SUMIFS('Contract Data'!IW:IW,'Contract Data'!$C:$C,'Summary Rollforward'!$B12) -> 71500 | EI12: =+DZ12+EE12+EF12 -> 0 | EJ12: =+EK12-EI12 -> 284375 | EK12: =+EB12+ED12+EF12+EE12 -> 284375
B13: Café Rio | C13: Freeman Spogoli | AD13: =+'AR Calculation - Service'!AQ36-AE13 -> 0 | AE13: =+'Dec Invoicing'!I8 -> 27530 | AI13: =+'Dec 31'!G7 -> 27530 | AJ13: =+AK13-AI13 -> 0 | AK13: =+AB13+AD13+AG13+AF13+AE13 -> 27530 | AM13: 0 | AN13: =+'Dec Invoicing'!Q8 -> 0 | AO13: =+'AR Calculation - Service'!AR35 -> -27530 | AQ13: =+AI13+AN13+AO13 -> 0 | AR13: =+AS13-AQ13 -> 0 | AS13: =+AK13+AM13+AO13+AN13 -> 0 | AU13: 0 | AV13: =+'Dec Invoicing'!Y8 -> 0 | AW13: 0 | AY13: =+AQ13+AV13+AW13 -> 0 | AZ13: =+BA13-AY13 -> 0 | BA13: =+AS13+AU13+AW13+AV13 -> 0 | BC13: 0 | BD13: =+'Dec Invoicing'!AG8 -> 0 | BG13: =+AY13+BD13+BE13 -> 0 | BH13: =+BI13-BG13 -> 0 | BI13: =+BA13+BC13+BE13+BD13 -> 0 | BK13: =+'AR Calculation - Service'!AU36-'Summary Rollforward'!BL13 -> 34673 | BL13: 0 | BO13: =+BG13+BL13+BM13 -> 0 | BP13: =+BQ13-BO13 -> 34673 | BQ13: =+BI13+BK13+BM13+BL13 -> 34673 | BS13: =BV13-BT13 -> -34673 | BT13: 34673 | BU13: 0 | BV13: =SUMIFS('Contract Data'!IP:IP,'Contract Data'!C:C,'Summary Rollforward'!B13) -> 0 | BX13: =+BO13+BT13+BU13 -> 34673 | BY13: =+BZ13-BX13 -> 0 | BZ13: =+BQ13+BS13+BU13+BT13 -> 34673 | CB13: =CE13-CC13 -> 0 | CC13: =SUMIFS('June 25 Inv'!G:G,'June 25 Inv'!D:D,'Summary Rollforward'!$B13) -> 0 | CD13: =-SUMIFS('Jun25 Dep'!I:I,'Jun25 Dep'!F:F,'Summary Rollforward'!$B13) -> -34673 | CE13: =SUMIFS('Contract Data'!IQ:IQ,'Contract Data'!$C:$C,'Summary Rollforward'!$B13) -> 0 | CG13: =+BX13+CC13+CD13 -> 0 | CH13: =+CI13-CG13 -> 0 | CI13: =+BZ13+CB13+CD13+CC13 -> 0 | CK13: =CN13-CL13 -> 0 | CL13: =SUMIFS('Jul 25 Inv'!H:H,'Jul 25 Inv'!E:E,'Summary Rollforward'!$B13) -> 0 | CM13: =-SUMIFS('Jul25 Dep'!J:J,'Jul25 Dep'!F:F,'Summary Rollforward'!$B13) -> 0 | CN13: =SUMIFS('Contract Data'!IR:IR,'Contract Data'!$C:$C,'Summary Rollforward'!$B13) -> 0 | CP13: =+CG13+CL13+CM13 -> 0 | CQ13: =+CR13-CP13 -> 0 | CR13: =+CI13+CK13+CM13+CL13 -> 0 | CT13: =CW13-CU13 -> 0 | CU13: =SUMIFS('Aug 25 Inv'!H:H,'Aug 25 Inv'!E:E,'Summary Rollforward'!$B13) -> 0 | CV13: =-SUMIFS('Aug25 Dep'!J:J,'Aug25 Dep'!F:F,'Summary Rollforward'!$B13) -> 0 | CW13: =SUMIFS('Contract Data'!IS:IS,'Contract Data'!$C:$C,'Summary Rollforward'!$B13) -> 0 | CY13: =+CP13+CU13+CV13 -> 0 | CZ13: =+DA13-CY13 -> 0 | DA13: =+CR13+CT13+CV13+CU13 -> 0 | DC13: =DF13-DD13 -> 0 | DD13: =SUMIFS('Sep 25 Inv'!H:H,'Sep 25 Inv'!E:E,'Summary Rollforward'!$B13) -> 0 | DE13: =-SUMIFS('Sep25 Dep'!J:J,'Sep25 Dep'!F:F,'Summary Rollforward'!$B13) -> 0 | DF13: =SUMIFS('Contract Data'!IT:IT,'Contract Data'!$C:$C,'Summary Rollforward'!$B13) -> 0 | DH13: =+CY13+DD13+DE13 -> 0 | DI13: =+DJ13-DH13 -> 0 | DJ13: =+DA13+DC13+DE13+DD13 -> 0 | DL13: =DO13-DM13 -> 0 | DM13: =SUMIFS('Oct 25 Inv'!H:H,'Oct 25 Inv'!E:E,'Summary Rollforward'!$B13) -> 0 | DN13: =-SUMIFS('Oct25 Dep'!J:J,'Oct25 Dep'!F:F,'Summary Rollforward'!$B13) -> 0 | DO13: =SUMIFS('Contract Data'!IU:IU,'Contract Data'!$C:$C,'Summary Rollforward'!$B13) -> 0 | DQ13: =+DH13+DM13+DN13 -> 0 | DR13: =+DS13-DQ13 -> 0 | DS13: =+DJ13+DL13+DN13+DM13 -> 0 | DU13: =DX13-DV13 -> 13215.333 | DV13: =SUMIFS('Nov 25 Inv'!H:H,'Nov 25 Inv'!E:E,'Summary Rollforward'!$B13) -> 0 | DW13: =-SUMIFS('Nov25 Dep'!J:J,'Nov25 Dep'!F:F,'Summary Rollforward'!$B13) -> 0 | DX13: =SUMIFS('Contract Data'!IV:IV,'Contract Data'!$C:$C,'Summary Rollforward'!$B13) -> 13215.333 | DZ13: =+DQ13+DV13+DW13 -> 0 | EA13: =+EB13-DZ13 -> 13215.333 | EB13: =+DS13+DU13+DW13+DV13 -> 13215.333 | ED13: =EG13-EE13 -> 0 | EE13: =SUMIFS('Dec 25 Inv'!H:H,'Dec 25 Inv'!E:E,'Summary Rollforward'!$B13) -> 0 | EF13: =-SUMIFS('Dec25 Dep'!I:I,'Dec25 Dep'!F:F,'Summary Rollforward'!$B13) -> 0 | EG13: =SUMIFS('Contract Data'!IW:IW,'Contract Data'!$C:$C,'Summary Rollforward'!$B13) -> 0 | EI13: =+DZ13+EE13+EF13 -> 0 | EJ13: =+EK13-EI13 -> 13215.333 | EK13: =+EB13+ED13+EF13+EE13 -> 13215.333
B14: California Fish Grill | C14: KarpReilly | CB14: =CE14-CC14 -> -1545.83 | CC14: =SUMIFS('June 25 Inv'!G:G,'June 25 Inv'!D:D,'Summary Rollforward'!$B14) -> 22083.33 | CD14: =-SUMIFS('Jun25 Dep'!I:I,'Jun25 Dep'!F:F,'Summary Rollforward'!$B14) -> 0 | CE14: =SUMIFS('Contract Data'!IQ:IQ,'Contract Data'!$C:$C,'Summary Rollforward'!$B14) -> 20537.5 | CG14: =+BX14+CC14+CD14 -> 22083.33 | CH14: =+CI14-CG14 -> -1545.83 | CI14: =+BZ14+CB14+CD14+CC14 -> 20537.5 | CK14: =CN14-CL14 -> 18991.67 | CL14: =SUMIFS('Jul 25 Inv'!H:H,'Jul 25 Inv'!E:E,'Summary Rollforward'!$B14) -> 22083.33 | CM14: =-SUMIFS('Jul25 Dep'!J:J,'Jul25 Dep'!F:F,'Summary Rollforward'!$B14) -> 0 | CN14: =SUMIFS('Contract Data'!IR:IR,'Contract Data'!$C:$C,'Summary Rollforward'!$B14) -> 41075 | CP14: =+CG14+CL14+CM14 -> 44166.66 | CQ14: =+CR14-CP14 -> 17445.84 | CR14: =+CI14+CK14+CM14+CL14 -> 61612.5 | CT14: =CW14-CU14 -> 18991.67 | CU14: =SUMIFS('Aug 25 Inv'!H:H,'Aug 25 Inv'!E:E,'Summary Rollforward'!$B14) -> 22083.33 | CV14: =-SUMIFS('Aug25 Dep'!J:J,'Aug25 Dep'!F:F,'Summary Rollforward'!$B14) -> -22083.33 | CW14: =SUMIFS('Contract Data'!IS:IS,'Contract Data'!$C:$C,'Summary Rollforward'!$B14) -> 41075 | CY14: =+CP14+CU14+CV14 -> 44166.66 | CZ14: =+DA14-CY14 -> 36437.51 | DA14: =+CR14+CT14+CV14+CU14 -> 80604.17 | DC14: =DF14-DD14 -> 35220.72 | DD14: =SUMIFS('Sep 25 Inv'!H:H,'Sep 25 Inv'!E:E,'Summary Rollforward'!$B14) -> 22083.33 | DE14: =-SUMIFS('Sep25 Dep'!J:J,'Sep25 Dep'!F:F,'Summary Rollforward'!$B14) -> -44166.66 | DF14: =SUMIFS('Contract Data'!IT:IT,'Contract Data'!$C:$C,'Summary Rollforward'!$B14) -> 57304.05 | DH14: =+CY14+DD14+DE14 -> 22083.33 | DI14: =+DJ14-DH14 -> 71658.23 | DJ14: =+DA14+DC14+DE14+DD14 -> 93741.56 | DL14: =DO14-DM14 -> 51449.77 | DM14: =SUMIFS('Oct 25 Inv'!H:H,'Oct 25 Inv'!E:E,'Summary Rollforward'!$B14) -> 22083.33 | DN14: =-SUMIFS('Oct25 Dep'!J:J,'Oct25 Dep'!F:F,'Summary Rollforward'!$B14) -> -22083.33 | DO14: =SUMIFS('Contract Data'!IU:IU,'Contract Data'!$C:$C,'Summary Rollforward'!$B14) -> 73533.1 | DQ14: =+DH14+DM14+DN14 -> 22083.33 | DR14: =+DS14-DQ14 -> 123108 | DS14: =+DJ14+DL14+DN14+DM14 -> 145191.33 | DU14: =DX14-DV14 -> 22916.67 | DV14: =SUMIFS('Nov 25 Inv'!H:H,'Nov 25 Inv'!E:E,'Summary Rollforward'!$B14) -> 22083.33 | DW14: =-SUMIFS('Nov25 Dep'!J:J,'Nov25 Dep'!F:F,'Summary Rollforward'!$B14) -> 0 | DX14: =SUMIFS('Contract Data'!IV:IV,'Contract Data'!$C:$C,'Summary Rollforward'!$B14) -> 45000 | DZ14: =+DQ14+DV14+DW14 -> 44166.66 | EA14: =+EB14-DZ14 -> 146024.67 | EB14: =+DS14+DU14+DW14+DV14 -> 190191.33 | ED14: =EG14-EE14 -> 7916.67 | EE14: =SUMIFS('Dec 25 Inv'!H:H,'Dec 25 Inv'!E:E,'Summary Rollforward'!$B14) -> 24197.49 | EF14: =-SUMIFS('Dec25 Dep'!I:I,'Dec25 Dep'!F:F,'Summary Rollforward'!$B14) -> -44166.66 | EG14: =SUMIFS('Contract Data'!IW:IW,'Contract Data'!$C:$C,'Summary Rollforward'!$B14) -> 32114.16 | EI14: =+DZ14+EE14+EF14 -> 24197.49 | EJ14: =+EK14-EI14 -> 153941.34 | EK14: =+EB14+ED14+EF14+EE14 -> 178138.83
B15: CAM | C15: Cross Rapids | E15: 0 | F15: =+G15-E15 -> 57750 | G15: =+'AR Calculation - Service'!AM41 -> 57750 | I15: =+'AR Calculation - Service'!AN40 -> 59675 | M15: =+N15-L15 -> 117425 | N15: =+G15+I15+J15 -> 117425 | P15: 36575 | S15: =+'Oct 31'!G7 -> 77000 | T15: =+U15-S15 -> 77000 | U15: =+N15+P15+Q15 -> 154000 | W15: 0 | X15: =+'Nov Collections'!I59 -> -77000 | Z15: =+'Nov 30'!G7 -> 77000 | AA15: =+AB15-Z15 -> 0 | AB15: =+U15+W15+X15 -> 77000 | AD15: 0 | AG15: ='AR Calculation - Service'!AQ39 -> -77000 | AI15: =+'Nov 30'!K7 -> 0 | AJ15: =+AK15-AI15 -> -2.910383e-11 | AK15: =+AB15+AD15+AG15+AF15+AE15 -> -2.910383e-11 | AM15: 0 | AO15: =-'Oct Collections'!AF12-'Oct Collections'!AF13 -> 0 | AQ15: =+AI15+AN15+AO15 -> 0 | AR15: =+AS15-AQ15 -> -2.910383e-11 | AS15: =+AK15+AM15+AO15+AN15 -> -2.910383e-11 | AU15: 0 | AW15: =-'Oct Collections'!AN12-'Oct Collections'!AN13 -> 0 | AY15: =+AQ15+AV15+AW15 -> 0 | AZ15: =+BA15-AY15 -> -2.910383e-11 | BA15: =+AS15+AU15+AW15+AV15 -> -2.910383e-11 | BC15: 0 | BG15: =+AY15+BD15+BE15 -> 0 | BH15: =+BI15-BG15 -> -2.910383e-11 | BI15: =+BA15+BC15+BE15+BD15 -> -2.910383e-11 | BO15: =+BG15+BL15+BM15 -> 0 | BP15: =+BQ15-BO15 -> -2.910383e-11 | BQ15: =+BI15+BK15+BM15+BL15 -> -2.910383e-11 | BS15: =BV15-BT15 -> 0 | BT15: 0 | BU15: 0 | BV15: =SUMIFS('Contract Data'!IP:IP,'Contract Data'!C:C,'Summary Rollforward'!B15) -> 0 | BX15: =+BO15+BT15+BU15 -> 0 | BY15: =+BZ15-BX15 -> -2.910383e-11 | BZ15: =+BQ15+BS15+BU15+BT15 -> -2.910383e-11 | CB15: =CE15-CC15 -> 0 | CC15: =SUMIFS('June 25 Inv'!G:G,'June 25 Inv'!D:D,'Summary Rollforward'!$B15) -> 0 | CD15: =-SUMIFS('Jun25 Dep'!I:I,'Jun25 Dep'!F:F,'Summary Rollforward'!$B15) -> 0 | CE15: =SUMIFS('Contract Data'!IQ:IQ,'Contract Data'!$C:$C,'Summary Rollforward'!$B15) -> 0 | CG15: =+BX15+CC15+CD15 -> 0 | CH15: =+CI15-CG15 -> -2.910383e-11 | CI15: =+BZ15+CB15+CD15+CC15 -> -2.910383e-11 | CK15: =CN15-CL15 -> 0 | CL15: =SUMIFS('Jul 25 Inv'!H:H,'Jul 25 Inv'!E:E,'Summary Rollforward'!$B15) -> 0 | CM15: =-SUMIFS('Jul25 Dep'!J:J,'Jul25 Dep'!F:F,'Summary Rollforward'!$B15) -> 0 | CN15: =SUMIFS('Contract Data'!IR:IR,'Contract Data'!$C:$C,'Summary Rollforward'!$B15) -> 0 | CP15: =+CG15+CL15+CM15 -> 0 | CQ15: =+CR15-CP15 -> -2.910383e-11 | CR15: =+CI15+CK15+CM15+CL15 -> -2.910383e-11 | CT15: =CW15-CU15 -> 0 | CU15: =SUMIFS('Aug 25 Inv'!H:H,'Aug 25 Inv'!E:E,'Summary Rollforward'!$B15) -> 0 | CV15: =-SUMIFS('Aug25 Dep'!J:J,'Aug25 Dep'!F:F,'Summary Rollforward'!$B15) -> 0 | CW15: =SUMIFS('Contract Data'!IS:IS,'Contract Data'!$C:$C,'Summary Rollforward'!$B15) -> 0 | CY15: =+CP15+CU15+CV15 -> 0 | CZ15: =+DA15-CY15 -> -2.910383e-11 | DA15: =+CR15+CT15+CV15+CU15 -> -2.910383e-11 | DC15: =DF15-DD15 -> 0 | DD15: =SUMIFS('Sep 25 Inv'!H:H,'Sep 25 Inv'!E:E,'Summary Rollforward'!$B15) -> 0 | DE15: =-SUMIFS('Sep25 Dep'!J:J,'Sep25 Dep'!F:F,'Summary Rollforward'!$B15) -> 0 | DF15: =SUMIFS('Contract Data'!IT:IT,'Contract Data'!$C:$C,'Summary Rollforward'!$B15) -> 0 | DH15: =+CY15+DD15+DE15 -> 0 | DI15: =+DJ15-DH15 -> -2.910383e-11 | DJ15: =+DA15+DC15+DE15+DD15 -> -2.910383e-11 | DL15: =DO15-DM15 -> 0 | DM15: =SUMIFS('Oct 25 Inv'!H:H,'Oct 25 Inv'!E:E,'Summary Rollforward'!$B15) -> 0 | DN15: =-SUMIFS('Oct25 Dep'!J:J,'Oct25 Dep'!F:F,'Summary Rollforward'!$B15) -> 0 | DO15: =SUMIFS('Contract Data'!IU:IU,'Contract Data'!$C:$C,'Summary Rollforward'!$B15) -> 0 | DQ15: =+DH15+DM15+DN15 -> 0 | DR15: =+DS15-DQ15 -> -2.910383e-11 | DS15: =+DJ15+DL15+DN15+DM15 -> -2.910383e-11 | DU15: =DX15-DV15 -> 0 | DV15: =SUMIFS('Nov 25 Inv'!H:H,'Nov 25 Inv'!E:E,'Summary Rollforward'!$B15) -> 0 | DW15: =-SUMIFS('Nov25 Dep'!J:J,'Nov25 Dep'!F:F,'Summary Rollforward'!$B15) -> 0 | DX15: =SUMIFS('Contract Data'!IV:IV,'Contract Data'!$C:$C,'Summary Rollforward'!$B15) -> 0 | DZ15: =+DQ15+DV15+DW15 -> 0 | EA15: =+EB15-DZ15 -> -2.910383e-11 | EB15: =+DS15+DU15+DW15+DV15 -> -2.910383e-11 | ED15: =EG15-EE15 -> 2.910383e-11 | EE15: =SUMIFS('Dec 25 Inv'!H:H,'Dec 25 Inv'!E:E,'Summary Rollforward'!$B15) -> 0 | EF15: =-SUMIFS('Dec25 Dep'!I:I,'Dec25 Dep'!F:F,'Summary Rollforward'!$B15) -> 0 | EG15: =-EB15 -> 2.910383e-11 | EI15: =+DZ15+EE15+EF15 -> 0 | EJ15: =+EK15-EI15 -> 0 | EK15: =+EB15+ED15+EF15+EE15 -> 0
B16: Capsa Healthcare | C16: LLCP | ED16: =EG16-EE16 -> 0 | EE16: =SUMIFS('Dec 25 Inv'!H:H,'Dec 25 Inv'!E:E,'Summary Rollforward'!$B16) -> 30000 | EF16: =-SUMIFS('Dec25 Dep'!I:I,'Dec25 Dep'!F:F,'Summary Rollforward'!$B16) -> 0 | EG16: =SUMIFS('Contract Data'!IW:IW,'Contract Data'!$C:$C,'Summary Rollforward'!$B16) -> 30000 | EI16: =+DZ16+EE16+EF16 -> 30000 | EJ16: =+EK16-EI16 -> 0 | EK16: =+EB16+ED16+EF16+EE16 -> 30000
B17: Cascade | C17: Trive | BK17: =+'AR Calculation - Service'!AU381-'Summary Rollforward'!BL17 -> 65875 | BL17: 0 | BO17: =+BG17+BL17+BM17 -> 0 | BP17: =+BQ17-BO17 -> 65875 | BQ17: =+BI17+BK17+BM17+BL17 -> 65875 | BS17: =BV17-BT17 -> 65875 | BT17: 0 | BU17: 0 | BV17: =SUMIFS('Contract Data'!IP:IP,'Contract Data'!C:C,'Summary Rollforward'!B17) -> 65875 | BX17: =+BO17+BT17+BU17 -> 0 | BY17: =+BZ17-BX17 -> 131750 | BZ17: =+BQ17+BS17+BU17+BT17 -> 131750 | CB17: =CE17-CC17 -> 65875 | CC17: =SUMIFS('June 25 Inv'!G:G,'June 25 Inv'!D:D,'Summary Rollforward'!$B17) -> 0 | CD17: =-SUMIFS('Jun25 Dep'!I:I,'Jun25 Dep'!F:F,'Summary Rollforward'!$B17) -> 0 | CE17: =SUMIFS('Contract Data'!IQ:IQ,'Contract Data'!$C:$C,'Summary Rollforward'!$B17) -> 65875 | CG17: =+BX17+CC17+CD17 -> 0 | CH17: =+CI17-CG17 -> 197625 | CI17: =+BZ17+CB17+CD17+CC17 -> 197625 | CK17: =CN17-CL17 -> 65875 | CL17: =SUMIFS('Jul 25 Inv'!H:H,'Jul 25 Inv'!E:E,'Summary Rollforward'!$B17) -> 0 | CM17: =-SUMIFS('Jul25 Dep'!J:J,'Jul25 Dep'!F:F,'Summary Rollforward'!$B17) -> 0 | CN17: =SUMIFS('Contract Data'!IR:IR,'Contract Data'!$C:$C,'Summary Rollforward'!$B17) -> 65875 | CP17: =+CG17+CL17+CM17 -> 0 | CQ17: =+CR17-CP17 -> 263500 | CR17: =+CI17+CK17+CM17+CL17 -> 263500 | CT17: =CW17-CU17 -> 65875 | CU17: =SUMIFS('Aug 25 Inv'!H:H,'Aug 25 Inv'!E:E,'Summary Rollforward'!$B17) -> 0 | CV17: =-SUMIFS('Aug25 Dep'!J:J,'Aug25 Dep'!F:F,'Summary Rollforward'!$B17) -> 0 | CW17: =SUMIFS('Contract Data'!IS:IS,'Contract Data'!$C:$C,'Summary Rollforward'!$B17) -> 65875 | CY17: =+CP17+CU17+CV17 -> 0 | CZ17: =+DA17-CY17 -> 329375 | DA17: =+CR17+CT17+CV17+CU17 -> 329375 | DC17: =DF17-DD17 -> -53125 | DD17: =SUMIFS('Sep 25 Inv'!H:H,'Sep 25 Inv'!E:E,'Summary Rollforward'!$B17) -> 85000 | DE17: =-SUMIFS('Sep25 Dep'!J:J,'Sep25 Dep'!F:F,'Summary Rollforward'!$B17) -> 0 | DF17: =SUMIFS('Contract Data'!IT:IT,'Contract Data'!$C:$C,'Summary Rollforward'!$B17) -> 31875 | DH17: =+CY17+DD17+DE17 -> 85000 | DI17: =+DJ17-DH17 -> 276250 | DJ17: =+DA17+DC17+DE17+DD17 -> 361250 | DL17: =DO17-DM17 -> -53125 | DM17: =SUMIFS('Oct 25 Inv'!H:H,'Oct 25 Inv'!E:E,'Summary Rollforward'!$B17) -> 85000 | DN17: =-SUMIFS('Oct25 Dep'!J:J,'Oct25 Dep'!F:F,'Summary Rollforward'!$B17) -> -85000 | DO17: =SUMIFS('Contract Data'!IU:IU,'Contract Data'!$C:$C,'Summary Rollforward'!$B17) -> 31875 | DQ17: =+DH17+DM17+DN17 -> 85000 | DR17: =+DS17-DQ17 -> 223125 | DS17: =+DJ17+DL17+DN17+DM17 -> 308125 | DU17: =DX17-DV17 -> -53125 | DV17: =SUMIFS('Nov 25 Inv'!H:H,'Nov 25 Inv'!E:E,'Summary Rollforward'!$B17) -> 85000 | DW17: =-SUMIFS('Nov25 Dep'!J:J,'Nov25 Dep'!F:F,'Summary Rollforward'!$B17) -> -85000 | DX17: =SUMIFS('Contract Data'!IV:IV,'Contract Data'!$C:$C,'Summary Rollforward'!$B17) -> 31875 | DZ17: =+DQ17+DV17+DW17 -> 85000 | EA17: =+EB17-DZ17 -> 170000 | EB17: =+DS17+DU17+DW17+DV17 -> 255000 | ED17: =EG17-EE17 -> 0 | EE17: =SUMIFS('Dec 25 Inv'!H:H,'Dec 25 Inv'!E:E,'Summary Rollforward'!$B17) -> 0 | EF17: =-SUMIFS('Dec25 Dep'!I:I,'Dec25 Dep'!F:F,'Summary Rollforward'!$B17) -> -85000 | EG17: =SUMIFS('Contract Data'!IW:IW,'Contract Data'!$C:$C,'Summary Rollforward'!$B17) -> 0 | EI17: =+DZ17+EE17+EF17 -> 0 | EJ17: =+EK17-EI17 -> 170000 | EK17: =+EB17+ED17+EF17+EE17 -> 170000
B18: Christianbook, LLC | C18: Nonantum Capital Partners | F18: =+G18-E18 -> 31250 | G18: =+'AR Calculation - Service'!AM286 -> 31250 | I18: =+'AR Calculation - Service'!AN285 -> 58125 | L18: =+'Sep 30'!G8 -> 75000 | M18: =+N18-L18 -> 14375 | N18: =+G18+I18+J18 -> 89375 | P18: 58125 | S18: =+'Oct 31'!G8 -> 150000 | T18: =+U18-S18 -> -2500 | U18: =+N18+P18+Q18 -> 147500 | W18: =+'AR Calculation - Service'!AP285 -> 58125 | X18: =+'Nov Collections'!I9+'Nov Collections'!I24 -> -150000 | Z18: =+'Nov 30'!G8 -> 75000 | AA18: =+AB18-Z18 -> -19375 | AB18: =+U18+W18+X18 -> 55625 | AD18: =+'AR Calculation - Service'!AQ285-AE18 -> 625 | AE18: =+'Dec Invoicing'!I9 -> 75000 | AG18: =+'AR Calculation - Service'!AQ284 -> -75000 | AI18: =+'Dec 31'!G8 -> 75000 | AJ18: =+AK18-AI18 -> -18750 | AK18: =+AB18+AD18+AG18+AF18+AE18 -> 56250 | AM18: =+'AR Calculation - Service'!AR285-'Summary Rollforward'!AN18 -> -12500 | AN18: =+'Jan Invoicing'!G7 -> 75000 | AO18: =+'AR Calculation - Service'!AR284 -> -75000 | AQ18: =+AI18+AN18+AO18 -> 75000 | AR18: =+AS18-AQ18 -> -31250 | AS18: =+AK18+AM18+AO18+AN18 -> 43750 | AU18: =+'AR Calculation - Service'!AS285-'Summary Rollforward'!AV18 -> 31250 | AV18: =+'Jan Invoicing'!O7 -> 0 | AW18: =+'AR Calculation - Service'!BB284 -> 0 | AY18: =+AQ18+AV18+AW18 -> 75000 | AZ18: =+BA18-AY18 -> 0 | BA18: =+AS18+AU18+AW18+AV18 -> 75000 | BC18: 0 | BD18: =+'Jan Invoicing'!W7 -> 0 | BE18: =+'AR Calculation - Service'!AT284 -> -75000 | BG18: =+AY18+BD18+BE18 -> 0 | BH18: =+BI18-BG18 -> 0 | BI18: =+BA18+BC18+BE18+BD18 -> 0 | BM18: =+'AR Calculation - Service'!BB284 -> 0 | BO18: =+BG18+BL18+BM18 -> 0 | BP18: =+BQ18-BO18 -> 0 | BQ18: =+BI18+BK18+BM18+BL18 -> 0 | BS18: =BV18-BT18 -> 0 | BT18: 0 | BU18: 0 | BV18: =SUMIFS('Contract Data'!IP:IP,'Contract Data'!C:C,'Summary Rollforward'!B18) -> 0 | BX18: =+BO18+BT18+BU18 -> 0 | BY18: =+BZ18-BX18 -> 0 | BZ18: =+BQ18+BS18+BU18+BT18 -> 0 | CB18: =CE18-CC18 -> 0 | CC18: =SUMIFS('June 25 Inv'!G:G,'June 25 Inv'!D:D,'Summary Rollforward'!$B18) -> 0 | CD18: =-SUMIFS('Jun25 Dep'!I:I,'Jun25 Dep'!F:F,'Summary Rollforward'!$B18) -> 0 | CE18: =SUMIFS('Contract Data'!IQ:IQ,'Contract Data'!$C:$C,'Summary Rollforward'!$B18) -> 0 | CG18: =+BX18+CC18+CD18 -> 0 | CH18: =+CI18-CG18 -> 0 | CI18: =+BZ18+CB18+CD18+CC18 -> 0 | CK18: =CN18-CL18 -> 0 | CL18: =SUMIFS('Jul 25 Inv'!H:H,'Jul 25 Inv'!E:E,'Summary Rollforward'!$B18) -> 0 | CM18: =-SUMIFS('Jul25 Dep'!J:J,'Jul25 Dep'!F:F,'Summary Rollforward'!$B18) -> 0 | CN18: =SUMIFS('Contract Data'!IR:IR,'Contract Data'!$C:$C,'Summary Rollforward'!$B18) -> 0 | CP18: =+CG18+CL18+CM18 -> 0 | CQ18: =+CR18-CP18 -> 0 | CR18: =+CI18+CK18+CM18+CL18 -> 0 | CT18: =CW18-CU18 -> 0 | CU18: =SUMIFS('Aug 25 Inv'!H:H,'Aug 25 Inv'!E:E,'Summary Rollforward'!$B18) -> 0 | CV18: =-SUMIFS('Aug25 Dep'!J:J,'Aug25 Dep'!F:F,'Summary Rollforward'!$B18) -> 0 | CW18: =SUMIFS('Contract Data'!IS:IS,'Contract Data'!$C:$C,'Summary Rollforward'!$B18) -> 0 | CY18: =+CP18+CU18+CV18 -> 0 | CZ18: =+DA18-CY18 -> 0 | DA18: =+CR18+CT18+CV18+CU18 -> 0 | DC18: =DF18-DD18 -> 0 | DD18: =SUMIFS('Sep 25 Inv'!H:H,'Sep 25 Inv'!E:E,'Summary Rollforward'!$B18) -> 0 | DE18: =-SUMIFS('Sep25 Dep'!J:J,'Sep25 Dep'!F:F,'Summary Rollforward'!$B18) -> 0 | DF18: =SUMIFS('Contract Data'!IT:IT,'Contract Data'!$C:$C,'Summary Rollforward'!$B18) -> 0 | DH18: =+CY18+DD18+DE18 -> 0 | DI18: =+DJ18-DH18 -> 0 | DJ18: =+DA18+DC18+DE18+DD18 -> 0 | DL18: =DO18-DM18 -> 0 | DM18: =SUMIFS('Oct 25 Inv'!H:H,'Oct 25 Inv'!E:E,'Summary Rollforward'!$B18) -> 0 | DN18: =-SUMIFS('Oct25 Dep'!J:J,'Oct25 Dep'!F:F,'Summary Rollforward'!$B18) -> 0 | DO18: =SUMIFS('Contract Data'!IU:IU,'Contract Data'!$C:$C,'Summary Rollforward'!$B18) -> 0 | DQ18: =+DH18+DM18+DN18 -> 0 | DR18: =+DS18-DQ18 -> 0 | DS18: =+DJ18+DL18+DN18+DM18 -> 0 | DU18: =DX18-DV18 -> 0 | DV18: =SUMIFS('Nov 25 Inv'!H:H,'Nov 25 Inv'!E:E,'Summary Rollforward'!$B18) -> 0 | DW18: =-SUMIFS('Nov25 Dep'!J:J,'Nov25 Dep'!F:F,'Summary Rollforward'!$B18) -> 0 | DX18: =SUMIFS('Contract Data'!IV:IV,'Contract Data'!$C:$C,'Summary Rollforward'!$B18) -> 0 | DZ18: =+DQ18+DV18+DW18 -> 0 | EA18: =+EB18-DZ18 -> 0 | EB18: =+DS18+DU18+DW18+DV18 -> 0 | ED18: =EG18-EE18 -> 0 | EE18: =SUMIFS('Dec 25 Inv'!H:H,'Dec 25 Inv'!E:E,'Summary Rollforward'!$B18) -> 0 | EF18: =-SUMIFS('Dec25 Dep'!I:I,'Dec25 Dep'!F:F,'Summary Rollforward'!$B18) -> 0 | EG18: =SUMIFS('Contract Data'!IW:IW,'Contract Data'!$C:$C,'Summary Rollforward'!$B18) -> 0 | EI18: =+DZ18+EE18+EF18 -> 0 | EJ18: =+EK18-EI18 -> 0 | EK18: =+EB18+ED18+EF18+EE18 -> 0
B19: Covercraft | C19: Century Park | E19: 0 | F19: =+G19-E19 -> 58367 | G19: =+'AR Calculation - Service'!AM57 -> 58367 | M19: =+N19-L19 -> 58367 | N19: =+G19+I19+J19 -> 58367 | S19: 0 | T19: =+U19-S19 -> 58367 | U19: =+N19+P19+Q19 -> 58367 | W19: 0 | Z19: 0 | AA19: =+AB19-Z19 -> 58367 | AB19: =+U19+W19+X19 -> 58367 | AD19: 0 | AF19: -58367 | AI19: 0 | AJ19: =+AK19-AI19 -> -1.1641532e-10 | AK19: =+AB19+AD19+AG19+AF19+AE19 -> -1.1641532e-10 | AM19: 0 | AO19: =-'Oct Collections'!AF14-'Oct Collections'!AF15 -> 0 | AQ19: =+AI19+AN19+AO19 -> 0 | AR19: =+AS19-AQ19 -> -1.1641532e-10 | AS19: =+AK19+AM19+AO19+AN19 -> -1.1641532e-10 | AU19: 0 | AW19: =-'Oct Collections'!AN14-'Oct Collections'!AN15 -> 0 | AY19: =+AQ19+AV19+AW19 -> 0 | AZ19: =+BA19-AY19 -> -1.1641532e-10 | BA19: =+AS19+AU19+AW19+AV19 -> -1.1641532e-10 | BC19: 0 | BG19: =+AY19+BD19+BE19 -> 0 | BH19: =+BI19-BG19 -> -1.1641532e-10 | BI19: =+BA19+BC19+BE19+BD19 -> -1.1641532e-10 | BO19: =+BG19+BL19+BM19 -> 0 | BP19: =+BQ19-BO19 -> -1.1641532e-10 | BQ19: =+BI19+BK19+BM19+BL19 -> -1.1641532e-10 | BS19: =BV19-BT19 -> 0 | BT19: 0 | BU19: 0 | BV19: =SUMIFS('Contract Data'!IP:IP,'Contract Data'!C:C,'Summary Rollforward'!B19) -> 0 | BX19: =+BO19+BT19+BU19 -> 0 | BY19: =+BZ19-BX19 -> -1.1641532e-10 | BZ19: =+BQ19+BS19+BU19+BT19 -> -1.1641532e-10 | CB19: =CE19-CC19 -> 0 | CC19: =SUMIFS('June 25 Inv'!G:G,'June 25 Inv'!D:D,'Summary Rollforward'!$B19) -> 0 | CD19: =-SUMIFS('Jun25 Dep'!I:I,'Jun25 Dep'!F:F,'Summary Rollforward'!$B19) -> 0 | CE19: =SUMIFS('Contract Data'!IQ:IQ,'Contract Data'!$C:$C,'Summary Rollforward'!$B19) -> 0 | CG19: =+BX19+CC19+CD19 -> 0 | CH19: =+CI19-CG19 -> -1.1641532e-10 | CI19: =+BZ19+CB19+CD19+CC19 -> -1.1641532e-10 | CK19: =CN19-CL19 -> 0 | CL19: =SUMIFS('Jul 25 Inv'!H:H,'Jul 25 Inv'!E:E,'Summary Rollforward'!$B19) -> 0 | CM19: =-SUMIFS('Jul25 Dep'!J:J,'Jul25 Dep'!F:F,'Summary Rollforward'!$B19) -> 0 | CN19: =SUMIFS('Contract Data'!IR:IR,'Contract Data'!$C:$C,'Summary Rollforward'!$B19) -> 0 | CP19: =+CG19+CL19+CM19 -> 0 | CQ19: =+CR19-CP19 -> -1.1641532e-10 | CR19: =+CI19+CK19+CM19+CL19 -> -1.1641532e-10 | CT19: =CW19-CU19 -> 0 | CU19: =SUMIFS('Aug 25 Inv'!H:H,'Aug 25 Inv'!E:E,'Summary Rollforward'!$B19) -> 0 | CV19: =-SUMIFS('Aug25 Dep'!J:J,'Aug25 Dep'!F:F,'Summary Rollforward'!$B19) -> 0 | CW19: =SUMIFS('Contract Data'!IS:IS,'Contract Data'!$C:$C,'Summary Rollforward'!$B19) -> 0 | CY19: =+CP19+CU19+CV19 -> 0 | CZ19: =+DA19-CY19 -> -1.1641532e-10 | DA19: =+CR19+CT19+CV19+CU19 -> -1.1641532e-10 | DC19: =DF19-DD19 -> 0 | DD19: =SUMIFS('Sep 25 Inv'!H:H,'Sep 25 Inv'!E:E,'Summary Rollforward'!$B19) -> 0 | DE19: =-SUMIFS('Sep25 Dep'!J:J,'Sep25 Dep'!F:F,'Summary Rollforward'!$B19) -> 0 | DF19: =SUMIFS('Contract Data'!IT:IT,'Contract Data'!$C:$C,'Summary Rollforward'!$B19) -> 0 | DH19: =+CY19+DD19+DE19 -> 0 | DI19: =+DJ19-DH19 -> -1.1641532e-10 | DJ19: =+DA19+DC19+DE19+DD19 -> -1.1641532e-10 | DL19: =DO19-DM19 -> 0 | DM19: =SUMIFS('Oct 25 Inv'!H:H,'Oct 25 Inv'!E:E,'Summary Rollforward'!$B19) -> 0 | DN19: =-SUMIFS('Oct25 Dep'!J:J,'Oct25 Dep'!F:F,'Summary Rollforward'!$B19) -> 0 | DO19: =SUMIFS('Contract Data'!IU:IU,'Contract Data'!$C:$C,'Summary Rollforward'!$B19) -> 0 | DQ19: =+DH19+DM19+DN19 -> 0 | DR19: =+DS19-DQ19 -> -1.1641532e-10 | DS19: =+DJ19+DL19+DN19+DM19 -> -1.1641532e-10 | DU19: =DX19-DV19 -> 0 | DV19: =SUMIFS('Nov 25 Inv'!H:H,'Nov 25 Inv'!E:E,'Summary Rollforward'!$B19) -> 0 | DW19: =-SUMIFS('Nov25 Dep'!J:J,'Nov25 Dep'!F:F,'Summary Rollforward'!$B19) -> 0 | DX19: =SUMIFS('Contract Data'!IV:IV,'Contract Data'!$C:$C,'Summary Rollforward'!$B19) -> 0 | DZ19: =+DQ19+DV19+DW19 -> 0 | EA19: =+EB19-DZ19 -> -1.1641532e-10 | EB19: =+DS19+DU19+DW19+DV19 -> -1.1641532e-10 | ED19: =EG19-EE19 -> 1.1641532e-10 | EE19: =SUMIFS('Dec 25 Inv'!H:H,'Dec 25 Inv'!E:E,'Summary Rollforward'!$B19) -> 0 | EF19: =-SUMIFS('Dec25 Dep'!I:I,'Dec25 Dep'!F:F,'Summary Rollforward'!$B19) -> 0 | EG19: =-EB19 -> 1.1641532e-10 | EI19: =+DZ19+EE19+EF19 -> 0 | EJ19: =+EK19-EI19 -> 0 | EK19: =+EB19+ED19+EF19+EE19 -> 0
B20: D&H United | C20: Windpoint | E20: =+'Aug 31'!G7 -> 201000 | F20: =+G20-E20 -> -117250 | G20: =+'AR Calculation - Service'!AM278 -> 83750 | I20: =+'AR Calculation - Service'!AN277 -> 51925 | L20: =+'Sep 30'!G9 -> 201000 | M20: =+N20-L20 -> -65325 | N20: =+G20+I20+J20 -> 135675 | P20: 51925 | Q20: =-'Oct Collections'!J10-'Oct Collections'!J11 -> -134000 | S20: =+'Oct 31'!G9 -> 134000 | T20: =+U20-S20 -> -80400 | U20: =+N20+P20+Q20 -> 53600 | W20: =+'AR Calculation - Service'!AP277 -> 51925 | X20: =+'Nov Collections'!I50 -> -67000 | Z20: =+'Nov 30'!G9 -> 134000 | AA20: =+AB20-Z20 -> -95475 | AB20: =+U20+W20+X20 -> 38525 | AD20: =+'AR Calculation - Service'!AQ277 -> 95475 | AG20: =+'AR Calculation - Service'!AQ276 -> -67000 | AI20: =+'Dec 31'!G9 -> 67000 | AJ20: =+AK20-AI20 -> 0 | AK20: =+AB20+AD20+AG20+AF20+AE20 -> 67000 | AM20: 0 | AO20: =-'Oct Collections'!AF15-'Oct Collections'!AF16 -> 0 | AQ20: =+AI20+AN20+AO20 -> 67000 | AR20: =+AS20-AQ20 -> 0 | AS20: =+AK20+AM20+AO20+AN20 -> 67000 | AU20: 0 | AW20: =-'Oct Collections'!AN15-'Oct Collections'!AN16 -> 0 | AY20: =+AQ20+AV20+AW20 -> 67000 | AZ20: =+BA20-AY20 -> 0 | BA20: =+AS20+AU20+AW20+AV20 -> 67000 | BC20: 0 | BG20: =+AY20+BD20+BE20 -> 67000 | BH20: =+BI20-BG20 -> 0 | BI20: =+BA20+BC20+BE20+BD20 -> 67000 | BM20: =+'AR Calculation - Service'!AU276 -> -67000 | BO20: =+BG20+BL20+BM20 -> 0 | BP20: =+BQ20-BO20 -> 0 | BQ20: =+BI20+BK20+BM20+BL20 -> 0 | BS20: =BV20-BT20 -> 0 | BT20: 0 | BU20: 0 | BV20: =SUMIFS('Contract Data'!IP:IP,'Contract Data'!C:C,'Summary Rollforward'!B20) -> 0 | BX20: =+BO20+BT20+BU20 -> 0 | BY20: =+BZ20-BX20 -> 0 | BZ20: =+BQ20+BS20+BU20+BT20 -> 0 | CB20: =CE20-CC20 -> 0 | CC20: =SUMIFS('June 25 Inv'!G:G,'June 25 Inv'!D:D,'Summary Rollforward'!$B20) -> 0 | CD20: =-SUMIFS('Jun25 Dep'!I:I,'Jun25 Dep'!F:F,'Summary Rollforward'!$B20) -> 0 | CE20: =SUMIFS('Contract Data'!IQ:IQ,'Contract Data'!$C:$C,'Summary Rollforward'!$B20) -> 0 | CG20: =+BX20+CC20+CD20 -> 0 | CH20: =+CI20-CG20 -> 0 | CI20: =+BZ20+CB20+CD20+CC20 -> 0 | CK20: =CN20-CL20 -> 0 | CL20: =SUMIFS('Jul 25 Inv'!H:H,'Jul 25 Inv'!E:E,'Summary Rollforward'!$B20) -> 0 | CM20: =-SUMIFS('Jul25 Dep'!J:J,'Jul25 Dep'!F:F,'Summary Rollforward'!$B20) -> 0 | CN20: =SUMIFS('Contract Data'!IR:IR,'Contract Data'!$C:$C,'Summary Rollforward'!$B20) -> 0 | CP20: =+CG20+CL20+CM20 -> 0 | CQ20: =+CR20-CP20 -> 0 | CR20: =+CI20+CK20+CM20+CL20 -> 0 | CT20: =CW20-CU20 -> 0 | CU20: =SUMIFS('Aug 25 Inv'!H:H,'Aug 25 Inv'!E:E,'Summary Rollforward'!$B20) -> 0 | CV20: =-SUMIFS('Aug25 Dep'!J:J,'Aug25 Dep'!F:F,'Summary Rollforward'!$B20) -> 0 | CW20: =SUMIFS('Contract Data'!IS:IS,'Contract Data'!$C:$C,'Summary Rollforward'!$B20) -> 0 | CY20: =+CP20+CU20+CV20 -> 0 | CZ20: =+DA20-CY20 -> 0 | DA20: =+CR20+CT20+CV20+CU20 -> 0 | DC20: =DF20-DD20 -> 0 | DD20: =SUMIFS('Sep 25 Inv'!H:H,'Sep 25 Inv'!E:E,'Summary Rollforward'!$B20) -> 0 | DE20: =-SUMIFS('Sep25 Dep'!J:J,'Sep25 Dep'!F:F,'Summary Rollforward'!$B20) -> 0 | DF20: =SUMIFS('Contract Data'!IT:IT,'Contract Data'!$C:$C,'Summary Rollforward'!$B20) -> 0 | DH20: =+CY20+DD20+DE20 -> 0 | DI20: =+DJ20-DH20 -> 0 | DJ20: =+DA20+DC20+DE20+DD20 -> 0 | DL20: =DO20-DM20 -> 0 | DM20: =SUMIFS('Oct 25 Inv'!H:H,'Oct 25 Inv'!E:E,'Summary Rollforward'!$B20) -> 0 | DN20: =-SUMIFS('Oct25 Dep'!J:J,'Oct25 Dep'!F:F,'Summary Rollforward'!$B20) -> 0 | DO20: =SUMIFS('Contract Data'!IU:IU,'Contract Data'!$C:$C,'Summary Rollforward'!$B20) -> 0 | DQ20: =+DH20+DM20+DN20 -> 0 | DR20: =+DS20-DQ20 -> 0 | DS20: =+DJ20+DL20+DN20+DM20 -> 0 | DU20: =DX20-DV20 -> 0 | DV20: =SUMIFS('Nov 25 Inv'!H:H,'Nov 25 Inv'!E:E,'Summary Rollforward'!$B20) -> 0 | DW20: =-SUMIFS('Nov25 Dep'!J:J,'Nov25 Dep'!F:F,'Summary Rollforward'!$B20) -> 0 | DX20: =SUMIFS('Contract Data'!IV:IV,'Contract Data'!$C:$C,'Summary Rollforward'!$B20) -> 0 | DZ20: =+DQ20+DV20+DW20 -> 0 | EA20: =+EB20-DZ20 -> 0 | EB20: =+DS20+DU20+DW20+DV20 -> 0 | ED20: =EG20-EE20 -> 0 | EE20: =SUMIFS('Dec 25 Inv'!H:H,'Dec 25 Inv'!E:E,'Summary Rollforward'!$B20) -> 0 | EF20: =-SUMIFS('Dec25 Dep'!I:I,'Dec25 Dep'!F:F,'Summary Rollforward'!$B20) -> 0 | EG20: =SUMIFS('Contract Data'!IW:IW,'Contract Data'!$C:$C,'Summary Rollforward'!$B20) -> 0 | EI20: =+DZ20+EE20+EF20 -> 0 | EJ20: =+EK20-EI20 -> 0 | EK20: =+EB20+ED20+EF20+EE20 -> 0
B21: Double B Foods | C21: Anderson Group | DC21: =DF21-DD21 -> 13562.5 | DD21: =SUMIFS('Sep 25 Inv'!H:H,'Sep 25 Inv'!E:E,'Summary Rollforward'!$B21) -> 0 | DE21: =-SUMIFS('Sep25 Dep'!J:J,'Sep25 Dep'!F:F,'Summary Rollforward'!$B21) -> 0 | DF21: =SUMIFS('Contract Data'!IT:IT,'Contract Data'!$C:$C,'Summary Rollforward'!$B21) -> 13562.5 | DH21: =+CY21+DD21+DE21 -> 0 | DI21: =+DJ21-DH21 -> 13562.5 | DJ21: =+DA21+DC21+DE21+DD21 -> 13562.5 | DL21: =DO21-DM21 -> 13562.5 | DM21: =SUMIFS('Oct 25 Inv'!H:H,'Oct 25 Inv'!E:E,'Summary Rollforward'!$B21) -> 0 | DN21: =-SUMIFS('Oct25 Dep'!J:J,'Oct25 Dep'!F:F,'Summary Rollforward'!$B21) -> 0 | DO21: =SUMIFS('Contract Data'!IU:IU,'Contract Data'!$C:$C,'Summary Rollforward'!$B21) -> 13562.5 | DQ21: =+DH21+DM21+DN21 -> 0 | DR21: =+DS21-DQ21 -> 27125 | DS21: =+DJ21+DL21+DN21+DM21 -> 27125 | DU21: =DX21-DV21 -> -9625 | DV21: =SUMIFS('Nov 25 Inv'!H:H,'Nov 25 Inv'!E:E,'Summary Rollforward'!$B21) -> 36750 | DW21: =-SUMIFS('Nov25 Dep'!J:J,'Nov25 Dep'!F:F,'Summary Rollforward'!$B21) -> -36750 | DX21: =SUMIFS('Contract Data'!IV:IV,'Contract Data'!$C:$C,'Summary Rollforward'!$B21) -> 27125 | DZ21: =+DQ21+DV21+DW21 -> 0 | EA21: =+EB21-DZ21 -> 17500 | EB21: =+DS21+DU21+DW21+DV21 -> 17500 | ED21: =EG21-EE21 -> -3941.42 | EE21: =SUMIFS('Dec 25 Inv'!H:H,'Dec 25 Inv'!E:E,'Summary Rollforward'!$B21) -> 41303.7 | EF21: =-SUMIFS('Dec25 Dep'!I:I,'Dec25 Dep'!F:F,'Summary Rollforward'!$B21) -> 0 | EG21: =SUMIFS('Contract Data'!IW:IW,'Contract Data'!$C:$C,'Summary Rollforward'!$B21) -> 37362.28 | EI21: =+DZ21+EE21+EF21 -> 41303.7 | EJ21: =+EK21-EI21 -> 13558.58 | EK21: =+EB21+ED21+EF21+EE21 -> 54862.28
B22: Douglas Washing & Sanitizing | C22: LLCP | P22: 46500 | S22: 0 | U22: =+N22+P22+Q22 -> 46500 | W22: =+'AR Calculation - Service'!AP297 -> 46500 | Z22: =+'Nov 30'!G10 -> 50000 | AA22: =+AB22-Z22 -> 43000 | AB22: =+U22+W22+X22 -> 93000 | AD22: =+'AR Calculation - Service'!AQ297-AE22 -> -34965 | AE22: =+'Dec Invoicing'!I16 -> 50000 | AG22: =+'AR Calculation - Service'!AQ296 -> -50000 | AI22: =+'Dec 31'!G10 -> 50000 | AJ22: =+AK22-AI22 -> 8035 | AK22: =+AB22+AD22+AG22+AF22+AE22 -> 58035 | AM22: =+'AR Calculation - Service'!AR297-'Summary Rollforward'!AN22 -> -12201 | AN22: =+'Jan Invoicing'!G10 -> 53868 | AO22: =-'Oct Collections'!AF16-'Oct Collections'!AF17 -> 0 | AQ22: =+AI22+AN22+AO22 -> 103868 | AR22: =+AS22-AQ22 -> -4166 | AS22: =+AK22+AM22+AO22+AN22 -> 99702 | AU22: =+'AR Calculation - Service'!AS297-'Summary Rollforward'!AV22 -> 41667 | AV22: =+'Jan Invoicing'!O10 -> 0 | AW22: =-'Oct Collections'!AN16-'Oct Collections'!AN17 -> 0 | AY22: =+AQ22+AV22+AW22 -> 103868 | AZ22: =+BA22-AY22 -> 37501 | BA22: =+AS22+AU22+AW22+AV22 -> 141369 | BC22: =+'AR Calculation - Service'!AT297-'Summary Rollforward'!BD22 -> 41667 | BD22: =+'Jan Invoicing'!W10 -> 0 | BG22: =+AY22+BD22+BE22 -> 103868 | BH22: =+BI22-BG22 -> 79168 | BI22: =+BA22+BC22+BE22+BD22 -> 183036 | BO22: =+BG22+BL22+BM22 -> 103868 | BP22: =+BQ22-BO22 -> 79168 | BQ22: =+BI22+BK22+BM22+BL22 -> 183036 | BS22: =BV22-BT22 -> -50000 | BT22: 50000 | BU22: -103868 | BV22: =SUMIFS('Contract Data'!IP:IP,'Contract Data'!C:C,'Summary Rollforward'!B22) -> 0 | BX22: =+BO22+BT22+BU22 -> 50000 | BY22: =+BZ22-BX22 -> 29168 | BZ22: =+BQ22+BS22+BU22+BT22 -> 79168 | CB22: =CE22-CC22 -> 0 | CC22: =SUMIFS('June 25 Inv'!G:G,'June 25 Inv'!D:D,'Summary Rollforward'!$B22) -> 0 | CD22: =-SUMIFS('Jun25 Dep'!I:I,'Jun25 Dep'!F:F,'Summary Rollforward'!$B22) -> 0 | CE22: =SUMIFS('Contract Data'!IQ:IQ,'Contract Data'!$C:$C,'Summary Rollforward'!$B22) -> 0 | CG22: =+BX22+CC22+CD22 -> 50000 | CH22: =+CI22-CG22 -> 29168 | CI22: =+BZ22+CB22+CD22+CC22 -> 79168 | CK22: =CN22-CL22 -> -29168 | CL22: =SUMIFS('Jul 25 Inv'!H:H,'Jul 25 Inv'!E:E,'Summary Rollforward'!$B22) -> 50000 | CM22: =-SUMIFS('Jul25 Dep'!J:J,'Jul25 Dep'!F:F,'Summary Rollforward'!$B22) -> -50000 | CN22: =SUMIFS('Contract Data'!IR:IR,'Contract Data'!$C:$C,'Summary Rollforward'!$B22) -> 20832 | CP22: =+CG22+CL22+CM22 -> 50000 | CQ22: =+CR22-CP22 -> 0 | CR22: =+CI22+CK22+CM22+CL22 -> 50000 | CT22: =CW22-CU22 -> 0 | CU22: =SUMIFS('Aug 25 Inv'!H:H,'Aug 25 Inv'!E:E,'Summary Rollforward'!$B22) -> 0 | CV22: =-SUMIFS('Aug25 Dep'!J:J,'Aug25 Dep'!F:F,'Summary Rollforward'!$B22) -> -50000 | CW22: =SUMIFS('Contract Data'!IS:IS,'Contract Data'!$C:$C,'Summary Rollforward'!$B22) -> 0 | CY22: =+CP22+CU22+CV22 -> 0 | CZ22: =+DA22-CY22 -> 0 | DA22: =+CR22+CT22+CV22+CU22 -> 0 | DC22: =DF22-DD22 -> 0 | DD22: =SUMIFS('Sep 25 Inv'!H:H,'Sep 25 Inv'!E:E,'Summary Rollforward'!$B22) -> 0 | DE22: =-SUMIFS('Sep25 Dep'!J:J,'Sep25 Dep'!F:F,'Summary Rollforward'!$B22) -> 0 | DF22: =SUMIFS('Contract Data'!IT:IT,'Contract Data'!$C:$C,'Summary Rollforward'!$B22) -> 0 | DH22: =+CY22+DD22+DE22 -> 0 | DI22: =+DJ22-DH22 -> 0 | DJ22: =+DA22+DC22+DE22+DD22 -> 0 | DL22: =DO22-DM22 -> 0 | DM22: =SUMIFS('Oct 25 Inv'!H:H,'Oct 25 Inv'!E:E,'Summary Rollforward'!$B22) -> 0 | DN22: =-SUMIFS('Oct25 Dep'!J:J,'Oct25 Dep'!F:F,'Summary Rollforward'!$B22) -> 0 | DO22: =SUMIFS('Contract Data'!IU:IU,'Contract Data'!$C:$C,'Summary Rollforward'!$B22) -> 0 | DQ22: =+DH22+DM22+DN22 -> 0 | DR22: =+DS22-DQ22 -> 0 | DS22: =+DJ22+DL22+DN22+DM22 -> 0 | DU22: =DX22-DV22 -> 0 | DV22: =SUMIFS('Nov 25 Inv'!H:H,'Nov 25 Inv'!E:E,'Summary Rollforward'!$B22) -> 0 | DW22: =-SUMIFS('Nov25 Dep'!J:J,'Nov25 Dep'!F:F,'Summary Rollforward'!$B22) -> 0 | DX22: =SUMIFS('Contract Data'!IV:IV,'Contract Data'!$C:$C,'Summary Rollforward'!$B22) -> 0 | DZ22: =+DQ22+DV22+DW22 -> 0 | EA22: =+EB22-DZ22 -> 0 | EB22: =+DS22+DU22+DW22+DV22 -> 0 | ED22: =EG22-EE22 -> 0 | EE22: =SUMIFS('Dec 25 Inv'!H:H,'Dec 25 Inv'!E:E,'Summary Rollforward'!$B22) -> 0 | EF22: =-SUMIFS('Dec25 Dep'!I:I,'Dec25 Dep'!F:F,'Summary Rollforward'!$B22) -> 0 | EG22: =SUMIFS('Contract Data'!IW:IW,'Contract Data'!$C:$C,'Summary Rollforward'!$B22) -> 0 | EI22: =+DZ22+EE22+EF22 -> 0 | EJ22: =+EK22-EI22 -> 0 | EK22: =+EB22+ED22+EF22+EE22 -> 0
B23: Emerald Technologies | C23: Crestview Partners | BK23: =+'AR Calculation - Service'!AU385-'Summary Rollforward'!BL23 -> -12375 | BL23: =+'Apr Invoices'!G19 -> 55000 | BO23: =+BG23+BL23+BM23 -> 55000 | BP23: =+BQ23-BO23 -> -12375 | BQ23: =+BI23+BK23+BM23+BL23 -> 42625 | BS23: =BV23-BT23 -> -12375 | BT23: 55000 | BU23: 0 | BV23: =SUMIFS('Contract Data'!IP:IP,'Contract Data'!C:C,'Summary Rollforward'!B23) -> 42625 | BX23: =+BO23+BT23+BU23 -> 110000 | BY23: =+BZ23-BX23 -> -24750 | BZ23: =+BQ23+BS23+BU23+BT23 -> 85250 | CB23: =CE23-CC23 -> -12375 | CC23: =SUMIFS('June 25 Inv'!G:G,'June 25 Inv'!D:D,'Summary Rollforward'!$B23) -> 55000 | CD23: =-SUMIFS('Jun25 Dep'!I:I,'Jun25 Dep'!F:F,'Summary Rollforward'!$B23) -> 0 | CE23: =SUMIFS('Contract Data'!IQ:IQ,'Contract Data'!$C:$C,'Summary Rollforward'!$B23) -> 42625 | CG23: =+BX23+CC23+CD23 -> 165000 | CH23: =+CI23-CG23 -> -37125 | CI23: =+BZ23+CB23+CD23+CC23 -> 127875 | CK23: =CN23-CL23 -> -12375 | CL23: =SUMIFS('Jul 25 Inv'!H:H,'Jul 25 Inv'!E:E,'Summary Rollforward'!$B23) -> 55000 | CM23: =-SUMIFS('Jul25 Dep'!J:J,'Jul25 Dep'!F:F,'Summary Rollforward'!$B23) -> -55000 | CN23: =SUMIFS('Contract Data'!IR:IR,'Contract Data'!$C:$C,'Summary Rollforward'!$B23) -> 42625 | CP23: =+CG23+CL23+CM23 -> 165000 | CQ23: =+CR23-CP23 -> -49500 | CR23: =+CI23+CK23+CM23+CL23 -> 115500 | CT23: =CW23-CU23 -> -12375 | CU23: =SUMIFS('Aug 25 Inv'!H:H,'Aug 25 Inv'!E:E,'Summary Rollforward'!$B23) -> 55000 | CV23: =-SUMIFS('Aug25 Dep'!J:J,'Aug25 Dep'!F:F,'Summary Rollforward'!$B23) -> -110000 | CW23: =SUMIFS('Contract Data'!IS:IS,'Contract Data'!$C:$C,'Summary Rollforward'!$B23) -> 42625 | CY23: =+CP23+CU23+CV23 -> 110000 | CZ23: =+DA23-CY23 -> -61875 | DA23: =+CR23+CT23+CV23+CU23 -> 48125 | DC23: =DF23-DD23 -> 15000 | DD23: =SUMIFS('Sep 25 Inv'!H:H,'Sep 25 Inv'!E:E,'Summary Rollforward'!$B23) -> 0 | DE23: =-SUMIFS('Sep25 Dep'!J:J,'Sep25 Dep'!F:F,'Summary Rollforward'!$B23) -> -55000 | DF23: =SUMIFS('Contract Data'!IT:IT,'Contract Data'!$C:$C,'Summary Rollforward'!$B23) -> 15000 | DH23: =+CY23+DD23+DE23 -> 55000 | DI23: =+DJ23-DH23 -> -46875 | DJ23: =+DA23+DC23+DE23+DD23 -> 8125 | DL23: =DO23-DM23 -> 15000 | DM23: =SUMIFS('Oct 25 Inv'!H:H,'Oct 25 Inv'!E:E,'Summary Rollforward'!$B23) -> 0 | DN23: =-SUMIFS('Oct25 Dep'!J:J,'Oct25 Dep'!F:F,'Summary Rollforward'!$B23) -> 0 | DO23: =SUMIFS('Contract Data'!IU:IU,'Contract Data'!$C:$C,'Summary Rollforward'!$B23) -> 15000 | DQ23: =+DH23+DM23+DN23 -> 55000 | DR23: =+DS23-DQ23 -> -31875 | DS23: =+DJ23+DL23+DN23+DM23 -> 23125 | DU23: =DX23-DV23 -> 15000 | DV23: =SUMIFS('Nov 25 Inv'!H:H,'Nov 25 Inv'!E:E,'Summary Rollforward'!$B23) -> 0 | DW23: =-SUMIFS('Nov25 Dep'!J:J,'Nov25 Dep'!F:F,'Summary Rollforward'!$B23) -> 0 | DX23: =SUMIFS('Contract Data'!IV:IV,'Contract Data'!$C:$C,'Summary Rollforward'!$B23) -> 15000 | DZ23: =+DQ23+DV23+DW23 -> 55000 | EA23: =+EB23-DZ23 -> -16875 | EB23: =+DS23+DU23+DW23+DV23 -> 38125 | ED23: =EG23-EE23 -> 5625 | EE23: =SUMIFS('Dec 25 Inv'!H:H,'Dec 25 Inv'!E:E,'Summary Rollforward'!$B23) -> 0 | EF23: =-SUMIFS('Dec25 Dep'!I:I,'Dec25 Dep'!F:F,'Summary Rollforward'!$B23) -> 0 | EG23: =SUMIFS('Contract Data'!IW:IW,'Contract Data'!$C:$C,'Summary Rollforward'!$B23) -> 5625 | EI23: =+DZ23+EE23+EF23 -> 55000 | EJ23: =+EK23-EI23 -> -11250 | EK23: =+EB23+ED23+EF23+EE23 -> 43750
B24: Enerpac Tool Group | C24: NA | BK24: =+'AR Calculation - Service'!AU389-'Summary Rollforward'!BL24 -> -50000 | BL24: 50000 | BO24: =+BG24+BL24+BM24 -> 50000 | BP24: =+BQ24-BO24 -> -50000 | BQ24: =+BI24+BK24+BM24+BL24 -> 0 | BS24: =BV24-BT24 -> 0 | BT24: 0 | BU24: 0 | BV24: =SUMIFS('Contract Data'!IP:IP,'Contract Data'!C:C,'Summary Rollforward'!B24) -> 0 | BX24: =+BO24+BT24+BU24 -> 50000 | BY24: =+BZ24-BX24 -> -50000 | BZ24: =+BQ24+BS24+BU24+BT24 -> 0 | CB24: =CE24-CC24 -> 0 | CC24: =SUMIFS('June 25 Inv'!G:G,'June 25 Inv'!D:D,'Summary Rollforward'!$B24) -> 0 | CD24: =-SUMIFS('Jun25 Dep'!I:I,'Jun25 Dep'!F:F,'Summary Rollforward'!$B24) -> 0 | CE24: =SUMIFS('Contract Data'!IQ:IQ,'Contract Data'!$C:$C,'Summary Rollforward'!$B24) -> 0 | CG24: =+BX24+CC24+CD24 -> 50000 | CH24: =+CI24-CG24 -> -50000 | CI24: =+BZ24+CB24+CD24+CC24 -> 0 | CK24: =CN24-CL24 -> 15000 | CL24: =SUMIFS('Jul 25 Inv'!H:H,'Jul 25 Inv'!E:E,'Summary Rollforward'!$B24) -> 0 | CM24: =-SUMIFS('Jul25 Dep'!J:J,'Jul25 Dep'!F:F,'Summary Rollforward'!$B24) -> 0 | CN24: =SUMIFS('Contract Data'!IR:IR,'Contract Data'!$C:$C,'Summary Rollforward'!$B24) -> 15000 | CP24: =+CG24+CL24+CM24 -> 50000 | CQ24: =+CR24-CP24 -> -35000 | CR24: =+CI24+CK24+CM24+CL24 -> 15000 | CT24: =CW24-CU24 -> 15000 | CU24: =SUMIFS('Aug 25 Inv'!H:H,'Aug 25 Inv'!E:E,'Summary Rollforward'!$B24) -> 0 | CV24: =-SUMIFS('Aug25 Dep'!J:J,'Aug25 Dep'!F:F,'Summary Rollforward'!$B24) -> 0 | CW24: =SUMIFS('Contract Data'!IS:IS,'Contract Data'!$C:$C,'Summary Rollforward'!$B24) -> 15000 | CY24: =+CP24+CU24+CV24 -> 50000 | CZ24: =+DA24-CY24 -> -20000 | DA24: =+CR24+CT24+CV24+CU24 -> 30000 | DC24: =DF24-DD24 -> 60000 | DD24: =SUMIFS('Sep 25 Inv'!H:H,'Sep 25 Inv'!E:E,'Summary Rollforward'!$B24) -> 0 | DE24: =-SUMIFS('Sep25 Dep'!J:J,'Sep25 Dep'!F:F,'Summary Rollforward'!$B24) -> -50000 | DF24: =SUMIFS('Contract Data'!IT:IT,'Contract Data'!$C:$C,'Summary Rollforward'!$B24) -> 60000 | DH24: =+CY24+DD24+DE24 -> 0 | DI24: =+DJ24-DH24 -> 40000 | DJ24: =+DA24+DC24+DE24+DD24 -> 40000 | DL24: =DO24-DM24 -> 60000 | DM24: =SUMIFS('Oct 25 Inv'!H:H,'Oct 25 Inv'!E:E,'Summary Rollforward'!$B24) -> 0 | DN24: =-SUMIFS('Oct25 Dep'!J:J,'Oct25 Dep'!F:F,'Summary Rollforward'!$B24) -> 0 | DO24: =SUMIFS('Contract Data'!IU:IU,'Contract Data'!$C:$C,'Summary Rollforward'!$B24) -> 60000 | DQ24: =+DH24+DM24+DN24 -> 0 | DR24: =+DS24-DQ24 -> 100000 | DS24: =+DJ24+DL24+DN24+DM24 -> 100000 | DU24: =DX24-DV24 -> 60000 | DV24: =SUMIFS('Nov 25 Inv'!H:H,'Nov 25 Inv'!E:E,'Summary Rollforward'!$B24) -> 0 | DW24: =-SUMIFS('Nov25 Dep'!J:J,'Nov25 Dep'!F:F,'Summary Rollforward'!$B24) -> 0 | DX24: =SUMIFS('Contract Data'!IV:IV,'Contract Data'!$C:$C,'Summary Rollforward'!$B24) -> 60000 | DZ24: =+DQ24+DV24+DW24 -> 0 | EA24: =+EB24-DZ24 -> 160000 | EB24: =+DS24+DU24+DW24+DV24 -> 160000 | ED24: =EG24-EE24 -> 45396.33 | EE24: =SUMIFS('Dec 25 Inv'!H:H,'Dec 25 Inv'!E:E,'Summary Rollforward'!$B24) -> 14603.67 | EF24: =-SUMIFS('Dec25 Dep'!I:I,'Dec25 Dep'!F:F,'Summary Rollforward'!$B24) -> 0 | EG24: =SUMIFS('Contract Data'!IW:IW,'Contract Data'!$C:$C,'Summary Rollforward'!$B24) -> 60000 | EI24: =+DZ24+EE24+EF24 -> 14603.67 | EJ24: =+EK24-EI24 -> 205396.33 | EK24: =+EB24+ED24+EF24+EE24 -> 220000
B25: Epika | C25: Trivest | F25: =+G25-E25 -> 25000 | G25: =+'AR Calculation - Service'!AM290 -> 25000 | I25: =+'AR Calculation - Service'!AN289 -> 46500 | L25: =+'Sep 30'!G11 -> 100000 | M25: =+N25-L25 -> -28500 | N25: =+G25+I25+J25 -> 71500 | P25: 46500 | Q25: =-'Oct Collections'!J7 -> -100000 | S25: =+'Sep 30'!N11 -> 0 | T25: =+U25-S25 -> 18000 | U25: =+N25+P25+Q25 -> 18000 | W25: =+'AR Calculation - Service'!AP289 -> 46500 | X25: =-'Oct Collections'!Q7 -> 0 | Z25: =+'Sep 30'!U11 -> 0 | AA25: =+AB25-Z25 -> 64500 | AB25: =+U25+W25+X25 -> 64500 | AD25: =+'AR Calculation - Service'!AQ289-AE25 -> 18683 | AE25: =+'Dec Invoicing'!I12 -> 100000 | AG25: =-'Oct Collections'!X7 -> 0 | AI25: =+'Dec 31'!G11 -> 100000 | AJ25: =+AK25-AI25 -> 83183 | AK25: =+AB25+AD25+AG25+AF25+AE25 -> 183183 | AM25: =+'AR Calculation - Service'!AR289-'Summary Rollforward'!AN25 -> 50000 | AN25: =+'Dec Invoicing'!Q12 -> 0 | AO25: =-'Oct Collections'!AF17-'Oct Collections'!AF18 -> 0 | AQ25: =+AI25+AN25+AO25 -> 100000 | AR25: =+AS25-AQ25 -> 133183 | AS25: =+AK25+AM25+AO25+AN25 -> 233183 | AU25: =+'AR Calculation - Service'!AS289-'Summary Rollforward'!AV25 -> 25000 | AV25: =+'Dec Invoicing'!Y12 -> 0 | AW25: =-'Oct Collections'!AN17-'Oct Collections'!AN18 -> 0 | AY25: =+AQ25+AV25+AW25 -> 100000 | AZ25: =+BA25-AY25 -> 158183 | BA25: =+AS25+AU25+AW25+AV25 -> 258183 | BC25: =+'AR Calculation - Service'!AT289-'Summary Rollforward'!BD25 -> -18089 | BD25: =+'Mar Invoices'!G15 -> 100000 | BG25: =+AY25+BD25+BE25 -> 200000 | BH25: =+BI25-BG25 -> 140094 | BI25: =+BA25+BC25+BE25+BD25 -> 340094 | BK25: =+'AR Calculation - Service'!AU289-'Summary Rollforward'!BL25 -> -140094 | BL25: =+'Apr Invoices'!G6 -> 140094 | BM25: 100000 | BO25: =+BG25+BL25+BM25 -> 440094 | BP25: =+BQ25-BO25 -> 0 | BQ25: =+BI25+BK25+BM25+BL25 -> 440094 | BS25: =BV25-BT25 -> 0 | BT25: 0 | BU25: -100000 | BV25: =SUMIFS('Contract Data'!IP:IP,'Contract Data'!C:C,'Summary Rollforward'!B25) -> 0 | BX25: =+BO25+BT25+BU25 -> 340094 | BY25: =+BZ25-BX25 -> 0 | BZ25: =+BQ25+BS25+BU25+BT25 -> 340094 | CB25: =CE25-CC25 -> 0 | CC25: =SUMIFS('June 25 Inv'!G:G,'June 25 Inv'!D:D,'Summary Rollforward'!$B25) -> 27082 | CD25: =-SUMIFS('Jun25 Dep'!I:I,'Jun25 Dep'!F:F,'Summary Rollforward'!$B25) -> -340094 | CE25: =SUMIFS('Contract Data'!IQ:IQ,'Contract Data'!$C:$C,'Summary Rollforward'!$B25) -> 27082 | CG25: =+BX25+CC25+CD25 -> 27082 | CH25: =+CI25-CG25 -> 0 | CI25: =+BZ25+CB25+CD25+CC25 -> 27082 | CK25: =CN25-CL25 -> -0.2 | CL25: =SUMIFS('Jul 25 Inv'!H:H,'Jul 25 Inv'!E:E,'Summary Rollforward'!$B25) -> 7276.2 | CM25: =-SUMIFS('Jul25 Dep'!J:J,'Jul25 Dep'!F:F,'Summary Rollforward'!$B25) -> 0 | CN25: =SUMIFS('Contract Data'!IR:IR,'Contract Data'!$C:$C,'Summary Rollforward'!$B25) -> 7276 | CP25: =+CG25+CL25+CM25 -> 34358.2 | CQ25: =+CR25-CP25 -> -0.2 | CR25: =+CI25+CK25+CM25+CL25 -> 34358 | CT25: =CW25-CU25 -> 0 | CU25: =SUMIFS('Aug 25 Inv'!H:H,'Aug 25 Inv'!E:E,'Summary Rollforward'!$B25) -> 0 | CV25: =-SUMIFS('Aug25 Dep'!J:J,'Aug25 Dep'!F:F,'Summary Rollforward'!$B25) -> 0 | CW25: =SUMIFS('Contract Data'!IS:IS,'Contract Data'!$C:$C,'Summary Rollforward'!$B25) -> 0 | CY25: =+CP25+CU25+CV25 -> 34358.2 | CZ25: =+DA25-CY25 -> -0.2 | DA25: =+CR25+CT25+CV25+CU25 -> 34358 | DC25: =DF25-DD25 -> 0 | DD25: =SUMIFS('Sep 25 Inv'!H:H,'Sep 25 Inv'!E:E,'Summary Rollforward'!$B25) -> 0 | DE25: =-SUMIFS('Sep25 Dep'!J:J,'Sep25 Dep'!F:F,'Summary Rollforward'!$B25) -> -34358.2 | DF25: =SUMIFS('Contract Data'!IT:IT,'Contract Data'!$C:$C,'Summary Rollforward'!$B25) -> 0 | DH25: =+CY25+DD25+DE25 -> 0 | DI25: =+DJ25-DH25 -> -0.2 | DJ25: =+DA25+DC25+DE25+DD25 -> -0.2 | DL25: =DO25-DM25 -> 0 | DM25: =SUMIFS('Oct 25 Inv'!H:H,'Oct 25 Inv'!E:E,'Summary Rollforward'!$B25) -> 0 | DN25: =-SUMIFS('Oct25 Dep'!J:J,'Oct25 Dep'!F:F,'Summary Rollforward'!$B25) -> 0 | DO25: =SUMIFS('Contract Data'!IU:IU,'Contract Data'!$C:$C,'Summary Rollforward'!$B25) -> 0 | DQ25: =+DH25+DM25+DN25 -> 0 | DR25: =+DS25-DQ25 -> -0.2 | DS25: =+DJ25+DL25+DN25+DM25 -> -0.2 | DU25: =DX25-DV25 -> 0 | DV25: =SUMIFS('Nov 25 Inv'!H:H,'Nov 25 Inv'!E:E,'Summary Rollforward'!$B25) -> 0 | DW25: =-SUMIFS('Nov25 Dep'!J:J,'Nov25 Dep'!F:F,'Summary Rollforward'!$B25) -> 0 | DX25: =SUMIFS('Contract Data'!IV:IV,'Contract Data'!$C:$C,'Summary Rollforward'!$B25) -> 0 | DZ25: =+DQ25+DV25+DW25 -> 0 | EA25: =+EB25-DZ25 -> -0.2 | EB25: =+DS25+DU25+DW25+DV25 -> -0.2 | ED25: =EG25-EE25 -> 0.2 | EE25: =SUMIFS('Dec 25 Inv'!H:H,'Dec 25 Inv'!E:E,'Summary Rollforward'!$B25) -> 0 | EF25: =-SUMIFS('Dec25 Dep'!I:I,'Dec25 Dep'!F:F,'Summary Rollforward'!$B25) -> 0 | EG25: =-EB25 -> 0.2 | EI25: =+DZ25+EE25+EF25 -> 0 | EJ25: =+EK25-EI25 -> 0 | EK25: =+EB25+ED25+EF25+EE25 -> 0
B26: Envirowaste Services Group | C26: Trivest | BC26: =+'AR Calculation - Service'!AT357-BD26 -> 14338 | BH26: =+BI26-BG26 -> 14338 | BI26: =+BA26+BC26+BE26+BD26 -> 14338 | BK26: =+'AR Calculation - Service'!AU357-'Summary Rollforward'!BL26 -> -5325 | BL26: =+'Apr Invoices'!G18 -> 34000 | BO26: =+BG26+BL26+BM26 -> 34000 | BP26: =+BQ26-BO26 -> 9013 | BQ26: =+BI26+BK26+BM26+BL26 -> 43013 | BS26: =BV26-BT26 -> -11325 | BT26: 40000 | BU26: 0 | BV26: =SUMIFS('Contract Data'!IP:IP,'Contract Data'!C:C,'Summary Rollforward'!B26) -> 28675 | BX26: =+BO26+BT26+BU26 -> 74000 | BY26: =+BZ26-BX26 -> -2312 | BZ26: =+BQ26+BS26+BU26+BT26 -> 71688 | CB26: =CE26-CC26 -> -6025 | CC26: =SUMIFS('June 25 Inv'!G:G,'June 25 Inv'!D:D,'Summary Rollforward'!$B26) -> 37000 | CD26: =-SUMIFS('Jun25 Dep'!I:I,'Jun25 Dep'!F:F,'Summary Rollforward'!$B26) -> -34000 | CE26: =SUMIFS('Contract Data'!IQ:IQ,'Contract Data'!$C:$C,'Summary Rollforward'!$B26) -> 30975 | CG26: =+BX26+CC26+CD26 -> 77000 | CH26: =+CI26-CG26 -> -8337 | CI26: =+BZ26+CB26+CD26+CC26 -> 68663 | CK26: =CN26-CL26 -> -3725 | CL26: =SUMIFS('Jul 25 Inv'!H:H,'Jul 25 Inv'!E:E,'Summary Rollforward'!$B26) -> 37000 | CM26: =-SUMIFS('Jul25 Dep'!J:J,'Jul25 Dep'!F:F,'Summary Rollforward'!$B26) -> -40000 | CN26: =SUMIFS('Contract Data'!IR:IR,'Contract Data'!$C:$C,'Summary Rollforward'!$B26) -> 33275 | CP26: =+CG26+CL26+CM26 -> 74000 | CQ26: =+CR26-CP26 -> -12062 | CR26: =+CI26+CK26+CM26+CL26 -> 61938 | CT26: =CW26-CU26 -> -3725 | CU26: =SUMIFS('Aug 25 Inv'!H:H,'Aug 25 Inv'!E:E,'Summary Rollforward'!$B26) -> 37000 | CV26: =-SUMIFS('Aug25 Dep'!J:J,'Aug25 Dep'!F:F,'Summary Rollforward'!$B26) -> -37000 | CW26: =SUMIFS('Contract Data'!IS:IS,'Contract Data'!$C:$C,'Summary Rollforward'!$B26) -> 33275 | CY26: =+CP26+CU26+CV26 -> 74000 | CZ26: =+DA26-CY26 -> -15787 | DA26: =+CR26+CT26+CV26+CU26 -> 58213 | DC26: =DF26-DD26 -> 18962.5 | DD26: =SUMIFS('Sep 25 Inv'!H:H,'Sep 25 Inv'!E:E,'Summary Rollforward'!$B26) -> 0 | DE26: =-SUMIFS('Sep25 Dep'!J:J,'Sep25 Dep'!F:F,'Summary Rollforward'!$B26) -> -37000 | DF26: =SUMIFS('Contract Data'!IT:IT,'Contract Data'!$C:$C,'Summary Rollforward'!$B26) -> 18962.5 | DH26: =+CY26+DD26+DE26 -> 37000 | DI26: =+DJ26-DH26 -> 3175.5 | DJ26: =+DA26+DC26+DE26+DD26 -> 40175.5 | DL26: =DO26-DM26 -> 15950 | DM26: =SUMIFS('Oct 25 Inv'!H:H,'Oct 25 Inv'!E:E,'Summary Rollforward'!$B26) -> 0 | DN26: =-SUMIFS('Oct25 Dep'!J:J,'Oct25 Dep'!F:F,'Summary Rollforward'!$B26) -> -37000 | DO26: =SUMIFS('Contract Data'!IU:IU,'Contract Data'!$C:$C,'Summary Rollforward'!$B26) -> 15950 | DQ26: =+DH26+DM26+DN26 -> 0 | DR26: =+DS26-DQ26 -> 19125.5 | DS26: =+DJ26+DL26+DN26+DM26 -> 19125.5 | DU26: =DX26-DV26 -> -8258 | DV26: =SUMIFS('Nov 25 Inv'!H:H,'Nov 25 Inv'!E:E,'Summary Rollforward'!$B26) -> 11258 | DW26: =-SUMIFS('Nov25 Dep'!J:J,'Nov25 Dep'!F:F,'Summary Rollforward'!$B26) -> 0 | DX26: =SUMIFS('Contract Data'!IV:IV,'Contract Data'!$C:$C,'Summary Rollforward'!$B26) -> 3000 | DZ26: =+DQ26+DV26+DW26 -> 11258 | EA26: =+EB26-DZ26 -> 10867.5 | EB26: =+DS26+DU26+DW26+DV26 -> 22125.5 | ED26: =EG26-EE26 -> -10867.5 | EE26: =SUMIFS('Dec 25 Inv'!H:H,'Dec 25 Inv'!E:E,'Summary Rollforward'!$B26) -> 17173 | EF26: =-SUMIFS('Dec25 Dep'!I:I,'Dec25 Dep'!F:F,'Summary Rollforward'!$B26) -> 0 | EG26: =SUMIFS('Contract Data'!IW:IW,'Contract Data'!$C:$C,'Summary Rollforward'!$B26) -> 6305.5 | EI26: =+DZ26+EE26+EF26 -> 28431 | EJ26: =+EK26-EI26 -> 0 | EK26: =+EB26+ED26+EF26+EE26 -> 28431
B27: Experigreen Lawn Care, LLC | C27: Windpoint | CT27: =CW27-CU27 -> 13562.5 | CU27: =SUMIFS('Aug 25 Inv'!H:H,'Aug 25 Inv'!E:E,'Summary Rollforward'!$B27) -> 0 | CV27: =-SUMIFS('Aug25 Dep'!J:J,'Aug25 Dep'!F:F,'Summary Rollforward'!$B27) -> 0 | CW27: =SUMIFS('Contract Data'!IS:IS,'Contract Data'!$C:$C,'Summary Rollforward'!$B27) -> 13562.5 | CY27: =+CP27+CU27+CV27 -> 0 | CZ27: =+DA27-CY27 -> 13562.5 | DA27: =+CR27+CT27+CV27+CU27 -> 13562.5 | DC27: =DF27-DD27 -> 27125 | DD27: =SUMIFS('Sep 25 Inv'!H:H,'Sep 25 Inv'!E:E,'Summary Rollforward'!$B27) -> 0 | DE27: =-SUMIFS('Sep25 Dep'!J:J,'Sep25 Dep'!F:F,'Summary Rollforward'!$B27) -> 0 | DF27: =SUMIFS('Contract Data'!IT:IT,'Contract Data'!$C:$C,'Summary Rollforward'!$B27) -> 27125 | DH27: =+CY27+DD27+DE27 -> 0 | DI27: =+DJ27-DH27 -> 40687.5 | DJ27: =+DA27+DC27+DE27+DD27 -> 40687.5 | DL27: =DO27-DM27 -> 27125 | DM27: =SUMIFS('Oct 25 Inv'!H:H,'Oct 25 Inv'!E:E,'Summary Rollforward'!$B27) -> 0 | DN27: =-SUMIFS('Oct25 Dep'!J:J,'Oct25 Dep'!F:F,'Summary Rollforward'!$B27) -> 0 | DO27: =SUMIFS('Contract Data'!IU:IU,'Contract Data'!$C:$C,'Summary Rollforward'!$B27) -> 27125 | DQ27: =+DH27+DM27+DN27 -> 0 | DR27: =+DS27-DQ27 -> 67812.5 | DS27: =+DJ27+DL27+DN27+DM27 -> 67812.5 | DU27: =DX27-DV27 -> -5335.26 | DV27: =SUMIFS('Nov 25 Inv'!H:H,'Nov 25 Inv'!E:E,'Summary Rollforward'!$B27) -> 35000 | DW27: =-SUMIFS('Nov25 Dep'!J:J,'Nov25 Dep'!F:F,'Summary Rollforward'!$B27) -> 0 | DX27: =SUMIFS('Contract Data'!IV:IV,'Contract Data'!$C:$C,'Summary Rollforward'!$B27) -> 29664.74 | DZ27: =+DQ27+DV27+DW27 -> 35000 | EA27: =+EB27-DZ27 -> 62477.24 | EB27: =+DS27+DU27+DW27+DV27 -> 97477.24 | ED27: =EG27-EE27 -> -9920.52 | EE27: =SUMIFS('Dec 25 Inv'!H:H,'Dec 25 Inv'!E:E,'Summary Rollforward'!$B27) -> 35000 | EF27: =-SUMIFS('Dec25 Dep'!I:I,'Dec25 Dep'!F:F,'Summary Rollforward'!$B27) -> -35000 | EG27: =SUMIFS('Contract Data'!IW:IW,'Contract Data'!$C:$C,'Summary Rollforward'!$B27) -> 25079.48 | EI27: =+DZ27+EE27+EF27 -> 35000 | EJ27: =+EK27-EI27 -> 52556.72 | EK27: =+EB27+ED27+EF27+EE27 -> 87556.72
B28: Flexcon | C28: NA | CB28: =CE28-CC28 -> -7562.5 | CC28: =SUMIFS('June 25 Inv'!G:G,'June 25 Inv'!D:D,'Summary Rollforward'!$B28) -> 25000 | CD28: =-SUMIFS('Jun25 Dep'!I:I,'Jun25 Dep'!F:F,'Summary Rollforward'!$B28) -> 0 | CE28: =SUMIFS('Contract Data'!IQ:IQ,'Contract Data'!$C:$C,'Summary Rollforward'!$B28) -> 17437.5 | CG28: =+BX28+CC28+CD28 -> 25000 | CH28: =+CI28-CG28 -> -7562.5 | CI28: =+BZ28+CB28+CD28+CC28 -> 17437.5 | CK28: =CN28-CL28 -> 34875 | CL28: =SUMIFS('Jul 25 Inv'!H:H,'Jul 25 Inv'!E:E,'Summary Rollforward'!$B28) -> 0 | CM28: =-SUMIFS('Jul25 Dep'!J:J,'Jul25 Dep'!F:F,'Summary Rollforward'!$B28) -> 0 | CN28: =SUMIFS('Contract Data'!IR:IR,'Contract Data'!$C:$C,'Summary Rollforward'!$B28) -> 34875 | CP28: =+CG28+CL28+CM28 -> 25000 | CQ28: =+CR28-CP28 -> 27312.5 | CR28: =+CI28+CK28+CM28+CL28 -> 52312.5 | CT28: =CW28-CU28 -> 34875 | CU28: =SUMIFS('Aug 25 Inv'!H:H,'Aug 25 Inv'!E:E,'Summary Rollforward'!$B28) -> 0 | CV28: =-SUMIFS('Aug25 Dep'!J:J,'Aug25 Dep'!F:F,'Summary Rollforward'!$B28) -> 0 | CW28: =SUMIFS('Contract Data'!IS:IS,'Contract Data'!$C:$C,'Summary Rollforward'!$B28) -> 34875 | CY28: =+CP28+CU28+CV28 -> 25000 | CZ28: =+DA28-CY28 -> 62187.5 | DA28: =+CR28+CT28+CV28+CU28 -> 87187.5 | DC28: =DF28-DD28 -> 18371.03 | DD28: =SUMIFS('Sep 25 Inv'!H:H,'Sep 25 Inv'!E:E,'Summary Rollforward'!$B28) -> 25000 | DE28: =-SUMIFS('Sep25 Dep'!J:J,'Sep25 Dep'!F:F,'Summary Rollforward'!$B28) -> -25000 | DF28: =SUMIFS('Contract Data'!IT:IT,'Contract Data'!$C:$C,'Summary Rollforward'!$B28) -> 43371.03 | DH28: =+CY28+DD28+DE28 -> 25000 | DI28: =+DJ28-DH28 -> 80558.53 | DJ28: =+DA28+DC28+DE28+DD28 -> 105558.53 | DL28: =DO28-DM28 -> -125 | DM28: =SUMIFS('Oct 25 Inv'!H:H,'Oct 25 Inv'!E:E,'Summary Rollforward'!$B28) -> 55000 | DN28: =-SUMIFS('Oct25 Dep'!J:J,'Oct25 Dep'!F:F,'Summary Rollforward'!$B28) -> -25000 | DO28: =SUMIFS('Contract Data'!IU:IU,'Contract Data'!$C:$C,'Summary Rollforward'!$B28) -> 54875 | DQ28: =+DH28+DM28+DN28 -> 55000 | DR28: =+DS28-DQ28 -> 80433.53 | DS28: =+DJ28+DL28+DN28+DM28 -> 135433.53 | DU28: =DX28-DV28 -> -10000 | DV28: =SUMIFS('Nov 25 Inv'!H:H,'Nov 25 Inv'!E:E,'Summary Rollforward'!$B28) -> 60000 | DW28: =-SUMIFS('Nov25 Dep'!J:J,'Nov25 Dep'!F:F,'Summary Rollforward'!$B28) -> -55000 | DX28: =SUMIFS('Contract Data'!IV:IV,'Contract Data'!$C:$C,'Summary Rollforward'!$B28) -> 50000 | DZ28: =+DQ28+DV28+DW28 -> 60000 | EA28: =+EB28-DZ28 -> 70433.53 | EB28: =+DS28+DU28+DW28+DV28 -> 130433.53 | ED28: =EG28-EE28 -> 40000 | EE28: =SUMIFS('Dec 25 Inv'!H:H,'Dec 25 Inv'!E:E,'Summary Rollforward'!$B28) -> 0 | EF28: =-SUMIFS('Dec25 Dep'!I:I,'Dec25 Dep'!F:F,'Summary Rollforward'!$B28) -> -60000 | EG28: =SUMIFS('Contract Data'!IW:IW,'Contract Data'!$C:$C,'Summary Rollforward'!$B28) -> 40000 | EI28: =+DZ28+EE28+EF28 -> 0 | EJ28: =+EK28-EI28 -> 110433.53 | EK28: =+EB28+ED28+EF28+EE28 -> 110433.53
B29: Friendly Home Service Group | C29: RFE Investment Partners | DC29: =DF29-DD29 -> 0 | DD29: =SUMIFS('Sep 25 Inv'!H:H,'Sep 25 Inv'!E:E,'Summary Rollforward'!$B29) -> 0 | DE29: =-SUMIFS('Sep25 Dep'!J:J,'Sep25 Dep'!F:F,'Summary Rollforward'!$B29) -> 0 | DF29: =SUMIFS('Contract Data'!IT:IT,'Contract Data'!$C:$C,'Summary Rollforward'!$B29) -> 0 | DH29: =+CY29+DD29+DE29 -> 0 | DI29: =+DJ29-DH29 -> 0 | DJ29: =+DA29+DC29+DE29+DD29 -> 0 | DL29: =DO29-DM29 -> 0 | DM29: =SUMIFS('Oct 25 Inv'!H:H,'Oct 25 Inv'!E:E,'Summary Rollforward'!$B29) -> 0 | DN29: =-SUMIFS('Oct25 Dep'!J:J,'Oct25 Dep'!F:F,'Summary Rollforward'!$B29) -> 0 | DO29: =SUMIFS('Contract Data'!IU:IU,'Contract Data'!$C:$C,'Summary Rollforward'!$B29) -> 0 | DQ29: =+DH29+DM29+DN29 -> 0 | DR29: =+DS29-DQ29 -> 0 | DS29: =+DJ29+DL29+DN29+DM29 -> 0 | DU29: =DX29-DV29 -> 0 | DV29: =SUMIFS('Nov 25 Inv'!H:H,'Nov 25 Inv'!E:E,'Summary Rollforward'!$B29) -> 0 | DW29: =-SUMIFS('Nov25 Dep'!J:J,'Nov25 Dep'!F:F,'Summary Rollforward'!$B29) -> 0 | DX29: =SUMIFS('Contract Data'!IV:IV,'Contract Data'!$C:$C,'Summary Rollforward'!$B29) -> 0 | DZ29: =+DQ29+DV29+DW29 -> 0 | EA29: =+EB29-DZ29 -> 0 | EB29: =+DS29+DU29+DW29+DV29 -> 0 | ED29: =EG29-EE29 -> 20792.94 | EE29: =SUMIFS('Dec 25 Inv'!H:H,'Dec 25 Inv'!E:E,'Summary Rollforward'!$B29) -> 0 | EF29: =-SUMIFS('Dec25 Dep'!I:I,'Dec25 Dep'!F:F,'Summary Rollforward'!$B29) -> 0 | EG29: =SUMIFS('Contract Data'!IW:IW,'Contract Data'!$C:$C,'Summary Rollforward'!$B29) -> 20792.94 | EI29: =+DZ29+EE29+EF29 -> 0 | EJ29: =+EK29-EI29 -> 20792.94 | EK29: =+EB29+ED29+EF29+EE29 -> 20792.94
B30: Genova Diagnostics | C30: LLCP | E30: =+'Aug 31'!G8 -> 50000 | F30: =+G30-E30 -> 83215.992 | G30: =+'AR Calculation - Service'!AM77 -> 133215.99 | I30: =+'AR Calculation - Service'!AN76 -> 94220 | L30: =+'Sep 30'!G10 -> 50000 | M30: =+N30-L30 -> 177435.99 | N30: =+G30+I30+J30 -> 227435.99 | P30: 10208.75 | S30: =+'Oct 31'!G10 -> 50000 | T30: =+U30-S30 -> 187644.74 | U30: =+N30+P30+Q30 -> 237644.74 | W30: 0 | X30: =+'Nov Collections'!I12 -> -50000 | Z30: =+'Oct 31'!N10 -> 0 | AA30: =+AB30-Z30 -> 187644.74 | AB30: =+U30+W30+X30 -> 187644.74 | AD30: =+'AR Calculation - Service'!AQ76 -> 2436 | AG30: =+'Nov Collections'!P12 -> 0 | AI30: =+'Oct 31'!R10 -> 0 | AJ30: =+AK30-AI30 -> 190080.74 | AK30: =+AB30+AD30+AG30+AF30+AE30 -> 190080.74 | AM30: 0 | AO30: =-'Oct Collections'!AF18-'Oct Collections'!AF19 -> 0 | AQ30: =+AI30+AN30+AO30 -> 0 | AR30: =+AS30-AQ30 -> 190080.74 | AS30: =+AK30+AM30+AO30+AN30 -> 190080.74 | AU30: 0 | AW30: =-'Oct Collections'!AN18-'Oct Collections'!AN19 -> 0 | AY30: =+AQ30+AV30+AW30 -> 0 | AZ30: =+BA30-AY30 -> 190080.74 | BA30: =+AS30+AU30+AW30+AV30 -> 190080.74 | BC30: 0 | BG30: =+AY30+BD30+BE30 -> 0 | BH30: =+BI30-BG30 -> 190080.74 | BI30: =+BA30+BC30+BE30+BD30 -> 190080.74 | BO30: =+BG30+BL30+BM30 -> 0 | BP30: =+BQ30-BO30 -> 190080.74 | BQ30: =+BI30+BK30+BM30+BL30 -> 190080.74 | BS30: =BV30-BT30 -> -87500 | BT30: 87500 | BU30: 0 | BV30: =SUMIFS('Contract Data'!IP:IP,'Contract Data'!C:C,'Summary Rollforward'!B30) -> 0 | BX30: =+BO30+BT30+BU30 -> 87500 | BY30: =+BZ30-BX30 -> 102580.74 | BZ30: =+BQ30+BS30+BU30+BT30 -> 190080.74 | CB30: =CE30-CC30 -> -15080.742 | CC30: =SUMIFS('June 25 Inv'!G:G,'June 25 Inv'!D:D,'Summary Rollforward'!$B30) -> 0 | CD30: =-SUMIFS('Jun25 Dep'!I:I,'Jun25 Dep'!F:F,'Summary Rollforward'!$B30) -> -87500 | CE30: =SUMIFS('Contract Data'!IQ:IQ,'Contract Data'!$C:$C,'Summary Rollforward'!$B30) -> -15080.742 | CG30: =+BX30+CC30+CD30 -> 0 | CH30: =+CI30-CG30 -> 87500 | CI30: =+BZ30+CB30+CD30+CC30 -> 87500 | CK30: =CN30-CL30 -> 0 | CL30: =SUMIFS('Jul 25 Inv'!H:H,'Jul 25 Inv'!E:E,'Summary Rollforward'!$B30) -> 0 | CM30: =-SUMIFS('Jul25 Dep'!J:J,'Jul25 Dep'!F:F,'Summary Rollforward'!$B30) -> 0 | CN30: =SUMIFS('Contract Data'!IR:IR,'Contract Data'!$C:$C,'Summary Rollforward'!$B30) -> 0 | CP30: =+CG30+CL30+CM30 -> 0 | CQ30: =+CR30-CP30 -> 87500 | CR30: =+CI30+CK30+CM30+CL30 -> 87500 | CT30: =CW30-CU30 -> 0 | CU30: =SUMIFS('Aug 25 Inv'!H:H,'Aug 25 Inv'!E:E,'Summary Rollforward'!$B30) -> 0 | CV30: =-SUMIFS('Aug25 Dep'!J:J,'Aug25 Dep'!F:F,'Summary Rollforward'!$B30) -> 0 | CW30: =SUMIFS('Contract Data'!IS:IS,'Contract Data'!$C:$C,'Summary Rollforward'!$B30) -> 0 | CY30: =+CP30+CU30+CV30 -> 0 | CZ30: =+DA30-CY30 -> 87500 | DA30: =+CR30+CT30+CV30+CU30 -> 87500 | DC30: =DF30-DD30 -> 0 | DD30: =SUMIFS('Sep 25 Inv'!H:H,'Sep 25 Inv'!E:E,'Summary Rollforward'!$B30) -> 0 | DE30: =-SUMIFS('Sep25 Dep'!J:J,'Sep25 Dep'!F:F,'Summary Rollforward'!$B30) -> 0 | DF30: =SUMIFS('Contract Data'!IT:IT,'Contract Data'!$C:$C,'Summary Rollforward'!$B30) -> 0 | DH30: =+CY30+DD30+DE30 -> 0 | DI30: =+DJ30-DH30 -> 87500 | DJ30: =+DA30+DC30+DE30+DD30 -> 87500 | DL30: =DO30-DM30 -> 0 | DM30: =SUMIFS('Oct 25 Inv'!H:H,'Oct 25 Inv'!E:E,'Summary Rollforward'!$B30) -> 0 | DN30: =-SUMIFS('Oct25 Dep'!J:J,'Oct25 Dep'!F:F,'Summary Rollforward'!$B30) -> 0 | DO30: =SUMIFS('Contract Data'!IU:IU,'Contract Data'!$C:$C,'Summary Rollforward'!$B30) -> 0 | DQ30: =+DH30+DM30+DN30 -> 0 | DR30: =+DS30-DQ30 -> 87500 | DS30: =+DJ30+DL30+DN30+DM30 -> 87500 | DU30: =DX30-DV30 -> -87500 | DV30: =SUMIFS('Nov 25 Inv'!H:H,'Nov 25 Inv'!E:E,'Summary Rollforward'!$B30) -> 87500 | DW30: =-SUMIFS('Nov25 Dep'!J:J,'Nov25 Dep'!F:F,'Summary Rollforward'!$B30) -> 0 | DX30: =SUMIFS('Contract Data'!IV:IV,'Contract Data'!$C:$C,'Summary Rollforward'!$B30) -> 0 | DZ30: =+DQ30+DV30+DW30 -> 87500 | EA30: =+EB30-DZ30 -> 0 | EB30: =+DS30+DU30+DW30+DV30 -> 87500 | ED30: =EG30-EE30 -> 0 | EE30: =SUMIFS('Dec 25 Inv'!H:H,'Dec 25 Inv'!E:E,'Summary Rollforward'!$B30) -> 0 | EF30: =-SUMIFS('Dec25 Dep'!I:I,'Dec25 Dep'!F:F,'Summary Rollforward'!$B30) -> 0 | EG30: =SUMIFS('Contract Data'!IW:IW,'Contract Data'!$C:$C,'Summary Rollforward'!$B30) -> 0 | EI30: =+DZ30+EE30+EF30 -> 87500 | EJ30: =+EK30-EI30 -> 0 | EK30: =+EB30+ED30+EF30+EE30 -> 87500
B31: Greenrise Technologies | C31: Boyne Capital | F31: =+G31-E31 -> 72705.6 | G31: =+'AR Calculation - Service'!AM81 -> 72705.6 | M31: =+N31-L31 -> 72705.6 | N31: =+G31+I31+J31 -> 72705.6 | S31: 0 | T31: =+U31-S31 -> 72705.6 | U31: =+N31+P31+Q31 -> 72705.6 | W31: 0 | Z31: 0 | AA31: =+AB31-Z31 -> 72705.6 | AB31: =+U31+W31+X31 -> 72705.6 | AD31: =+'AR Calculation - Service'!AQ80 -> 258386 | AI31: 0 | AJ31: =+AK31-AI31 -> 331091.6 | AK31: =+AB31+AD31+AG31+AF31+AE31 -> 331091.6 | AM31: 0 | AO31: =-'Oct Collections'!AF19-'Oct Collections'!AF20 -> 0 | AQ31: =+AI31+AN31+AO31 -> 0 | AR31: =+AS31-AQ31 -> 331091.6 | AS31: =+AK31+AM31+AO31+AN31 -> 331091.6 | AU31: 0 | AW31: =-'Oct Collections'!AN19-'Oct Collections'!AN20 -> 0 | AY31: =+AQ31+AV31+AW31 -> 0 | AZ31: =+BA31-AY31 -> 331091.6 | BA31: =+AS31+AU31+AW31+AV31 -> 331091.6 | BC31: 0 | BG31: =+AY31+BD31+BE31 -> 0 | BH31: =+BI31-BG31 -> 331091.6 | BI31: =+BA31+BC31+BE31+BD31 -> 331091.6 | BO31: =+BG31+BL31+BM31 -> 0 | BP31: =+BQ31-BO31 -> 331091.6 | BQ31: =+BI31+BK31+BM31+BL31 -> 331091.6 | BS31: =BV31-BT31 -> 0 | BT31: 0 | BU31: 0 | BV31: =SUMIFS('Contract Data'!IP:IP,'Contract Data'!C:C,'Summary Rollforward'!B31) -> 0 | BX31: =+BO31+BT31+BU31 -> 0 | BY31: =+BZ31-BX31 -> 331091.6 | BZ31: =+BQ31+BS31+BU31+BT31 -> 331091.6 | CB31: =CE31-CC31 -> 0 | CC31: =SUMIFS('June 25 Inv'!G:G,'June 25 Inv'!D:D,'Summary Rollforward'!$B31) -> 0 | CD31: =-SUMIFS('Jun25 Dep'!I:I,'Jun25 Dep'!F:F,'Summary Rollforward'!$B31) -> 0 | CE31: =SUMIFS('Contract Data'!IQ:IQ,'Contract Data'!$C:$C,'Summary Rollforward'!$B31) -> 0 | CG31: =+BX31+CC31+CD31 -> 0 | CH31: =+CI31-CG31 -> 331091.6 | CI31: =+BZ31+CB31+CD31+CC31 -> 331091.6 | CK31: =CN31-CL31 -> -108364 | CL31: =SUMIFS('Jul 25 Inv'!H:H,'Jul 25 Inv'!E:E,'Summary Rollforward'!$B31) -> 108364 | CM31: =-SUMIFS('Jul25 Dep'!J:J,'Jul25 Dep'!F:F,'Summary Rollforward'!$B31) -> 0 | CN31: =SUMIFS('Contract Data'!IR:IR,'Contract Data'!$C:$C,'Summary Rollforward'!$B31) -> 0 | CP31: =+CG31+CL31+CM31 -> 108364 | CQ31: =+CR31-CP31 -> 222727.6 | CR31: =+CI31+CK31+CM31+CL31 -> 331091.6 | CT31: =CW31-CU31 -> 0 | CU31: =SUMIFS('Aug 25 Inv'!H:H,'Aug 25 Inv'!E:E,'Summary Rollforward'!$B31) -> 0 | CV31: =-SUMIFS('Aug25 Dep'!J:J,'Aug25 Dep'!F:F,'Summary Rollforward'!$B31) -> -81273 | CW31: =SUMIFS('Contract Data'!IS:IS,'Contract Data'!$C:$C,'Summary Rollforward'!$B31) -> 0 | CY31: =+CP31+CU31+CV31 -> 27091 | CZ31: =+DA31-CY31 -> 222727.6 | DA31: =+CR31+CT31+CV31+CU31 -> 249818.6 | DC31: =DF31-DD31 -> 0 | DD31: =SUMIFS('Sep 25 Inv'!H:H,'Sep 25 Inv'!E:E,'Summary Rollforward'!$B31) -> 0 | DE31: =-SUMIFS('Sep25 Dep'!J:J,'Sep25 Dep'!F:F,'Summary Rollforward'!$B31) -> -27091 | DF31: =SUMIFS('Contract Data'!IT:IT,'Contract Data'!$C:$C,'Summary Rollforward'!$B31) -> 0 | DH31: =+CY31+DD31+DE31 -> 0 | DI31: =+DJ31-DH31 -> 222727.6 | DJ31: =+DA31+DC31+DE31+DD31 -> 222727.6 | DL31: =DO31-DM31 -> 0 | DM31: =SUMIFS('Oct 25 Inv'!H:H,'Oct 25 Inv'!E:E,'Summary Rollforward'!$B31) -> 0 | DN31: =-SUMIFS('Oct25 Dep'!J:J,'Oct25 Dep'!F:F,'Summary Rollforward'!$B31) -> 0 | DO31: =SUMIFS('Contract Data'!IU:IU,'Contract Data'!$C:$C,'Summary Rollforward'!$B31) -> 0 | DQ31: =+DH31+DM31+DN31 -> 0 | DR31: =+DS31-DQ31 -> 222727.6 | DS31: =+DJ31+DL31+DN31+DM31 -> 222727.6 | DU31: =DX31-DV31 -> -88611 | DV31: =SUMIFS('Nov 25 Inv'!H:H,'Nov 25 Inv'!E:E,'Summary Rollforward'!$B31) -> 88611 | DW31: =-SUMIFS('Nov25 Dep'!J:J,'Nov25 Dep'!F:F,'Summary Rollforward'!$B31) -> 0 | DX31: =SUMIFS('Contract Data'!IV:IV,'Contract Data'!$C:$C,'Summary Rollforward'!$B31) -> 0 | DZ31: =+DQ31+DV31+DW31 -> 88611 | EA31: =+EB31-DZ31 -> 134116.6 | EB31: =+DS31+DU31+DW31+DV31 -> 222727.6 | ED31: =EG31-EE31 -> 0 | EE31: =SUMIFS('Dec 25 Inv'!H:H,'Dec 25 Inv'!E:E,'Summary Rollforward'!$B31) -> 0 | EF31: =-SUMIFS('Dec25 Dep'!I:I,'Dec25 Dep'!F:F,'Summary Rollforward'!$B31) -> 0 | EG31: =SUMIFS('Contract Data'!IW:IW,'Contract Data'!$C:$C,'Summary Rollforward'!$B31) -> 0 | EI31: =+DZ31+EE31+EF31 -> 88611 | EJ31: =+EK31-EI31 -> 134116.6 | EK31: =+EB31+ED31+EF31+EE31 -> 222727.6
B32: GLOBO Language Solutions | C32: VSS Capital | AQ32: =+AI32+AN32+AO32 -> 0 | AR32: =+AS32-AQ32 -> 0 | AS32: =+AK32+AM32+AO32+AN32 -> 0 | AU32: =+'AR Calculation - Service'!AS349 -> 7750 | AV32: 0 | AY32: =+AQ32+AV32+AW32 -> 0 | AZ32: =+BA32-AY32 -> 7750 | BA32: =+AS32+AU32+AW32+AV32 -> 7750 | BC32: =+'AR Calculation - Service'!AT349-'Summary Rollforward'!BD32 -> -4500 | BD32: =+'Mar Invoices'!G20 -> 20000 | BG32: =+AY32+BD32+BE32 -> 20000 | BH32: =+BI32-BG32 -> 3250 | BI32: =+BA32+BC32+BE32+BD32 -> 23250 | BK32: =+'AR Calculation - Service'!AU349-'Summary Rollforward'!BL32 -> -4500 | BL32: =+'Apr Invoices'!G13 -> 20000 | BO32: =+BG32+BL32+BM32 -> 40000 | BP32: =+BQ32-BO32 -> -1250 | BQ32: =+BI32+BK32+BM32+BL32 -> 38750 | BS32: =BV32-BT32 -> 1156.7 | BT32: 20000 | BU32: 0 | BV32: =SUMIFS('Contract Data'!IP:IP,'Contract Data'!C:C,'Summary Rollforward'!B32) -> 21156.7 | BX32: =+BO32+BT32+BU32 -> 60000 | BY32: =+BZ32-BX32 -> -93.3 | BZ32: =+BQ32+BS32+BU32+BT32 -> 59906.7 | CB32: =CE32-CC32 -> 6813.4 | CC32: =SUMIFS('June 25 Inv'!G:G,'June 25 Inv'!D:D,'Summary Rollforward'!$B32) -> 20000 | CD32: =-SUMIFS('Jun25 Dep'!I:I,'Jun25 Dep'!F:F,'Summary Rollforward'!$B32) -> -60000 | CE32: =SUMIFS('Contract Data'!IQ:IQ,'Contract Data'!$C:$C,'Summary Rollforward'!$B32) -> 26813.4 | CG32: =+BX32+CC32+CD32 -> 20000 | CH32: =+CI32-CG32 -> 6720.1 | CI32: =+BZ32+CB32+CD32+CC32 -> 26720.1 | CK32: =CN32-CL32 -> 32405.9 | CL32: =SUMIFS('Jul 25 Inv'!H:H,'Jul 25 Inv'!E:E,'Summary Rollforward'!$B32) -> 20000 | CM32: =-SUMIFS('Jul25 Dep'!J:J,'Jul25 Dep'!F:F,'Summary Rollforward'!$B32) -> -20000 | CN32: =SUMIFS('Contract Data'!IR:IR,'Contract Data'!$C:$C,'Summary Rollforward'!$B32) -> 52405.9 | CP32: =+CG32+CL32+CM32 -> 20000 | CQ32: =+CR32-CP32 -> 39126 | CR32: =+CI32+CK32+CM32+CL32 -> 59126 | CT32: =CW32-CU32 -> 8454.7333 | CU32: =SUMIFS('Aug 25 Inv'!H:H,'Aug 25 Inv'!E:E,'Summary Rollforward'!$B32) -> 18336.6 | CV32: =-SUMIFS('Aug25 Dep'!J:J,'Aug25 Dep'!F:F,'Summary Rollforward'!$B32) -> -20000 | CW32: =SUMIFS('Contract Data'!IS:IS,'Contract Data'!$C:$C,'Summary Rollforward'!$B32) -> 26791.333 | CY32: =+CP32+CU32+CV32 -> 18336.6 | CZ32: =+DA32-CY32 -> 47580.733 | DA32: =+CR32+CT32+CV32+CU32 -> 65917.333 | DC32: =DF32-DD32 -> -4795.3333 | DD32: =SUMIFS('Sep 25 Inv'!H:H,'Sep 25 Inv'!E:E,'Summary Rollforward'!$B32) -> 0 | DE32: =-SUMIFS('Sep25 Dep'!J:J,'Sep25 Dep'!F:F,'Summary Rollforward'!$B32) -> -18336.6 | DF32: =SUMIFS('Contract Data'!IT:IT,'Contract Data'!$C:$C,'Summary Rollforward'!$B32) -> -4795.3333 | DH32: =+CY32+DD32+DE32 -> 0 | DI32: =+DJ32-DH32 -> 42785.4 | DJ32: =+DA32+DC32+DE32+DD32 -> 42785.4 | DL32: =DO32-DM32 -> -34804.8 | DM32: =SUMIFS('Oct 25 Inv'!H:H,'Oct 25 Inv'!E:E,'Summary Rollforward'!$B32) -> 34804.8 | DN32: =-SUMIFS('Oct25 Dep'!J:J,'Oct25 Dep'!F:F,'Summary Rollforward'!$B32) -> -34804.8 | DO32: =SUMIFS('Contract Data'!IU:IU,'Contract Data'!$C:$C,'Summary Rollforward'!$B32) -> 0 | DQ32: =+DH32+DM32+DN32 -> 0 | DR32: =+DS32-DQ32 -> 7980.6 | DS32: =+DJ32+DL32+DN32+DM32 -> 7980.6 | DU32: =DX32-DV32 -> -9204.57 | DV32: =SUMIFS('Nov 25 Inv'!H:H,'Nov 25 Inv'!E:E,'Summary Rollforward'!$B32) -> 9204.57 | DW32: =-SUMIFS('Nov25 Dep'!J:J,'Nov25 Dep'!F:F,'Summary Rollforward'!$B32) -> 0 | DX32: =SUMIFS('Contract Data'!IV:IV,'Contract Data'!$C:$C,'Summary Rollforward'!$B32) -> 0 | DZ32: =+DQ32+DV32+DW32 -> 9204.57 | EA32: =+EB32-DZ32 -> -1223.97 | EB32: =+DS32+DU32+DW32+DV32 -> 7980.6 | ED32: =EG32-EE32 -> 0 | EE32: =SUMIFS('Dec 25 Inv'!H:H,'Dec 25 Inv'!E:E,'Summary Rollforward'!$B32) -> 0 | EF32: =-SUMIFS('Dec25 Dep'!I:I,'Dec25 Dep'!F:F,'Summary Rollforward'!$B32) -> -9204.57 | EG32: =SUMIFS('Contract Data'!IW:IW,'Contract Data'!$C:$C,'Summary Rollforward'!$B32) -> 0 | EI32: =+DZ32+EE32+EF32 -> 0 | EJ32: =+EK32-EI32 -> -1223.97 | EK32: =+EB32+ED32+EF32+EE32 -> -1223.97
B33: Growth Orthopedics Services | BS33: =BV33-BT33 -> -15312.5 | BT33: 25000 | BU33: 0 | BV33: =SUMIFS('Contract Data'!IP:IP,'Contract Data'!C:C,'Summary Rollforward'!B33) -> 9687.5 | BX33: =+BO33+BT33+BU33 -> 25000 | BY33: =+BZ33-BX33 -> -15312.5 | BZ33: =+BQ33+BS33+BU33+BT33 -> 9687.5 | CB33: =CE33-CC33 -> -5625 | CC33: =SUMIFS('June 25 Inv'!G:G,'June 25 Inv'!D:D,'Summary Rollforward'!$B33) -> 25000 | CD33: =-SUMIFS('Jun25 Dep'!I:I,'Jun25 Dep'!F:F,'Summary Rollforward'!$B33) -> 0 | CE33: =SUMIFS('Contract Data'!IQ:IQ,'Contract Data'!$C:$C,'Summary Rollforward'!$B33) -> 19375 | CG33: =+BX33+CC33+CD33 -> 50000 | CH33: =+CI33-CG33 -> -20937.5 | CI33: =+BZ33+CB33+CD33+CC33 -> 29062.5 | CK33: =CN33-CL33 -> -5625 | CL33: =SUMIFS('Jul 25 Inv'!H:H,'Jul 25 Inv'!E:E,'Summary Rollforward'!$B33) -> 25000 | CM33: =-SUMIFS('Jul25 Dep'!J:J,'Jul25 Dep'!F:F,'Summary Rollforward'!$B33) -> 0 | CN33: =SUMIFS('Contract Data'!IR:IR,'Contract Data'!$C:$C,'Summary Rollforward'!$B33) -> 19375 | CP33: =+CG33+CL33+CM33 -> 75000 | CQ33: =+CR33-CP33 -> -26562.5 | CR33: =+CI33+CK33+CM33+CL33 -> 48437.5 | CT33: =CW33-CU33 -> 627 | CU33: =SUMIFS('Aug 25 Inv'!H:H,'Aug 25 Inv'!E:E,'Summary Rollforward'!$B33) -> 25000 | CV33: =-SUMIFS('Aug25 Dep'!J:J,'Aug25 Dep'!F:F,'Summary Rollforward'!$B33) -> -50000 | CW33: =SUMIFS('Contract Data'!IS:IS,'Contract Data'!$C:$C,'Summary Rollforward'!$B33) -> 25627 | CY33: =+CP33+CU33+CV33 -> 50000 | CZ33: =+DA33-CY33 -> -25935.5 | DA33: =+CR33+CT33+CV33+CU33 -> 24064.5 | DC33: =DF33-DD33 -> 16254 | DD33: =SUMIFS('Sep 25 Inv'!H:H,'Sep 25 Inv'!E:E,'Summary Rollforward'!$B33) -> 25000 | DE33: =-SUMIFS('Sep25 Dep'!J:J,'Sep25 Dep'!F:F,'Summary Rollforward'!$B33) -> 0 | DF33: =SUMIFS('Contract Data'!IT:IT,'Contract Data'!$C:$C,'Summary Rollforward'!$B33) -> 41254 | DH33: =+CY33+DD33+DE33 -> 75000 | DI33: =+DJ33-DH33 -> -9681.5 | DJ33: =+DA33+DC33+DE33+DD33 -> 65318.5 | DL33: =DO33-DM33 -> 20000 | DM33: =SUMIFS('Oct 25 Inv'!H:H,'Oct 25 Inv'!E:E,'Summary Rollforward'!$B33) -> 0 | DN33: =-SUMIFS('Oct25 Dep'!J:J,'Oct25 Dep'!F:F,'Summary Rollforward'!$B33) -> 0 | DO33: =SUMIFS('Contract Data'!IU:IU,'Contract Data'!$C:$C,'Summary Rollforward'!$B33) -> 20000 | DQ33: =+DH33+DM33+DN33 -> 75000 | DR33: =+DS33-DQ33 -> 10318.5 | DS33: =+DJ33+DL33+DN33+DM33 -> 85318.5 | DU33: =DX33-DV33 -> 29375 | DV33: =SUMIFS('Nov 25 Inv'!H:H,'Nov 25 Inv'!E:E,'Summary Rollforward'!$B33) -> 0 | DW33: =-SUMIFS('Nov25 Dep'!J:J,'Nov25 Dep'!F:F,'Summary Rollforward'!$B33) -> -25000 | DX33: =SUMIFS('Contract Data'!IV:IV,'Contract Data'!$C:$C,'Summary Rollforward'!$B33) -> 29375 | DZ33: =+DQ33+DV33+DW33 -> 50000 | EA33: =+EB33-DZ33 -> 39693.5 | EB33: =+DS33+DU33+DW33+DV33 -> 89693.5 | ED33: =EG33-EE33 -> 19687.5 | EE33: =SUMIFS('Dec 25 Inv'!H:H,'Dec 25 Inv'!E:E,'Summary Rollforward'!$B33) -> 0 | EF33: =-SUMIFS('Dec25 Dep'!I:I,'Dec25 Dep'!F:F,'Summary Rollforward'!$B33) -> -50000 | EG33: =SUMIFS('Contract Data'!IW:IW,'Contract Data'!$C:$C,'Summary Rollforward'!$B33) -> 19687.5 | EI33: =+DZ33+EE33+EF33 -> 0 | EJ33: =+EK33-EI33 -> 59381 | EK33: =+EB33+ED33+EF33+EE33 -> 59381
B34: Heart & Vascular Partners | C34: Assured Health Care Partners | BC34: =+'AR Calculation - Service'!AT373 -> 22088 | BH34: =+BI34-BG34 -> 22088 | BI34: =+BA34+BC34+BE34+BD34 -> 22088 | BK34: =+'AR Calculation - Service'!AU373-'Summary Rollforward'!BL34 -> -12825 | BL34: =+'Apr Invoices'!G15 -> 57000 | BO34: =+BG34+BL34+BM34 -> 57000 | BP34: =+BQ34-BO34 -> 9263 | BQ34: =+BI34+BK34+BM34+BL34 -> 66263 | BS34: =BV34-BT34 -> -12825 | BT34: 57000 | BU34: 0 | BV34: =SUMIFS('Contract Data'!IP:IP,'Contract Data'!C:C,'Summary Rollforward'!B34) -> 44175 | BX34: =+BO34+BT34+BU34 -> 114000 | BY34: =+BZ34-BX34 -> -3562 | BZ34: =+BQ34+BS34+BU34+BT34 -> 110438 | CB34: =CE34-CC34 -> -12825 | CC34: =SUMIFS('June 25 Inv'!G:G,'June 25 Inv'!D:D,'Summary Rollforward'!$B34) -> 57000 | CD34: =-SUMIFS('Jun25 Dep'!I:I,'Jun25 Dep'!F:F,'Summary Rollforward'!$B34) -> 0 | CE34: =SUMIFS('Contract Data'!IQ:IQ,'Contract Data'!$C:$C,'Summary Rollforward'!$B34) -> 44175 | CG34: =+BX34+CC34+CD34 -> 171000 | CH34: =+CI34-CG34 -> -16387 | CI34: =+BZ34+CB34+CD34+CC34 -> 154613 | CK34: =CN34-CL34 -> -12825 | CL34: =SUMIFS('Jul 25 Inv'!H:H,'Jul 25 Inv'!E:E,'Summary Rollforward'!$B34) -> 57000 | CM34: =-SUMIFS('Jul25 Dep'!J:J,'Jul25 Dep'!F:F,'Summary Rollforward'!$B34) -> -57000 | CN34: =SUMIFS('Contract Data'!IR:IR,'Contract Data'!$C:$C,'Summary Rollforward'!$B34) -> 44175 | CP34: =+CG34+CL34+CM34 -> 171000 | CQ34: =+CR34-CP34 -> -29212 | CR34: =+CI34+CK34+CM34+CL34 -> 141788 | CT34: =CW34-CU34 -> -12825 | CU34: =SUMIFS('Aug 25 Inv'!H:H,'Aug 25 Inv'!E:E,'Summary Rollforward'!$B34) -> 57000 | CV34: =-SUMIFS('Aug25 Dep'!J:J,'Aug25 Dep'!F:F,'Summary Rollforward'!$B34) -> -114000 | CW34: =SUMIFS('Contract Data'!IS:IS,'Contract Data'!$C:$C,'Summary Rollforward'!$B34) -> 44175 | CY34: =+CP34+CU34+CV34 -> 114000 | CZ34: =+DA34-CY34 -> -42037 | DA34: =+CR34+CT34+CV34+CU34 -> 71963 | DC34: =DF34-DD34 -> 22087.5 | DD34: =SUMIFS('Sep 25 Inv'!H:H,'Sep 25 Inv'!E:E,'Summary Rollforward'!$B34) -> 0 | DE34: =-SUMIFS('Sep25 Dep'!J:J,'Sep25 Dep'!F:F,'Summary Rollforward'!$B34) -> 0 | DF34: =SUMIFS('Contract Data'!IT:IT,'Contract Data'!$C:$C,'Summary Rollforward'!$B34) -> 22087.5 | DH34: =+CY34+DD34+DE34 -> 114000 | DI34: =+DJ34-DH34 -> -19949.5 | DJ34: =+DA34+DC34+DE34+DD34 -> 94050.5 | DL34: =DO34-DM34 -> 19950 | DM34: =SUMIFS('Oct 25 Inv'!H:H,'Oct 25 Inv'!E:E,'Summary Rollforward'!$B34) -> 0 | DN34: =-SUMIFS('Oct25 Dep'!J:J,'Oct25 Dep'!F:F,'Summary Rollforward'!$B34) -> -57000 | DO34: =SUMIFS('Contract Data'!IU:IU,'Contract Data'!$C:$C,'Summary Rollforward'!$B34) -> 19950 | DQ34: =+DH34+DM34+DN34 -> 57000 | DR34: =+DS34-DQ34 -> 0.5 | DS34: =+DJ34+DL34+DN34+DM34 -> 57000.5 | DU34: =DX34-DV34 -> 0 | DV34: =SUMIFS('Nov 25 Inv'!H:H,'Nov 25 Inv'!E:E,'Summary Rollforward'!$B34) -> 0 | DW34: =-SUMIFS('Nov25 Dep'!J:J,'Nov25 Dep'!F:F,'Summary Rollforward'!$B34) -> 0 | DX34: =SUMIFS('Contract Data'!IV:IV,'Contract Data'!$C:$C,'Summary Rollforward'!$B34) -> 0 | DZ34: =+DQ34+DV34+DW34 -> 57000 | EA34: =+EB34-DZ34 -> 0.5 | EB34: =+DS34+DU34+DW34+DV34 -> 57000.5 | ED34: =EG34-EE34 -> 0 | EE34: =SUMIFS('Dec 25 Inv'!H:H,'Dec 25 Inv'!E:E,'Summary Rollforward'!$B34) -> 0 | EF34: =-SUMIFS('Dec25 Dep'!I:I,'Dec25 Dep'!F:F,'Summary Rollforward'!$B34) -> 0 | EG34: =SUMIFS('Contract Data'!IW:IW,'Contract Data'!$C:$C,'Summary Rollforward'!$B34) -> 0 | EI34: =+DZ34+EE34+EF34 -> 57000 | EJ34: =+EK34-EI34 -> 0.5 | EK34: =+EB34+ED34+EF34+EE34 -> 57000.5
B35: HFW Companies | C35: VSS Capital | CK35: =CN35-CL35 -> -18375 | CL35: =SUMIFS('Jul 25 Inv'!H:H,'Jul 25 Inv'!E:E,'Summary Rollforward'!$B35) -> 30000 | CM35: =-SUMIFS('Jul25 Dep'!J:J,'Jul25 Dep'!F:F,'Summary Rollforward'!$B35) -> 0 | CN35: =SUMIFS('Contract Data'!IR:IR,'Contract Data'!$C:$C,'Summary Rollforward'!$B35) -> 11625 | CP35: =+CG35+CL35+CM35 -> 30000 | CQ35: =+CR35-CP35 -> -18375 | CR35: =+CI35+CK35+CM35+CL35 -> 11625 | CT35: =CW35-CU35 -> -6750 | CU35: =SUMIFS('Aug 25 Inv'!H:H,'Aug 25 Inv'!E:E,'Summary Rollforward'!$B35) -> 30000 | CV35: =-SUMIFS('Aug25 Dep'!J:J,'Aug25 Dep'!F:F,'Summary Rollforward'!$B35) -> 0 | CW35: =SUMIFS('Contract Data'!IS:IS,'Contract Data'!$C:$C,'Summary Rollforward'!$B35) -> 23250 | CY35: =+CP35+CU35+CV35 -> 60000 | CZ35: =+DA35-CY35 -> -25125 | DA35: =+CR35+CT35+CV35+CU35 -> 34875 | DC35: =DF35-DD35 -> -6750 | DD35: =SUMIFS('Sep 25 Inv'!H:H,'Sep 25 Inv'!E:E,'Summary Rollforward'!$B35) -> 30000 | DE35: =-SUMIFS('Sep25 Dep'!J:J,'Sep25 Dep'!F:F,'Summary Rollforward'!$B35) -> -60000 | DF35: =SUMIFS('Contract Data'!IT:IT,'Contract Data'!$C:$C,'Summary Rollforward'!$B35) -> 23250 | DH35: =+CY35+DD35+DE35 -> 30000 | DI35: =+DJ35-DH35 -> -31875 | DJ35: =+DA35+DC35+DE35+DD35 -> -1875 | DL35: =DO35-DM35 -> -6750 | DM35: =SUMIFS('Oct 25 Inv'!H:H,'Oct 25 Inv'!E:E,'Summary Rollforward'!$B35) -> 30000 | DN35: =-SUMIFS('Oct25 Dep'!J:J,'Oct25 Dep'!F:F,'Summary Rollforward'!$B35) -> -30000 | DO35: =SUMIFS('Contract Data'!IU:IU,'Contract Data'!$C:$C,'Summary Rollforward'!$B35) -> 23250 | DQ35: =+DH35+DM35+DN35 -> 30000 | DR35: =+DS35-DQ35 -> -38625 | DS35: =+DJ35+DL35+DN35+DM35 -> -8625 | DU35: =DX35-DV35 -> -11100 | DV35: =SUMIFS('Nov 25 Inv'!H:H,'Nov 25 Inv'!E:E,'Summary Rollforward'!$B35) -> 30000 | DW35: =-SUMIFS('Nov25 Dep'!J:J,'Nov25 Dep'!F:F,'Summary Rollforward'!$B35) -> -30000 | DX35: =SUMIFS('Contract Data'!IV:IV,'Contract Data'!$C:$C,'Summary Rollforward'!$B35) -> 18900 | DZ35: =+DQ35+DV35+DW35 -> 30000 | EA35: =+EB35-DZ35 -> -49725 | EB35: =+DS35+DU35+DW35+DV35 -> -19725 | ED35: =EG35-EE35 -> 27800 | EE35: =SUMIFS('Dec 25 Inv'!H:H,'Dec 25 Inv'!E:E,'Summary Rollforward'!$B35) -> 3428.42 | EF35: =-SUMIFS('Dec25 Dep'!I:I,'Dec25 Dep'!F:F,'Summary Rollforward'!$B35) -> -30000 | EG35: =SUMIFS('Contract Data'!IW:IW,'Contract Data'!$C:$C,'Summary Rollforward'!$B35) -> 31228.42 | EI35: =+DZ35+EE35+EF35 -> 3428.42 | EJ35: =+EK35-EI35 -> -21925 | EK35: =+EB35+ED35+EF35+EE35 -> -18496.58
B36: Hytek | C36: Dunes Point | P36: 66262.5 | S36: =+'Oct 31'!G11 -> 57000 | U36: =+N36+P36+Q36 -> 66262.5 | W36: =+'AR Calculation - Service'!AP317 -> 44175 | Z36: =+'Nov 30'!G11 -> 114000 | AA36: =+AB36-Z36 -> -3562.5 | AB36: =+U36+W36+X36 -> 110437.5 | AD36: =+'AR Calculation - Service'!AQ317-AE36 -> 7654.5 | AE36: =+'Dec Invoicing'!I11 -> 57000 | AG36: =+'AR Calculation - Service'!AQ316 -> -57000 | AI36: =+'Dec 31'!G12 -> 114000 | AJ36: =+AK36-AI36 -> 4092 | AK36: =+AB36+AD36+AG36+AF36+AE36 -> 118092 | AM36: =+'AR Calculation - Service'!AR317-'Summary Rollforward'!AN36 -> -17237 | AN36: =+'Jan Invoicing'!G8 -> 64737 | AO36: =+'AR Calculation - Service'!AR316 -> -114000 | AQ36: =+AI36+AN36+AO36 -> 64737 | AR36: =+AS36-AQ36 -> -13145 | AS36: =+AK36+AM36+AO36+AN36 -> 51592 | AU36: =+'AR Calculation - Service'!AS317-'Summary Rollforward'!AV36 -> 47500 | AV36: =+'Jan Invoicing'!O8 -> 0 | AW36: =+'AR Calculation - Service'!BB316 -> 0 | AY36: =+AQ36+AV36+AW36 -> 64737 | AZ36: =+BA36-AY36 -> 34355 | BA36: =+AS36+AU36+AW36+AV36 -> 99092 | BC36: =+'AR Calculation - Service'!AT317-'Summary Rollforward'!BD36 -> -33250 | BD36: =+'Mar Invoices'!G8 -> 57000 | BE36: =+'AR Calculation - Service'!AT316 -> -64737 | BG36: =+AY36+BD36+BE36 -> 57000 | BH36: =+BI36-BG36 -> 1105 | BI36: =+BA36+BC36+BE36+BD36 -> 58105 | BM36: =+'AR Calculation - Service'!BB316 -> 0 | BO36: =+BG36+BL36+BM36 -> 57000 | BP36: =+BQ36-BO36 -> 1105 | BQ36: =+BI36+BK36+BM36+BL36 -> 58105 | BS36: =BV36-BT36 -> 0 | BT36: 0 | BU36: -57000 | BV36: =SUMIFS('Contract Data'!IP:IP,'Contract Data'!C:C,'Summary Rollforward'!B36) -> 0 | BX36: =+BO36+BT36+BU36 -> 0 | BY36: =+BZ36-BX36 -> 1105 | BZ36: =+BQ36+BS36+BU36+BT36 -> 1105 | CB36: =CE36-CC36 -> 0 | CC36: =SUMIFS('June 25 Inv'!G:G,'June 25 Inv'!D:D,'Summary Rollforward'!$B36) -> 0 | CD36: =-SUMIFS('Jun25 Dep'!I:I,'Jun25 Dep'!F:F,'Summary Rollforward'!$B36) -> 0 | CE36: =SUMIFS('Contract Data'!IQ:IQ,'Contract Data'!$C:$C,'Summary Rollforward'!$B36) -> 0 | CG36: =+BX36+CC36+CD36 -> 0 | CH36: =+CI36-CG36 -> 1105 | CI36: =+BZ36+CB36+CD36+CC36 -> 1105 | CK36: =CN36-CL36 -> 51922.5 | CL36: =SUMIFS('Jul 25 Inv'!H:H,'Jul 25 Inv'!E:E,'Summary Rollforward'!$B36) -> 0 | CM36: =-SUMIFS('Jul25 Dep'!J:J,'Jul25 Dep'!F:F,'Summary Rollforward'!$B36) -> 0 | CN36: =SUMIFS('Contract Data'!IR:IR,'Contract Data'!$C:$C,'Summary Rollforward'!$B36) -> 51922.5 | CP36: =+CG36+CL36+CM36 -> 0 | CQ36: =+CR36-CP36 -> 53027.5 | CR36: =+CI36+CK36+CM36+CL36 -> 53027.5 | CT36: =CW36-CU36 -> 51922.5 | CU36: =SUMIFS('Aug 25 Inv'!H:H,'Aug 25 Inv'!E:E,'Summary Rollforward'!$B36) -> 0 | CV36: =-SUMIFS('Aug25 Dep'!J:J,'Aug25 Dep'!F:F,'Summary Rollforward'!$B36) -> 0 | CW36: =SUMIFS('Contract Data'!IS:IS,'Contract Data'!$C:$C,'Summary Rollforward'!$B36) -> 51922.5 | CY36: =+CP36+CU36+CV36 -> 0 | CZ36: =+DA36-CY36 -> 104950 | DA36: =+CR36+CT36+CV36+CU36 -> 104950 | DC36: =DF36-DD36 -> 51922.5 | DD36: =SUMIFS('Sep 25 Inv'!H:H,'Sep 25 Inv'!E:E,'Summary Rollforward'!$B36) -> 0 | DE36: =-SUMIFS('Sep25 Dep'!J:J,'Sep25 Dep'!F:F,'Summary Rollforward'!$B36) -> 0 | DF36: =SUMIFS('Contract Data'!IT:IT,'Contract Data'!$C:$C,'Summary Rollforward'!$B36) -> 51922.5 | DH36: =+CY36+DD36+DE36 -> 0 | DI36: =+DJ36-DH36 -> 156872.5 | DJ36: =+DA36+DC36+DE36+DD36 -> 156872.5 | DL36: =DO36-DM36 -> -156872.5 | DM36: =SUMIFS('Oct 25 Inv'!H:H,'Oct 25 Inv'!E:E,'Summary Rollforward'!$B36) -> 204335.4 | DN36: =-SUMIFS('Oct25 Dep'!J:J,'Oct25 Dep'!F:F,'Summary Rollforward'!$B36) -> 0 | DO36: =SUMIFS('Contract Data'!IU:IU,'Contract Data'!$C:$C,'Summary Rollforward'!$B36) -> 47462.9 | DQ36: =+DH36+DM36+DN36 -> 204335.4 | DR36: =+DS36-DQ36 -> 0 | DS36: =+DJ36+DL36+DN36+DM36 -> 204335.4 | DU36: =DX36-DV36 -> 0 | DV36: =SUMIFS('Nov 25 Inv'!H:H,'Nov 25 Inv'!E:E,'Summary Rollforward'!$B36) -> 0 | DW36: =-SUMIFS('Nov25 Dep'!J:J,'Nov25 Dep'!F:F,'Summary Rollforward'!$B36) -> 0 | DX36: =SUMIFS('Contract Data'!IV:IV,'Contract Data'!$C:$C,'Summary Rollforward'!$B36) -> 0 | DZ36: =+DQ36+DV36+DW36 -> 204335.4 | EA36: =+EB36-DZ36 -> 0 | EB36: =+DS36+DU36+DW36+DV36 -> 204335.4 | ED36: =EG36-EE36 -> 0 | EE36: =SUMIFS('Dec 25 Inv'!H:H,'Dec 25 Inv'!E:E,'Summary Rollforward'!$B36) -> 0 | EF36: =-SUMIFS('Dec25 Dep'!I:I,'Dec25 Dep'!F:F,'Summary Rollforward'!$B36) -> -204335.4 | EG36: =SUMIFS('Contract Data'!IW:IW,'Contract Data'!$C:$C,'Summary Rollforward'!$B36) -> 0 | EI36: =+DZ36+EE36+EF36 -> 0 | EJ36: =+EK36-EI36 -> 0 | EK36: =+EB36+ED36+EF36+EE36 -> 0
B37: In-Place Machining Company | C37: LLCP | DL37: =DO37-DM37 -> -18375 | DM37: =SUMIFS('Oct 25 Inv'!H:H,'Oct 25 Inv'!E:E,'Summary Rollforward'!$B37) -> 30000 | DN37: =-SUMIFS('Oct25 Dep'!J:J,'Oct25 Dep'!F:F,'Summary Rollforward'!$B37) -> 0 | DO37: =SUMIFS('Contract Data'!IU:IU,'Contract Data'!$C:$C,'Summary Rollforward'!$B37) -> 11625 | DQ37: =+DH37+DM37+DN37 -> 30000 | DR37: =+DS37-DQ37 -> -18375 | DS37: =+DJ37+DL37+DN37+DM37 -> 11625 | DU37: =DX37-DV37 -> -6750 | DV37: =SUMIFS('Nov 25 Inv'!H:H,'Nov 25 Inv'!E:E,'Summary Rollforward'!$B37) -> 30000 | DW37: =-SUMIFS('Nov25 Dep'!J:J,'Nov25 Dep'!F:F,'Summary Rollforward'!$B37) -> 0 | DX37: =SUMIFS('Contract Data'!IV:IV,'Contract Data'!$C:$C,'Summary Rollforward'!$B37) -> 23250 | DZ37: =+DQ37+DV37+DW37 -> 60000 | EA37: =+EB37-DZ37 -> -25125 | EB37: =+DS37+DU37+DW37+DV37 -> 34875 | ED37: =EG37-EE37 -> -6750 | EE37: =SUMIFS('Dec 25 Inv'!H:H,'Dec 25 Inv'!E:E,'Summary Rollforward'!$B37) -> 30000 | EF37: =-SUMIFS('Dec25 Dep'!I:I,'Dec25 Dep'!F:F,'Summary Rollforward'!$B37) -> -30000 | EG37: =SUMIFS('Contract Data'!IW:IW,'Contract Data'!$C:$C,'Summary Rollforward'!$B37) -> 23250 | EI37: =+DZ37+EE37+EF37 -> 60000 | EJ37: =+EK37-EI37 -> -31875 | EK37: =+EB37+ED37+EF37+EE37 -> 28125
B38: Innovative Foodservice Group | C38: Trivest Partners | DC38: =DF38-DD38 -> -23062.5 | DD38: =SUMIFS('Sep 25 Inv'!H:H,'Sep 25 Inv'!E:E,'Summary Rollforward'!$B38) -> 25000 | DE38: =-SUMIFS('Sep25 Dep'!J:J,'Sep25 Dep'!F:F,'Summary Rollforward'!$B38) -> 0 | DF38: =SUMIFS('Contract Data'!IT:IT,'Contract Data'!$C:$C,'Summary Rollforward'!$B38) -> 1937.5 | DH38: =+CY38+DD38+DE38 -> 25000 | DI38: =+DJ38-DH38 -> -23062.5 | DJ38: =+DA38+DC38+DE38+DD38 -> 1937.5 | DL38: =DO38-DM38 -> 3875 | DM38: =SUMIFS('Oct 25 Inv'!H:H,'Oct 25 Inv'!E:E,'Summary Rollforward'!$B38) -> 0 | DN38: =-SUMIFS('Oct25 Dep'!J:J,'Oct25 Dep'!F:F,'Summary Rollforward'!$B38) -> 0 | DO38: =SUMIFS('Contract Data'!IU:IU,'Contract Data'!$C:$C,'Summary Rollforward'!$B38) -> 3875 | DQ38: =+DH38+DM38+DN38 -> 25000 | DR38: =+DS38-DQ38 -> -19187.5 | DS38: =+DJ38+DL38+DN38+DM38 -> 5812.5 | DU38: =DX38-DV38 -> 3875 | DV38: =SUMIFS('Nov 25 Inv'!H:H,'Nov 25 Inv'!E:E,'Summary Rollforward'!$B38) -> 0 | DW38: =-SUMIFS('Nov25 Dep'!J:J,'Nov25 Dep'!F:F,'Summary Rollforward'!$B38) -> -25000 | DX38: =SUMIFS('Contract Data'!IV:IV,'Contract Data'!$C:$C,'Summary Rollforward'!$B38) -> 3875 | DZ38: =+DQ38+DV38+DW38 -> 0 | EA38: =+EB38-DZ38 -> -15312.5 | EB38: =+DS38+DU38+DW38+DV38 -> -15312.5 | ED38: =EG38-EE38 -> 14075 | EE38: =SUMIFS('Dec 25 Inv'!H:H,'Dec 25 Inv'!E:E,'Summary Rollforward'!$B38) -> 0 | EF38: =-SUMIFS('Dec25 Dep'!I:I,'Dec25 Dep'!F:F,'Summary Rollforward'!$B38) -> 0 | EG38: =SUMIFS('Contract Data'!IW:IW,'Contract Data'!$C:$C,'Summary Rollforward'!$B38) -> 14075 | EI38: =+DZ38+EE38+EF38 -> 0 | EJ38: =+EK38-EI38 -> -1237.5 | EK38: =+EB38+ED38+EF38+EE38 -> -1237.5
B39: IPC Systems | DC39: =DF39-DD39 -> -33687.5 | DD39: =SUMIFS('Sep 25 Inv'!H:H,'Sep 25 Inv'!E:E,'Summary Rollforward'!$B39) -> 55000 | DE39: =-SUMIFS('Sep25 Dep'!J:J,'Sep25 Dep'!F:F,'Summary Rollforward'!$B39) -> 0 | DF39: =SUMIFS('Contract Data'!IT:IT,'Contract Data'!$C:$C,'Summary Rollforward'!$B39) -> 21312.5 | DH39: =+CY39+DD39+DE39 -> 55000 | DI39: =+DJ39-DH39 -> -33687.5 | DJ39: =+DA39+DC39+DE39+DD39 -> 21312.5 | DL39: =DO39-DM39 -> -12375 | DM39: =SUMIFS('Oct 25 Inv'!H:H,'Oct 25 Inv'!E:E,'Summary Rollforward'!$B39) -> 55000 | DN39: =-SUMIFS('Oct25 Dep'!J:J,'Oct25 Dep'!F:F,'Summary Rollforward'!$B39) -> 0 | DO39: =SUMIFS('Contract Data'!IU:IU,'Contract Data'!$C:$C,'Summary Rollforward'!$B39) -> 42625 | DQ39: =+DH39+DM39+DN39 -> 110000 | DR39: =+DS39-DQ39 -> -46062.5 | DS39: =+DJ39+DL39+DN39+DM39 -> 63937.5 | DU39: =DX39-DV39 -> -17000 | DV39: =SUMIFS('Nov 25 Inv'!H:H,'Nov 25 Inv'!E:E,'Summary Rollforward'!$B39) -> 55000 | DW39: =-SUMIFS('Nov25 Dep'!J:J,'Nov25 Dep'!F:F,'Summary Rollforward'!$B39) -> 0 | DX39: =SUMIFS('Contract Data'!IV:IV,'Contract Data'!$C:$C,'Summary Rollforward'!$B39) -> 38000 | DZ39: =+DQ39+DV39+DW39 -> 165000 | EA39: =+EB39-DZ39 -> -63062.5 | EB39: =+DS39+DU39+DW39+DV39 -> 101937.5 | ED39: =EG39-EE39 -> -15000 | EE39: =SUMIFS('Dec 25 Inv'!H:H,'Dec 25 Inv'!E:E,'Summary Rollforward'!$B39) -> 55000 | EF39: =-SUMIFS('Dec25 Dep'!I:I,'Dec25 Dep'!F:F,'Summary Rollforward'!$B39) -> 0 | EG39: =SUMIFS('Contract Data'!IW:IW,'Contract Data'!$C:$C,'Summary Rollforward'!$B39) -> 40000 | EI39: =+DZ39+EE39+EF39 -> 220000 | EJ39: =+EK39-EI39 -> -78062.5 | EK39: =+EB39+ED39+EF39+EE39 -> 141937.5
B40: K-1 Packaging Group | C40: Dunes Point | P40: 29062.5 | S40: =+'Oct 31'!G12 -> 75000 | T40: =+U40-S40 -> -45937.5 | U40: =+N40+P40+Q40 -> 29062.5 | W40: =+'AR Calculation - Service'!AP301 -> 75562.5 | Z40: =+'Nov 30'!G12 -> 75000 | AA40: =+AB40-Z40 -> 29625 | AB40: =+U40+W40+X40 -> 104625 | AD40: =+'AR Calculation - Service'!AQ301 -> 82875 | AG40: =+'AR Calculation - Service'!AQ300 -> -75000 | AI40: =+'Nov 30'!K12 -> 0 | AJ40: =+AK40-AI40 -> 112500 | AK40: =+AB40+AD40+AG40+AF40+AE40 -> 112500 | AM40: =+'AR Calculation - Service'!AR301-'Summary Rollforward'!AN40 -> -12500 | AN40: =+'Jan Invoicing'!G15 -> 75000 | AO40: =-'Oct Collections'!AF21-'Oct Collections'!AF22 -> 0 | AQ40: =+AI40+AN40+AO40 -> 75000 | AR40: =+AS40-AQ40 -> 100000 | AS40: =+AK40+AM40+AO40+AN40 -> 175000 | AU40: =+'AR Calculation - Service'!AS301-'Summary Rollforward'!AV40 -> 64796 | AV40: =+'Jan Invoicing'!O15 -> 0 | AW40: =-'Oct Collections'!AN21-'Oct Collections'!AN22 -> 0 | AY40: =+AQ40+AV40+AW40 -> 75000 | AZ40: =+BA40-AY40 -> 164796 | BA40: =+AS40+AU40+AW40+AV40 -> 239796 | BC40: =+'AR Calculation - Service'!AT301-'Summary Rollforward'!BD40 -> -14796 | BD40: =+'Mar Invoices'!G14 -> 77296 | BE40: =+'AR Calculation - Service'!AT300 -> -75000 | BG40: =+AY40+BD40+BE40 -> 77296 | BH40: =+BI40-BG40 -> 150000 | BI40: =+BA40+BC40+BE40+BD40 -> 227296 | BK40: =+'AR Calculation - Service'!AU301-'Summary Rollforward'!BL40 -> -75000 | BL40: =+'Apr Invoices'!G10 -> 75000 | BM40: =+'AR Calculation - Service'!AU300 -> -77296 | BO40: =+BG40+BL40+BM40 -> 75000 | BP40: =+BQ40-BO40 -> 75000 | BQ40: =+BI40+BK40+BM40+BL40 -> 150000 | BS40: =BV40-BT40 -> 0 | BT40: 0 | BU40: -75000 | BV40: =SUMIFS('Contract Data'!IP:IP,'Contract Data'!C:C,'Summary Rollforward'!B40) -> 0 | BX40: =+BO40+BT40+BU40 -> 0 | BY40: =+BZ40-BX40 -> 75000 | BZ40: =+BQ40+BS40+BU40+BT40 -> 75000 | CB40: =CE40-CC40 -> -75000 | CC40: =SUMIFS('June 25 Inv'!G:G,'June 25 Inv'!D:D,'Summary Rollforward'!$B40) -> 75000 | CD40: =-SUMIFS('Jun25 Dep'!I:I,'Jun25 Dep'!F:F,'Summary Rollforward'!$B40) -> 0 | CE40: =SUMIFS('Contract Data'!IQ:IQ,'Contract Data'!$C:$C,'Summary Rollforward'!$B40) -> 0 | CG40: =+BX40+CC40+CD40 -> 75000 | CH40: =+CI40-CG40 -> 0 | CI40: =+BZ40+CB40+CD40+CC40 -> 75000 | CK40: =CN40-CL40 -> 0 | CL40: =SUMIFS('Jul 25 Inv'!H:H,'Jul 25 Inv'!E:E,'Summary Rollforward'!$B40) -> 0 | CM40: =-SUMIFS('Jul25 Dep'!J:J,'Jul25 Dep'!F:F,'Summary Rollforward'!$B40) -> 0 | CN40: =SUMIFS('Contract Data'!IR:IR,'Contract Data'!$C:$C,'Summary Rollforward'!$B40) -> 0 | CP40: =+CG40+CL40+CM40 -> 75000 | CQ40: =+CR40-CP40 -> 0 | CR40: =+CI40+CK40+CM40+CL40 -> 75000 | CT40: =CW40-CU40 -> 0 | CU40: =SUMIFS('Aug 25 Inv'!H:H,'Aug 25 Inv'!E:E,'Summary Rollforward'!$B40) -> 0 | CV40: =-SUMIFS('Aug25 Dep'!J:J,'Aug25 Dep'!F:F,'Summary Rollforward'!$B40) -> -75000 | CW40: =SUMIFS('Contract Data'!IS:IS,'Contract Data'!$C:$C,'Summary Rollforward'!$B40) -> 0 | CY40: =+CP40+CU40+CV40 -> 0 | CZ40: =+DA40-CY40 -> 0 | DA40: =+CR40+CT40+CV40+CU40 -> 0 | DC40: =DF40-DD40 -> 0 | DD40: =SUMIFS('Sep 25 Inv'!H:H,'Sep 25 Inv'!E:E,'Summary Rollforward'!$B40) -> 0 | DE40: =-SUMIFS('Sep25 Dep'!J:J,'Sep25 Dep'!F:F,'Summary Rollforward'!$B40) -> 0 | DF40: =SUMIFS('Contract Data'!IT:IT,'Contract Data'!$C:$C,'Summary Rollforward'!$B40) -> 0 | DH40: =+CY40+DD40+DE40 -> 0 | DI40: =+DJ40-DH40 -> 0 | DJ40: =+DA40+DC40+DE40+DD40 -> 0 | DL40: =DO40-DM40 -> 0 | DM40: =SUMIFS('Oct 25 Inv'!H:H,'Oct 25 Inv'!E:E,'Summary Rollforward'!$B40) -> 0 | DN40: =-SUMIFS('Oct25 Dep'!J:J,'Oct25 Dep'!F:F,'Summary Rollforward'!$B40) -> 0 | DO40: =SUMIFS('Contract Data'!IU:IU,'Contract Data'!$C:$C,'Summary Rollforward'!$B40) -> 0 | DQ40: =+DH40+DM40+DN40 -> 0 | DR40: =+DS40-DQ40 -> 0 | DS40: =+DJ40+DL40+DN40+DM40 -> 0 | DU40: =DX40-DV40 -> 0 | DV40: =SUMIFS('Nov 25 Inv'!H:H,'Nov 25 Inv'!E:E,'Summary Rollforward'!$B40) -> 0 | DW40: =-SUMIFS('Nov25 Dep'!J:J,'Nov25 Dep'!F:F,'Summary Rollforward'!$B40) -> 0 | DX40: =SUMIFS('Contract Data'!IV:IV,'Contract Data'!$C:$C,'Summary Rollforward'!$B40) -> 0 | DZ40: =+DQ40+DV40+DW40 -> 0 | EA40: =+EB40-DZ40 -> 0 | EB40: =+DS40+DU40+DW40+DV40 -> 0 | ED40: =EG40-EE40 -> 0 | EE40: =SUMIFS('Dec 25 Inv'!H:H,'Dec 25 Inv'!E:E,'Summary Rollforward'!$B40) -> 2296.32 | EF40: =-SUMIFS('Dec25 Dep'!I:I,'Dec25 Dep'!F:F,'Summary Rollforward'!$B40) -> 0 | EG40: =SUMIFS('Contract Data'!IW:IW,'Contract Data'!$C:$C,'Summary Rollforward'!$B40) -> 2296.32 | EI40: =+DZ40+EE40+EF40 -> 2296.32 | EJ40: =+EK40-EI40 -> 0 | EK40: =+EB40+ED40+EF40+EE40 -> 2296.32
B41: Kravet | CK41: =CN41-CL41 -> -11262.5 | CL41: =SUMIFS('Jul 25 Inv'!H:H,'Jul 25 Inv'!E:E,'Summary Rollforward'!$B41) -> 17850 | CM41: =-SUMIFS('Jul25 Dep'!J:J,'Jul25 Dep'!F:F,'Summary Rollforward'!$B41) -> 0 | CN41: =SUMIFS('Contract Data'!IR:IR,'Contract Data'!$C:$C,'Summary Rollforward'!$B41) -> 6587.5 | CP41: =+CG41+CL41+CM41 -> 17850 | CQ41: =+CR41-CP41 -> -11262.5 | CR41: =+CI41+CK41+CM41+CL41 -> 6587.5 | CT41: =CW41-CU41 -> -4675 | CU41: =SUMIFS('Aug 25 Inv'!H:H,'Aug 25 Inv'!E:E,'Summary Rollforward'!$B41) -> 17850 | CV41: =-SUMIFS('Aug25 Dep'!J:J,'Aug25 Dep'!F:F,'Summary Rollforward'!$B41) -> 0 | CW41: =SUMIFS('Contract Data'!IS:IS,'Contract Data'!$C:$C,'Summary Rollforward'!$B41) -> 13175 | CY41: =+CP41+CU41+CV41 -> 35700 | CZ41: =+DA41-CY41 -> -15937.5 | DA41: =+CR41+CT41+CV41+CU41 -> 19762.5 | DC41: =DF41-DD41 -> -4675 | DD41: =SUMIFS('Sep 25 Inv'!H:H,'Sep 25 Inv'!E:E,'Summary Rollforward'!$B41) -> 17850 | DE41: =-SUMIFS('Sep25 Dep'!J:J,'Sep25 Dep'!F:F,'Summary Rollforward'!$B41) -> 0 | DF41: =SUMIFS('Contract Data'!IT:IT,'Contract Data'!$C:$C,'Summary Rollforward'!$B41) -> 13175 | DH41: =+CY41+DD41+DE41 -> 53550 | DI41: =+DJ41-DH41 -> -20612.5 | DJ41: =+DA41+DC41+DE41+DD41 -> 32937.5 | DL41: =DO41-DM41 -> 5325 | DM41: =SUMIFS('Oct 25 Inv'!H:H,'Oct 25 Inv'!E:E,'Summary Rollforward'!$B41) -> 17850 | DN41: =-SUMIFS('Oct25 Dep'!J:J,'Oct25 Dep'!F:F,'Summary Rollforward'!$B41) -> -53550 | DO41: =SUMIFS('Contract Data'!IU:IU,'Contract Data'!$C:$C,'Summary Rollforward'!$B41) -> 23175 | DQ41: =+DH41+DM41+DN41 -> 17850 | DR41: =+DS41-DQ41 -> -15287.5 | DS41: =+DJ41+DL41+DN41+DM41 -> 2562.5 | DU41: =DX41-DV41 -> 2325 | DV41: =SUMIFS('Nov 25 Inv'!H:H,'Nov 25 Inv'!E:E,'Summary Rollforward'!$B41) -> 17850 | DW41: =-SUMIFS('Nov25 Dep'!J:J,'Nov25 Dep'!F:F,'Summary Rollforward'!$B41) -> -17850 | DX41: =SUMIFS('Contract Data'!IV:IV,'Contract Data'!$C:$C,'Summary Rollforward'!$B41) -> 20175 | DZ41: =+DQ41+DV41+DW41 -> 17850 | EA41: =+EB41-DZ41 -> -12962.5 | EB41: =+DS41+DU41+DW41+DV41 -> 4887.5 | ED41: =EG41-EE41 -> 21587.5 | EE41: =SUMIFS('Dec 25 Inv'!H:H,'Dec 25 Inv'!E:E,'Summary Rollforward'!$B41) -> 0 | EF41: =-SUMIFS('Dec25 Dep'!I:I,'Dec25 Dep'!F:F,'Summary Rollforward'!$B41) -> 0 | EG41: =SUMIFS('Contract Data'!IW:IW,'Contract Data'!$C:$C,'Summary Rollforward'!$B41) -> 21587.5 | EI41: =+DZ41+EE41+EF41 -> 17850 | EJ41: =+EK41-EI41 -> 8625 | EK41: =+EB41+ED41+EF41+EE41 -> 26475
B42: Legacy Cabinets | C42: Black Diamond | CK42: =CN42-CL42 -> -18000 | CL42: =SUMIFS('Jul 25 Inv'!H:H,'Jul 25 Inv'!E:E,'Summary Rollforward'!$B42) -> 80000 | CM42: =-SUMIFS('Jul25 Dep'!J:J,'Jul25 Dep'!F:F,'Summary Rollforward'!$B42) -> 0 | CN42: =SUMIFS('Contract Data'!IR:IR,'Contract Data'!$C:$C,'Summary Rollforward'!$B42) -> 62000 | CP42: =+CG42+CL42+CM42 -> 80000 | CQ42: =+CR42-CP42 -> -18000 | CR42: =+CI42+CK42+CM42+CL42 -> 62000 | CT42: =CW42-CU42 -> -18000 | CU42: =SUMIFS('Aug 25 Inv'!H:H,'Aug 25 Inv'!E:E,'Summary Rollforward'!$B42) -> 80000 | CV42: =-SUMIFS('Aug25 Dep'!J:J,'Aug25 Dep'!F:F,'Summary Rollforward'!$B42) -> 0 | CW42: =SUMIFS('Contract Data'!IS:IS,'Contract Data'!$C:$C,'Summary Rollforward'!$B42) -> 62000 | CY42: =+CP42+CU42+CV42 -> 160000 | CZ42: =+DA42-CY42 -> -36000 | DA42: =+CR42+CT42+CV42+CU42 -> 124000 | DC42: =DF42-DD42 -> 62000 | DD42: =SUMIFS('Sep 25 Inv'!H:H,'Sep 25 Inv'!E:E,'Summary Rollforward'!$B42) -> 0 | DE42: =-SUMIFS('Sep25 Dep'!J:J,'Sep25 Dep'!F:F,'Summary Rollforward'!$B42) -> 0 | DF42: =SUMIFS('Contract Data'!IT:IT,'Contract Data'!$C:$C,'Summary Rollforward'!$B42) -> 62000 | DH42: =+CY42+DD42+DE42 -> 160000 | DI42: =+DJ42-DH42 -> 26000 | DJ42: =+DA42+DC42+DE42+DD42 -> 186000 | DL42: =DO42-DM42 -> -18000 | DM42: =SUMIFS('Oct 25 Inv'!H:H,'Oct 25 Inv'!E:E,'Summary Rollforward'!$B42) -> 80000 | DN42: =-SUMIFS('Oct25 Dep'!J:J,'Oct25 Dep'!F:F,'Summary Rollforward'!$B42) -> -80000 | DO42: =SUMIFS('Contract Data'!IU:IU,'Contract Data'!$C:$C,'Summary Rollforward'!$B42) -> 62000 | DQ42: =+DH42+DM42+DN42 -> 160000 | DR42: =+DS42-DQ42 -> 8000 | DS42: =+DJ42+DL42+DN42+DM42 -> 168000 | DU42: =DX42-DV42 -> -50000 | DV42: =SUMIFS('Nov 25 Inv'!H:H,'Nov 25 Inv'!E:E,'Summary Rollforward'!$B42) -> 80000 | DW42: =-SUMIFS('Nov25 Dep'!J:J,'Nov25 Dep'!F:F,'Summary Rollforward'!$B42) -> -80000 | DX42: =SUMIFS('Contract Data'!IV:IV,'Contract Data'!$C:$C,'Summary Rollforward'!$B42) -> 30000 | DZ42: =+DQ42+DV42+DW42 -> 160000 | EA42: =+EB42-DZ42 -> -42000 | EB42: =+DS42+DU42+DW42+DV42 -> 118000 | ED42: =EG42-EE42 -> -55000 | EE42: =SUMIFS('Dec 25 Inv'!H:H,'Dec 25 Inv'!E:E,'Summary Rollforward'!$B42) -> 85367.74 | EF42: =-SUMIFS('Dec25 Dep'!I:I,'Dec25 Dep'!F:F,'Summary Rollforward'!$B42) -> 0 | EG42: =SUMIFS('Contract Data'!IW:IW,'Contract Data'!$C:$C,'Summary Rollforward'!$B42) -> 30367.74 | EI42: =+DZ42+EE42+EF42 -> 245367.74 | EJ42: =+EK42-EI42 -> -97000 | EK42: =+EB42+ED42+EF42+EE42 -> 148367.74
B43: Kamik Investment Holdings Inc. | C43: Torquest Partners | E43: =+'Aug 31'!G9 -> 69000 | F43: =+G43-E43 -> -11500 | G43: =+'AR Calculation - Service'!AM282 -> 57500 | I43: =+'AR Calculation - Service'!AN281 -> 53475 | J43: =+'AR Calculation - Service'!AN280 -> -68975 | L43: =+'Sep 30'!G12 -> 69025 | M43: =+N43-L43 -> -27025 | N43: =+G43+I43+J43 -> 42000 | P43: 53475 | Q43: =-'Oct Collections'!J12-'Oct Collections'!J14 -> -68975 | S43: =+'Oct 31'!G13 -> 69050 | T43: =+U43-S43 -> -42550 | U43: =+N43+P43+Q43 -> 26500 | W43: =+'AR Calculation - Service'!AP281 -> 53475 | X43: =-'Oct Collections'!Q12-'Oct Collections'!Q14 -> 0 | Z43: =+'Nov 30'!G13 -> 138050 | AA43: =+AB43-Z43 -> -58075 | AB43: =+U43+W43+X43 -> 79975 | AD43: =+'AR Calculation - Service'!AQ281-AE43 -> 6154 | AE43: =+'Dec Invoicing'!I10+'Dec Invoicing'!I23 -> 68900 | AG43: =+'AR Calculation - Service'!AQ280 -> -137950 | AI43: =+'Dec 31'!G13 -> 69000 | AJ43: =+AK43-AI43 -> -51921 | AK43: =+AB43+AD43+AG43+AF43+AE43 -> 17079 | AM43: =+'AR Calculation - Service'!AR281-'Summary Rollforward'!AN43 -> 57500 | AN43: =+'Dec Invoicing'!Q10+'Dec Invoicing'!Q23 -> 0 | AO43: =-'Oct Collections'!AF22-'Oct Collections'!AF23 -> 0 | AQ43: =+AI43+AN43+AO43 -> 69000 | AR43: =+AS43-AQ43 -> 5579 | AS43: =+AK43+AM43+AO43+AN43 -> 74579 | AU43: =-AV43 -> -5479 | AV43: =+'Feb Invoices'!G8 -> 5479 | AW43: =-'Oct Collections'!AN22-'Oct Collections'!AN23 -> 0 | AY43: =+AQ43+AV43+AW43 -> 74479 | AZ43: =+BA43-AY43 -> 100 | BA43: =+AS43+AU43+AW43+AV43 -> 74579 | BC43: 0 | BD43: =+'Feb Invoices'!O8 -> 0 | BE43: =+'AR Calculation - Service'!AT280 -> -74444 | BG43: =+AY43+BD43+BE43 -> 35 | BH43: =+BI43-BG43 -> 100 | BI43: =+BA43+BC43+BE43+BD43 -> 135 | BK43: -100 | BM43: -35 | BO43: =+BG43+BL43+BM43 -> 0 | BP43: =+BQ43-BO43 -> 0 | BQ43: =+BI43+BK43+BM43+BL43 -> 0 | BS43: =BV43-BT43 -> 0 | BT43: 0 | BU43: 0 | BV43: =SUMIFS('Contract Data'!IP:IP,'Contract Data'!C:C,'Summary Rollforward'!B43) -> 0 | BX43: =+BO43+BT43+BU43 -> 0 | BY43: =+BZ43-BX43 -> 0 | BZ43: =+BQ43+BS43+BU43+BT43 -> 0 | CB43: =CE43-CC43 -> 0 | CC43: =SUMIFS('June 25 Inv'!G:G,'June 25 Inv'!D:D,'Summary Rollforward'!$B43) -> 0 | CD43: =-SUMIFS('Jun25 Dep'!I:I,'Jun25 Dep'!F:F,'Summary Rollforward'!$B43) -> 0 | CE43: =SUMIFS('Contract Data'!IQ:IQ,'Contract Data'!$C:$C,'Summary Rollforward'!$B43) -> 0 | CG43: =+BX43+CC43+CD43 -> 0 | CH43: =+CI43-CG43 -> 0 | CI43: =+BZ43+CB43+CD43+CC43 -> 0 | CK43: =CN43-CL43 -> 0 | CL43: =SUMIFS('Jul 25 Inv'!H:H,'Jul 25 Inv'!E:E,'Summary Rollforward'!$B43) -> 0 | CM43: =-SUMIFS('Jul25 Dep'!J:J,'Jul25 Dep'!F:F,'Summary Rollforward'!$B43) -> 0 | CN43: =SUMIFS('Contract Data'!IR:IR,'Contract Data'!$C:$C,'Summary Rollforward'!$B43) -> 0 | CP43: =+CG43+CL43+CM43 -> 0 | CQ43: =+CR43-CP43 -> 0 | CR43: =+CI43+CK43+CM43+CL43 -> 0 | CT43: =CW43-CU43 -> 0 | CU43: =SUMIFS('Aug 25 Inv'!H:H,'Aug 25 Inv'!E:E,'Summary Rollforward'!$B43) -> 0 | CV43: =-SUMIFS('Aug25 Dep'!J:J,'Aug25 Dep'!F:F,'Summary Rollforward'!$B43) -> 0 | CW43: =SUMIFS('Contract Data'!IS:IS,'Contract Data'!$C:$C,'Summary Rollforward'!$B43) -> 0 | CY43: =+CP43+CU43+CV43 -> 0 | CZ43: =+DA43-CY43 -> 0 | DA43: =+CR43+CT43+CV43+CU43 -> 0 | DC43: =DF43-DD43 -> 0 | DD43: =SUMIFS('Sep 25 Inv'!H:H,'Sep 25 Inv'!E:E,'Summary Rollforward'!$B43) -> 0 | DE43: =-SUMIFS('Sep25 Dep'!J:J,'Sep25 Dep'!F:F,'Summary Rollforward'!$B43) -> 0 | DF43: =SUMIFS('Contract Data'!IT:IT,'Contract Data'!$C:$C,'Summary Rollforward'!$B43) -> 0 | DH43: =+CY43+DD43+DE43 -> 0 | DI43: =+DJ43-DH43 -> 0 | DJ43: =+DA43+DC43+DE43+DD43 -> 0 | DL43: =DO43-DM43 -> 0 | DM43: =SUMIFS('Oct 25 Inv'!H:H,'Oct 25 Inv'!E:E,'Summary Rollforward'!$B43) -> 0 | DN43: =-SUMIFS('Oct25 Dep'!J:J,'Oct25 Dep'!F:F,'Summary Rollforward'!$B43) -> 0 | DO43: =SUMIFS('Contract Data'!IU:IU,'Contract Data'!$C:$C,'Summary Rollforward'!$B43) -> 0 | DQ43: =+DH43+DM43+DN43 -> 0 | DR43: =+DS43-DQ43 -> 0 | DS43: =+DJ43+DL43+DN43+DM43 -> 0 | DU43: =DX43-DV43 -> 0 | DV43: =SUMIFS('Nov 25 Inv'!H:H,'Nov 25 Inv'!E:E,'Summary Rollforward'!$B43) -> 0 | DW43: =-SUMIFS('Nov25 Dep'!J:J,'Nov25 Dep'!F:F,'Summary Rollforward'!$B43) -> 0 | DX43: =SUMIFS('Contract Data'!IV:IV,'Contract Data'!$C:$C,'Summary Rollforward'!$B43) -> 0 | DZ43: =+DQ43+DV43+DW43 -> 0 | EA43: =+EB43-DZ43 -> 0 | EB43: =+DS43+DU43+DW43+DV43 -> 0 | ED43: =EG43-EE43 -> 0 | EE43: =SUMIFS('Dec 25 Inv'!H:H,'Dec 25 Inv'!E:E,'Summary Rollforward'!$B43) -> 0 | EF43: =-SUMIFS('Dec25 Dep'!I:I,'Dec25 Dep'!F:F,'Summary Rollforward'!$B43) -> 0 | EG43: =SUMIFS('Contract Data'!IW:IW,'Contract Data'!$C:$C,'Summary Rollforward'!$B43) -> 0 | EI43: =+DZ43+EE43+EF43 -> 0 | EJ43: =+EK43-EI43 -> 0 | EK43: =+EB43+ED43+EF43+EE43 -> 0
B44: Milton Industries | C44: LLCP | DU44: =DX44-DV44 -> -18375 | DV44: =SUMIFS('Nov 25 Inv'!H:H,'Nov 25 Inv'!E:E,'Summary Rollforward'!$B44) -> 30000 | DW44: =-SUMIFS('Nov25 Dep'!J:J,'Nov25 Dep'!F:F,'Summary Rollforward'!$B44) -> 0 | DX44: =SUMIFS('Contract Data'!IV:IV,'Contract Data'!$C:$C,'Summary Rollforward'!$B44) -> 11625 | DZ44: =+DQ44+DV44+DW44 -> 30000 | EA44: =+EB44-DZ44 -> -18375 | EB44: =+DS44+DU44+DW44+DV44 -> 11625 | ED44: =EG44-EE44 -> -6750 | EE44: =SUMIFS('Dec 25 Inv'!H:H,'Dec 25 Inv'!E:E,'Summary Rollforward'!$B44) -> 30000 | EF44: =-SUMIFS('Dec25 Dep'!I:I,'Dec25 Dep'!F:F,'Summary Rollforward'!$B44) -> -30000 | EG44: =SUMIFS('Contract Data'!IW:IW,'Contract Data'!$C:$C,'Summary Rollforward'!$B44) -> 23250 | EI44: =+DZ44+EE44+EF44 -> 30000 | EJ44: =+EK44-EI44 -> -25125 | EK44: =+EB44+ED44+EF44+EE44 -> 4875
B45: Monarca Foods | C45: Windpoint | DL45: =DO45-DM45 -> -64312.5 | DM45: =SUMIFS('Oct 25 Inv'!H:H,'Oct 25 Inv'!E:E,'Summary Rollforward'!$B45) -> 105000 | DN45: =-SUMIFS('Oct25 Dep'!J:J,'Oct25 Dep'!F:F,'Summary Rollforward'!$B45) -> 0 | DO45: =SUMIFS('Contract Data'!IU:IU,'Contract Data'!$C:$C,'Summary Rollforward'!$B45) -> 40687.5 | DQ45: =+DH45+DM45+DN45 -> 105000 | DR45: =+DS45-DQ45 -> -64312.5 | DS45: =+DJ45+DL45+DN45+DM45 -> 40687.5 | DU45: =DX45-DV45 -> 81375 | DV45: =SUMIFS('Nov 25 Inv'!H:H,'Nov 25 Inv'!E:E,'Summary Rollforward'!$B45) -> 0 | DW45: =-SUMIFS('Nov25 Dep'!J:J,'Nov25 Dep'!F:F,'Summary Rollforward'!$B45) -> 0 | DX45: =SUMIFS('Contract Data'!IV:IV,'Contract Data'!$C:$C,'Summary Rollforward'!$B45) -> 81375 | DZ45: =+DQ45+DV45+DW45 -> 105000 | EA45: =+EB45-DZ45 -> 17062.5 | EB45: =+DS45+DU45+DW45+DV45 -> 122062.5 | ED45: =EG45-EE45 -> -28625 | EE45: =SUMIFS('Dec 25 Inv'!H:H,'Dec 25 Inv'!E:E,'Summary Rollforward'!$B45) -> 105000 | EF45: =-SUMIFS('Dec25 Dep'!I:I,'Dec25 Dep'!F:F,'Summary Rollforward'!$B45) -> -105000 | EG45: =SUMIFS('Contract Data'!IW:IW,'Contract Data'!$C:$C,'Summary Rollforward'!$B45) -> 76375 | EI45: =+DZ45+EE45+EF45 -> 105000 | EJ45: =+EK45-EI45 -> -11562.5 | EK45: =+EB45+ED45+EF45+EE45 -> 93437.5
B46: NativeSeed | C46: HWP | F46: =+G46-E46 -> 83200.604 | G46: =+'AR Calculation - Service'!AM133 -> 83200.604 | L46: =+'Sep 30'!G13 -> 77663 | M46: =+N46-L46 -> 5537.6044 | N46: =+G46+I46+J46 -> 83200.604 | Q46: =-'Oct Collections'!J13 -> -77663 | S46: 0 | T46: =+U46-S46 -> 5537.6044 | U46: =+N46+P46+Q46 -> 5537.6044 | X46: =-'Oct Collections'!Q13 -> 0 | Z46: 0 | AA46: =+AB46-Z46 -> 0 | AB46: 0 | AG46: =-'Oct Collections'!X13 -> 0 | AI46: 0 | AJ46: =+AK46-AI46 -> 0 | AK46: =+AB46+AD46+AG46+AF46+AE46 -> 0 | AM46: 0 | AO46: =-'Oct Collections'!AF23-'Oct Collections'!AF24 -> 0 | AQ46: =+AI46+AN46+AO46 -> 0 | AR46: =+AS46-AQ46 -> 0 | AS46: =+AK46+AM46+AO46+AN46 -> 0 | AU46: 0 | AW46: =-'Oct Collections'!AN23-'Oct Collections'!AN24 -> 0 | AY46: =+AQ46+AV46+AW46 -> 0 | AZ46: =+BA46-AY46 -> 0 | BA46: =+AS46+AU46+AW46+AV46 -> 0 | BC46: 0 | BG46: =+AY46+BD46+BE46 -> 0 | BH46: =+BI46-BG46 -> 0 | BI46: =+BA46+BC46+BE46+BD46 -> 0 | BO46: =+BG46+BL46+BM46 -> 0 | BP46: =+BQ46-BO46 -> 0 | BQ46: =+BI46+BK46+BM46+BL46 -> 0 | BS46: =BV46-BT46 -> 0 | BT46: 0 | BU46: 0 | BV46: =SUMIFS('Contract Data'!IP:IP,'Contract Data'!C:C,'Summary Rollforward'!B46) -> 0 | BX46: =+BO46+BT46+BU46 -> 0 | BY46: =+BZ46-BX46 -> 0 | BZ46: =+BQ46+BS46+BU46+BT46 -> 0 | CB46: =CE46-CC46 -> 0 | CC46: =SUMIFS('June 25 Inv'!G:G,'June 25 Inv'!D:D,'Summary Rollforward'!$B46) -> 0 | CD46: =-SUMIFS('Jun25 Dep'!I:I,'Jun25 Dep'!F:F,'Summary Rollforward'!$B46) -> 0 | CE46: =SUMIFS('Contract Data'!IQ:IQ,'Contract Data'!$C:$C,'Summary Rollforward'!$B46) -> 0 | CG46: =+BX46+CC46+CD46 -> 0 | CH46: =+CI46-CG46 -> 0 | CI46: =+BZ46+CB46+CD46+CC46 -> 0 | CK46: =CN46-CL46 -> 0 | CL46: =SUMIFS('Jul 25 Inv'!H:H,'Jul 25 Inv'!E:E,'Summary Rollforward'!$B46) -> 0 | CM46: =-SUMIFS('Jul25 Dep'!J:J,'Jul25 Dep'!F:F,'Summary Rollforward'!$B46) -> 0 | CN46: =SUMIFS('Contract Data'!IR:IR,'Contract Data'!$C:$C,'Summary Rollforward'!$B46) -> 0 | CP46: =+CG46+CL46+CM46 -> 0 | CQ46: =+CR46-CP46 -> 0 | CR46: =+CI46+CK46+CM46+CL46 -> 0 | CT46: =CW46-CU46 -> 0 | CU46: =SUMIFS('Aug 25 Inv'!H:H,'Aug 25 Inv'!E:E,'Summary Rollforward'!$B46) -> 0 | CV46: =-SUMIFS('Aug25 Dep'!J:J,'Aug25 Dep'!F:F,'Summary Rollforward'!$B46) -> 0 | CW46: =SUMIFS('Contract Data'!IS:IS,'Contract Data'!$C:$C,'Summary Rollforward'!$B46) -> 0 | CY46: =+CP46+CU46+CV46 -> 0 | CZ46: =+DA46-CY46 -> 0 | DA46: =+CR46+CT46+CV46+CU46 -> 0 | DC46: =DF46-DD46 -> 0 | DD46: =SUMIFS('Sep 25 Inv'!H:H,'Sep 25 Inv'!E:E,'Summary Rollforward'!$B46) -> 0 | DE46: =-SUMIFS('Sep25 Dep'!J:J,'Sep25 Dep'!F:F,'Summary Rollforward'!$B46) -> 0 | DF46: =SUMIFS('Contract Data'!IT:IT,'Contract Data'!$C:$C,'Summary Rollforward'!$B46) -> 0 | DH46: =+CY46+DD46+DE46 -> 0 | DI46: =+DJ46-DH46 -> 0 | DJ46: =+DA46+DC46+DE46+DD46 -> 0 | DL46: =DO46-DM46 -> 0 | DM46: =SUMIFS('Oct 25 Inv'!H:H,'Oct 25 Inv'!E:E,'Summary Rollforward'!$B46) -> 0 | DN46: =-SUMIFS('Oct25 Dep'!J:J,'Oct25 Dep'!F:F,'Summary Rollforward'!$B46) -> 0 | DO46: =SUMIFS('Contract Data'!IU:IU,'Contract Data'!$C:$C,'Summary Rollforward'!$B46) -> 0 | DQ46: =+DH46+DM46+DN46 -> 0 | DR46: =+DS46-DQ46 -> 0 | DS46: =+DJ46+DL46+DN46+DM46 -> 0 | DU46: =DX46-DV46 -> 0 | DV46: =SUMIFS('Nov 25 Inv'!H:H,'Nov 25 Inv'!E:E,'Summary Rollforward'!$B46) -> 0 | DW46: =-SUMIFS('Nov25 Dep'!J:J,'Nov25 Dep'!F:F,'Summary Rollforward'!$B46) -> 0 | DX46: =SUMIFS('Contract Data'!IV:IV,'Contract Data'!$C:$C,'Summary Rollforward'!$B46) -> 0 | DZ46: =+DQ46+DV46+DW46 -> 0 | EA46: =+EB46-DZ46 -> 0 | EB46: =+DS46+DU46+DW46+DV46 -> 0 | ED46: =EG46-EE46 -> 0 | EE46: =SUMIFS('Dec 25 Inv'!H:H,'Dec 25 Inv'!E:E,'Summary Rollforward'!$B46) -> 0 | EF46: =-SUMIFS('Dec25 Dep'!I:I,'Dec25 Dep'!F:F,'Summary Rollforward'!$B46) -> 0 | EG46: =SUMIFS('Contract Data'!IW:IW,'Contract Data'!$C:$C,'Summary Rollforward'!$B46) -> 0 | EI46: =+DZ46+EE46+EF46 -> 0 | EJ46: =+EK46-EI46 -> 0 | EK46: =+EB46+ED46+EF46+EE46 -> 0
B47: Naturpak | C47: Trivest Partners | BC47: =+'AR Calculation - Service'!AT365-'Summary Rollforward'!BD47 -> 25188 | BH47: =+BI47-BG47 -> 25188 | BI47: =+BA47+BC47+BE47+BD47 -> 25188 | BK47: =+'AR Calculation - Service'!AU365-'Summary Rollforward'!BL47 -> -14625 | BL47: =+'Apr Invoices'!G16 -> 65000 | BO47: =+BG47+BL47+BM47 -> 65000 | BP47: =+BQ47-BO47 -> 10563 | BQ47: =+BI47+BK47+BM47+BL47 -> 75563 | BS47: =BV47-BT47 -> 50375 | BT47: 0 | BU47: 0 | BV47: =SUMIFS('Contract Data'!IP:IP,'Contract Data'!C:C,'Summary Rollforward'!B47) -> 50375 | BX47: =+BO47+BT47+BU47 -> 65000 | BY47: =+BZ47-BX47 -> 60938 | BZ47: =+BQ47+BS47+BU47+BT47 -> 125938 | CB47: =CE47-CC47 -> -14625 | CC47: =SUMIFS('June 25 Inv'!G:G,'June 25 Inv'!D:D,'Summary Rollforward'!$B47) -> 65000 | CD47: =-SUMIFS('Jun25 Dep'!I:I,'Jun25 Dep'!F:F,'Summary Rollforward'!$B47) -> 0 | CE47: =SUMIFS('Contract Data'!IQ:IQ,'Contract Data'!$C:$C,'Summary Rollforward'!$B47) -> 50375 | CG47: =+BX47+CC47+CD47 -> 130000 | CH47: =+CI47-CG47 -> 46313 | CI47: =+BZ47+CB47+CD47+CC47 -> 176313 | CK47: =CN47-CL47 -> -14625 | CL47: =SUMIFS('Jul 25 Inv'!H:H,'Jul 25 Inv'!E:E,'Summary Rollforward'!$B47) -> 65000 | CM47: =-SUMIFS('Jul25 Dep'!J:J,'Jul25 Dep'!F:F,'Summary Rollforward'!$B47) -> -130000 | CN47: =SUMIFS('Contract Data'!IR:IR,'Contract Data'!$C:$C,'Summary Rollforward'!$B47) -> 50375 | CP47: =+CG47+CL47+CM47 -> 65000 | CQ47: =+CR47-CP47 -> 31688 | CR47: =+CI47+CK47+CM47+CL47 -> 96688 | CT47: =CW47-CU47 -> -14625 | CU47: =SUMIFS('Aug 25 Inv'!H:H,'Aug 25 Inv'!E:E,'Summary Rollforward'!$B47) -> 65000 | CV47: =-SUMIFS('Aug25 Dep'!J:J,'Aug25 Dep'!F:F,'Summary Rollforward'!$B47) -> 0 | CW47: =SUMIFS('Contract Data'!IS:IS,'Contract Data'!$C:$C,'Summary Rollforward'!$B47) -> 50375 | CY47: =+CP47+CU47+CV47 -> 130000 | CZ47: =+DA47-CY47 -> 17063 | DA47: =+CR47+CT47+CV47+CU47 -> 147063 | DC47: =DF47-DD47 -> -17062.5 | DD47: =SUMIFS('Sep 25 Inv'!H:H,'Sep 25 Inv'!E:E,'Summary Rollforward'!$B47) -> 65000 | DE47: =-SUMIFS('Sep25 Dep'!J:J,'Sep25 Dep'!F:F,'Summary Rollforward'!$B47) -> -130000 | DF47: =SUMIFS('Contract Data'!IT:IT,'Contract Data'!$C:$C,'Summary Rollforward'!$B47) -> 47937.5 | DH47: =+CY47+DD47+DE47 -> 65000 | DI47: =+DJ47-DH47 -> 0.5 | DJ47: =+DA47+DC47+DE47+DD47 -> 65000.5 | DL47: =DO47-DM47 -> 0 | DM47: =SUMIFS('Oct 25 Inv'!H:H,'Oct 25 Inv'!E:E,'Summary Rollforward'!$B47) -> 0 | DN47: =-SUMIFS('Oct25 Dep'!J:J,'Oct25 Dep'!F:F,'Summary Rollforward'!$B47) -> -65000 | DO47: =SUMIFS('Contract Data'!IU:IU,'Contract Data'!$C:$C,'Summary Rollforward'!$B47) -> 0 | DQ47: =+DH47+DM47+DN47 -> 0 | DR47: =+DS47-DQ47 -> 0.5 | DS47: =+DJ47+DL47+DN47+DM47 -> 0.5 | DU47: =DX47-DV47 -> 0 | DV47: =SUMIFS('Nov 25 Inv'!H:H,'Nov 25 Inv'!E:E,'Summary Rollforward'!$B47) -> 0 | DW47: =-SUMIFS('Nov25 Dep'!J:J,'Nov25 Dep'!F:F,'Summary Rollforward'!$B47) -> 0 | DX47: =SUMIFS('Contract Data'!IV:IV,'Contract Data'!$C:$C,'Summary Rollforward'!$B47) -> 0 | DZ47: =+DQ47+DV47+DW47 -> 0 | EA47: =+EB47-DZ47 -> 0.5 | EB47: =+DS47+DU47+DW47+DV47 -> 0.5 | ED47: =EG47-EE47 -> 0 | EE47: =SUMIFS('Dec 25 Inv'!H:H,'Dec 25 Inv'!E:E,'Summary Rollforward'!$B47) -> 3261.77 | EF47: =-SUMIFS('Dec25 Dep'!I:I,'Dec25 Dep'!F:F,'Summary Rollforward'!$B47) -> 0 | EG47: =SUMIFS('Contract Data'!IW:IW,'Contract Data'!$C:$C,'Summary Rollforward'!$B47) -> 3261.77 | EI47: =+DZ47+EE47+EF47 -> 3261.77 | EJ47: =+EK47-EI47 -> 0.5 | EK47: =+EB47+ED47+EF47+EE47 -> 3262.27
B48: Norlee Group | C48: HWP | ED48: =EG48-EE48 -> -49000 | EE48: =SUMIFS('Dec 25 Inv'!H:H,'Dec 25 Inv'!E:E,'Summary Rollforward'!$B48) -> 80000 | EF48: =-SUMIFS('Dec25 Dep'!I:I,'Dec25 Dep'!F:F,'Summary Rollforward'!$B48) -> 0 | EG48: =SUMIFS('Contract Data'!IW:IW,'Contract Data'!$C:$C,'Summary Rollforward'!$B48) -> 31000 | EI48: =+DZ48+EE48+EF48 -> 80000 | EJ48: =+EK48-EI48 -> -49000 | EK48: =+EB48+ED48+EF48+EE48 -> 31000
B49: NSM | C49: Ciniven | P49: 13175.31 | S49: 0 | U49: =+N49+P49+Q49 -> 13175.31 | W49: =+'AR Calculation - Service'!AP305 -> 13175 | Z49: 0 | AA49: =+AB49-Z49 -> 26350.31 | AB49: =+U49+W49+X49 -> 26350.31 | AD49: =+'AR Calculation - Service'!AQ305 -> 44483 | AI49: 0 | AJ49: =+AK49-AI49 -> 70833.31 | AK49: =+AB49+AD49+AG49+AF49+AE49 -> 70833.31 | AM49: =+'AR Calculation - Service'!AR305-'Summary Rollforward'!AN49 -> 14167 | AO49: =-'Oct Collections'!AF24-'Oct Collections'!AF25 -> 0 | AQ49: =+AI49+AN49+AO49 -> 0 | AR49: =+AS49-AQ49 -> 85000.31 | AS49: =+AK49+AM49+AO49+AN49 -> 85000.31 | AU49: =+'AR Calculation - Service'!BB305-'Summary Rollforward'!AV49 -> 0 | AW49: =-'Oct Collections'!AN24-'Oct Collections'!AN25 -> 0 | AY49: =+AQ49+AV49+AW49 -> 0 | AZ49: =+BA49-AY49 -> 85000.31 | BA49: =+AS49+AU49+AW49+AV49 -> 85000.31 | BC49: =+'AR Calculation - Service'!AT305-'Summary Rollforward'!BD49 -> -85000 | BD49: =+'Mar Invoices'!G16 -> 85000 | BG49: =+AY49+BD49+BE49 -> 85000 | BH49: =+BI49-BG49 -> 0.31 | BI49: =+BA49+BC49+BE49+BD49 -> 85000.31 | BK49: =+'AR Calculation - Service'!AU305-'Summary Rollforward'!BL49 -> -10000 | BL49: =+'Apr Invoices'!G12 -> 30000 | BM49: 0 | BO49: =+BG49+BL49+BM49 -> 115000 | BP49: =+BQ49-BO49 -> -9999.69 | BQ49: =+BI49+BK49+BM49+BL49 -> 105000.31 | BS49: =BV49-BT49 -> 10000 | BT49: -10000 | BU49: 0 | BV49: =SUMIFS('Contract Data'!IP:IP,'Contract Data'!C:C,'Summary Rollforward'!B49) -> 0 | BX49: =+BO49+BT49+BU49 -> 105000 | BY49: =+BZ49-BX49 -> 0.31 | BZ49: =+BQ49+BS49+BU49+BT49 -> 105000.31 | CB49: =CE49-CC49 -> 0 | CC49: =SUMIFS('June 25 Inv'!G:G,'June 25 Inv'!D:D,'Summary Rollforward'!$B49) -> 0 | CD49: =-SUMIFS('Jun25 Dep'!I:I,'Jun25 Dep'!F:F,'Summary Rollforward'!$B49) -> 0 | CE49: =SUMIFS('Contract Data'!IQ:IQ,'Contract Data'!$C:$C,'Summary Rollforward'!$B49) -> 0 | CG49: =+BX49+CC49+CD49 -> 105000 | CH49: =+CI49-CG49 -> 0.31 | CI49: =+BZ49+CB49+CD49+CC49 -> 105000.31 | CK49: =CN49-CL49 -> 0 | CL49: =SUMIFS('Jul 25 Inv'!H:H,'Jul 25 Inv'!E:E,'Summary Rollforward'!$B49) -> 0 | CM49: =-SUMIFS('Jul25 Dep'!J:J,'Jul25 Dep'!F:F,'Summary Rollforward'!$B49) -> 0 | CN49: =SUMIFS('Contract Data'!IR:IR,'Contract Data'!$C:$C,'Summary Rollforward'!$B49) -> 0 | CP49: =+CG49+CL49+CM49 -> 105000 | CQ49: =+CR49-CP49 -> 0.31 | CR49: =+CI49+CK49+CM49+CL49 -> 105000.31 | CT49: =CW49-CU49 -> 0 | CU49: =SUMIFS('Aug 25 Inv'!H:H,'Aug 25 Inv'!E:E,'Summary Rollforward'!$B49) -> 0 | CV49: =-SUMIFS('Aug25 Dep'!J:J,'Aug25 Dep'!F:F,'Summary Rollforward'!$B49) -> 0 | CW49: =SUMIFS('Contract Data'!IS:IS,'Contract Data'!$C:$C,'Summary Rollforward'!$B49) -> 0 | CY49: =+CP49+CU49+CV49 -> 105000 | CZ49: =+DA49-CY49 -> 0.31 | DA49: =+CR49+CT49+CV49+CU49 -> 105000.31 | DC49: =DF49-DD49 -> 0 | DD49: =SUMIFS('Sep 25 Inv'!H:H,'Sep 25 Inv'!E:E,'Summary Rollforward'!$B49) -> 0 | DE49: =-SUMIFS('Sep25 Dep'!J:J,'Sep25 Dep'!F:F,'Summary Rollforward'!$B49) -> -105000 | DF49: =SUMIFS('Contract Data'!IT:IT,'Contract Data'!$C:$C,'Summary Rollforward'!$B49) -> 0 | DH49: =+CY49+DD49+DE49 -> 0 | DI49: =+DJ49-DH49 -> 0.31 | DJ49: =+DA49+DC49+DE49+DD49 -> 0.31 | DL49: =DO49-DM49 -> 0 | DM49: =SUMIFS('Oct 25 Inv'!H:H,'Oct 25 Inv'!E:E,'Summary Rollforward'!$B49) -> 0 | DN49: =-SUMIFS('Oct25 Dep'!J:J,'Oct25 Dep'!F:F,'Summary Rollforward'!$B49) -> 0 | DO49: =SUMIFS('Contract Data'!IU:IU,'Contract Data'!$C:$C,'Summary Rollforward'!$B49) -> 0 | DQ49: =+DH49+DM49+DN49 -> 0 | DR49: =+DS49-DQ49 -> 0.31 | DS49: =+DJ49+DL49+DN49+DM49 -> 0.31 | DU49: =DX49-DV49 -> 0 | DV49: =SUMIFS('Nov 25 Inv'!H:H,'Nov 25 Inv'!E:E,'Summary Rollforward'!$B49) -> 0 | DW49: =-SUMIFS('Nov25 Dep'!J:J,'Nov25 Dep'!F:F,'Summary Rollforward'!$B49) -> 0 | DX49: =SUMIFS('Contract Data'!IV:IV,'Contract Data'!$C:$C,'Summary Rollforward'!$B49) -> 0 | DZ49: =+DQ49+DV49+DW49 -> 0 | EA49: =+EB49-DZ49 -> 0.31 | EB49: =+DS49+DU49+DW49+DV49 -> 0.31 | ED49: =EG49-EE49 -> 0 | EE49: =SUMIFS('Dec 25 Inv'!H:H,'Dec 25 Inv'!E:E,'Summary Rollforward'!$B49) -> 0 | EF49: =-SUMIFS('Dec25 Dep'!I:I,'Dec25 Dep'!F:F,'Summary Rollforward'!$B49) -> 0 | EG49: =SUMIFS('Contract Data'!IW:IW,'Contract Data'!$C:$C,'Summary Rollforward'!$B49) -> 0 | EI49: =+DZ49+EE49+EF49 -> 0 | EJ49: =+EK49-EI49 -> 0.31 | EK49: =+EB49+ED49+EF49+EE49 -> 0.31
B50: Nwestco | C50: Guardian | F50: =+G50-E50 -> 71842.054 | G50: =+'AR Calculation - Service'!AM137 -> 71842.054 | M50: =+N50-L50 -> 71842.054 | N50: =+G50+I50+J50 -> 71842.054 | S50: 0 | T50: =+U50-S50 -> 71842.054 | U50: =+N50+P50+Q50 -> 71842.054 | W50: 2696 | Z50: =+'Nov 30'!G14 -> 74538 | AA50: =+AB50-Z50 -> 0.054206766 | AB50: =+U50+W50+X50 -> 74538.054 | AI50: =+'Dec 31'!G14 -> 74538 | AJ50: =+AK50-AI50 -> 0.054206766 | AK50: =+AB50+AD50+AG50+AF50+AE50 -> 74538.054 | AM50: 0 | AO50: =-'Oct Collections'!AF25-'Oct Collections'!AF26 -> 0 | AQ50: =+AI50+AN50+AO50 -> 74538 | AR50: =+AS50-AQ50 -> 0.054206766 | AS50: =+AK50+AM50+AO50+AN50 -> 74538.054 | AU50: 0 | AW50: =+'AR Calculation - Service'!AS135 -> -74538 | AY50: =+AQ50+AV50+AW50 -> 0 | AZ50: =+BA50-AY50 -> 0.054206766 | BA50: =+AS50+AU50+AW50+AV50 -> 0.054206766 | BC50: 0 | BG50: =+AY50+BD50+BE50 -> 0 | BH50: =+BI50-BG50 -> 0.054206766 | BI50: =+BA50+BC50+BE50+BD50 -> 0.054206766 | BO50: =+BG50+BL50+BM50 -> 0 | BP50: =+BQ50-BO50 -> 0.054206766 | BQ50: =+BI50+BK50+BM50+BL50 -> 0.054206766 | BS50: =BV50-BT50 -> 0 | BT50: 0 | BU50: 0 | BV50: =SUMIFS('Contract Data'!IP:IP,'Contract Data'!C:C,'Summary Rollforward'!B50) -> 0 | BX50: =+BO50+BT50+BU50 -> 0 | BY50: =+BZ50-BX50 -> 0.054206766 | BZ50: =+BQ50+BS50+BU50+BT50 -> 0.054206766 | CB50: =CE50-CC50 -> 0 | CC50: =SUMIFS('June 25 Inv'!G:G,'June 25 Inv'!D:D,'Summary Rollforward'!$B50) -> 0 | CD50: =-SUMIFS('Jun25 Dep'!I:I,'Jun25 Dep'!F:F,'Summary Rollforward'!$B50) -> 0 | CE50: =SUMIFS('Contract Data'!IQ:IQ,'Contract Data'!$C:$C,'Summary Rollforward'!$B50) -> 0 | CG50: =+BX50+CC50+CD50 -> 0 | CH50: =+CI50-CG50 -> 0.054206766 | CI50: =+BZ50+CB50+CD50+CC50 -> 0.054206766 | CK50: =CN50-CL50 -> 0 | CL50: =SUMIFS('Jul 25 Inv'!H:H,'Jul 25 Inv'!E:E,'Summary Rollforward'!$B50) -> 0 | CM50: =-SUMIFS('Jul25 Dep'!J:J,'Jul25 Dep'!F:F,'Summary Rollforward'!$B50) -> 0 | CN50: =SUMIFS('Contract Data'!IR:IR,'Contract Data'!$C:$C,'Summary Rollforward'!$B50) -> 0 | CP50: =+CG50+CL50+CM50 -> 0 | CQ50: =+CR50-CP50 -> 0.054206766 | CR50: =+CI50+CK50+CM50+CL50 -> 0.054206766 | CT50: =CW50-CU50 -> 0 | CU50: =SUMIFS('Aug 25 Inv'!H:H,'Aug 25 Inv'!E:E,'Summary Rollforward'!$B50) -> 0 | CV50: =-SUMIFS('Aug25 Dep'!J:J,'Aug25 Dep'!F:F,'Summary Rollforward'!$B50) -> 0 | CW50: =SUMIFS('Contract Data'!IS:IS,'Contract Data'!$C:$C,'Summary Rollforward'!$B50) -> 0 | CY50: =+CP50+CU50+CV50 -> 0 | CZ50: =+DA50-CY50 -> 0.054206766 | DA50: =+CR50+CT50+CV50+CU50 -> 0.054206766 | DC50: =DF50-DD50 -> 0 | DD50: =SUMIFS('Sep 25 Inv'!H:H,'Sep 25 Inv'!E:E,'Summary Rollforward'!$B50) -> 0 | DE50: =-SUMIFS('Sep25 Dep'!J:J,'Sep25 Dep'!F:F,'Summary Rollforward'!$B50) -> 0 | DF50: =SUMIFS('Contract Data'!IT:IT,'Contract Data'!$C:$C,'Summary Rollforward'!$B50) -> 0 | DH50: =+CY50+DD50+DE50 -> 0 | DI50: =+DJ50-DH50 -> 0.054206766 | DJ50: =+DA50+DC50+DE50+DD50 -> 0.054206766 | DL50: =DO50-DM50 -> 0 | DM50: =SUMIFS('Oct 25 Inv'!H:H,'Oct 25 Inv'!E:E,'Summary Rollforward'!$B50) -> 0 | DN50: =-SUMIFS('Oct25 Dep'!J:J,'Oct25 Dep'!F:F,'Summary Rollforward'!$B50) -> 0 | DO50: =SUMIFS('Contract Data'!IU:IU,'Contract Data'!$C:$C,'Summary Rollforward'!$B50) -> 0 | DQ50: =+DH50+DM50+DN50 -> 0 | DR50: =+DS50-DQ50 -> 0.054206766 | DS50: =+DJ50+DL50+DN50+DM50 -> 0.054206766 | DU50: =DX50-DV50 -> 0 | DV50: =SUMIFS('Nov 25 Inv'!H:H,'Nov 25 Inv'!E:E,'Summary Rollforward'!$B50) -> 0 | DW50: =-SUMIFS('Nov25 Dep'!J:J,'Nov25 Dep'!F:F,'Summary Rollforward'!$B50) -> 0 | DX50: =SUMIFS('Contract Data'!IV:IV,'Contract Data'!$C:$C,'Summary Rollforward'!$B50) -> 0 | DZ50: =+DQ50+DV50+DW50 -> 0 | EA50: =+EB50-DZ50 -> 0.054206766 | EB50: =+DS50+DU50+DW50+DV50 -> 0.054206766 | ED50: =EG50-EE50 -> 0 | EE50: =SUMIFS('Dec 25 Inv'!H:H,'Dec 25 Inv'!E:E,'Summary Rollforward'!$B50) -> 0 | EF50: =-SUMIFS('Dec25 Dep'!I:I,'Dec25 Dep'!F:F,'Summary Rollforward'!$B50) -> 0 | EG50: =SUMIFS('Contract Data'!IW:IW,'Contract Data'!$C:$C,'Summary Rollforward'!$B50) -> 0 | EI50: =+DZ50+EE50+EF50 -> 0 | EJ50: =+EK50-EI50 -> 0.054206766 | EK50: =+EB50+ED50+EF50+EE50 -> 0.054206766
B51: O2B Kids | C51: Spire Capital | P51: 10074.69 | S51: 0 | U51: =+N51+P51+Q51 -> 10074.69 | W51: =+'AR Calculation - Service'!AP321 -> 20150 | Z51: 0 | AA51: =+AB51-Z51 -> 30224.69 | AB51: =+U51+W51+X51 -> 30224.69 | AD51: =+'AR Calculation - Service'!AQ321 -> 20150 | AI51: 0 | AJ51: =+AK51-AI51 -> 50374.69 | AK51: =+AB51+AD51+AG51+AF51+AE51 -> 50374.69 | AM51: =+'AR Calculation - Service'!AR321-'Summary Rollforward'!AN51 -> 20150 | AO51: =-'Oct Collections'!AF26-'Oct Collections'!AF27 -> 0 | AQ51: =+AI51+AN51+AO51 -> 0 | AR51: =+AS51-AQ51 -> 70524.69 | AS51: =+AK51+AM51+AO51+AN51 -> 70524.69 | AU51: =+'AR Calculation - Service'!AS321-'Summary Rollforward'!AV51 -> 24972 | AW51: =-'Oct Collections'!AN26-'Oct Collections'!AN27 -> 0 | AY51: =+AQ51+AV51+AW51 -> 0 | AZ51: =+BA51-AY51 -> 95496.69 | BA51: =+AS51+AU51+AW51+AV51 -> 95496.69 | BC51: =+'AR Calculation - Service'!AT321-'Summary Rollforward'!BD51 -> 20150 | BG51: =+AY51+BD51+BE51 -> 0 | BH51: =+BI51-BG51 -> 115646.69 | BI51: =+BA51+BC51+BE51+BD51 -> 115646.69 | BK51: =+'AR Calculation - Service'!AU321-'Summary Rollforward'!BL51 -> 19175 | BO51: =+BG51+BL51+BM51 -> 0 | BP51: =+BQ51-BO51 -> 134821.69 | BQ51: =+BI51+BK51+BM51+BL51 -> 134821.69 | BS51: =BV51-BT51 -> 19175 | BT51: 0 | BU51: 0 | BV51: =SUMIFS('Contract Data'!IP:IP,'Contract Data'!C:C,'Summary Rollforward'!B51) -> 19175 | BX51: =+BO51+BT51+BU51 -> 0 | BY51: =+BZ51-BX51 -> 153996.69 | BZ51: =+BQ51+BS51+BU51+BT51 -> 153996.69 | CB51: =CE51-CC51 -> 1158.3333 | CC51: =SUMIFS('June 25 Inv'!G:G,'June 25 Inv'!D:D,'Summary Rollforward'!$B51) -> 0 | CD51: =-SUMIFS('Jun25 Dep'!I:I,'Jun25 Dep'!F:F,'Summary Rollforward'!$B51) -> 0 | CE51: =SUMIFS('Contract Data'!IQ:IQ,'Contract Data'!$C:$C,'Summary Rollforward'!$B51) -> 1158.3333 | CG51: =+BX51+CC51+CD51 -> 0 | CH51: =+CI51-CG51 -> 155155.02 | CI51: =+BZ51+CB51+CD51+CC51 -> 155155.02 | CK51: =CN51-CL51 -> 20333.333 | CL51: =SUMIFS('Jul 25 Inv'!H:H,'Jul 25 Inv'!E:E,'Summary Rollforward'!$B51) -> 0 | CM51: =-SUMIFS('Jul25 Dep'!J:J,'Jul25 Dep'!F:F,'Summary Rollforward'!$B51) -> 0 | CN51: =SUMIFS('Contract Data'!IR:IR,'Contract Data'!$C:$C,'Summary Rollforward'!$B51) -> 20333.333 | CP51: =+CG51+CL51+CM51 -> 0 | CQ51: =+CR51-CP51 -> 175488.36 | CR51: =+CI51+CK51+CM51+CL51 -> 175488.36 | CT51: =CW51-CU51 -> 13444.444 | CU51: =SUMIFS('Aug 25 Inv'!H:H,'Aug 25 Inv'!E:E,'Summary Rollforward'!$B51) -> 0 | CV51: =-SUMIFS('Aug25 Dep'!J:J,'Aug25 Dep'!F:F,'Summary Rollforward'!$B51) -> 0 | CW51: =SUMIFS('Contract Data'!IS:IS,'Contract Data'!$C:$C,'Summary Rollforward'!$B51) -> 13444.444 | CY51: =+CP51+CU51+CV51 -> 0 | CZ51: =+DA51-CY51 -> 188932.8 | DA51: =+CR51+CT51+CV51+CU51 -> 188932.8 | DC51: =DF51-DD51 -> 18625.778 | DD51: =SUMIFS('Sep 25 Inv'!H:H,'Sep 25 Inv'!E:E,'Summary Rollforward'!$B51) -> 0 | DE51: =-SUMIFS('Sep25 Dep'!J:J,'Sep25 Dep'!F:F,'Summary Rollforward'!$B51) -> 0 | DF51: =SUMIFS('Contract Data'!IT:IT,'Contract Data'!$C:$C,'Summary Rollforward'!$B51) -> 18625.778 | DH51: =+CY51+DD51+DE51 -> 0 | DI51: =+DJ51-DH51 -> 207558.58 | DJ51: =+DA51+DC51+DE51+DD51 -> 207558.58 | DL51: =DO51-DM51 -> 5000 | DM51: =SUMIFS('Oct 25 Inv'!H:H,'Oct 25 Inv'!E:E,'Summary Rollforward'!$B51) -> 0 | DN51: =-SUMIFS('Oct25 Dep'!J:J,'Oct25 Dep'!F:F,'Summary Rollforward'!$B51) -> 0 | DO51: =SUMIFS('Contract Data'!IU:IU,'Contract Data'!$C:$C,'Summary Rollforward'!$B51) -> 5000 | DQ51: =+DH51+DM51+DN51 -> 0 | DR51: =+DS51-DQ51 -> 212558.58 | DS51: =+DJ51+DL51+DN51+DM51 -> 212558.58 | DU51: =DX51-DV51 -> 5000 | DV51: =SUMIFS('Nov 25 Inv'!H:H,'Nov 25 Inv'!E:E,'Summary Rollforward'!$B51) -> 0 | DW51: =-SUMIFS('Nov25 Dep'!J:J,'Nov25 Dep'!F:F,'Summary Rollforward'!$B51) -> 0 | DX51: =SUMIFS('Contract Data'!IV:IV,'Contract Data'!$C:$C,'Summary Rollforward'!$B51) -> 5000 | DZ51: =+DQ51+DV51+DW51 -> 0 | EA51: =+EB51-DZ51 -> 217558.58 | EB51: =+DS51+DU51+DW51+DV51 -> 217558.58 | ED51: =EG51-EE51 -> 0 | EE51: =SUMIFS('Dec 25 Inv'!H:H,'Dec 25 Inv'!E:E,'Summary Rollforward'!$B51) -> 4821.76 | EF51: =-SUMIFS('Dec25 Dep'!I:I,'Dec25 Dep'!F:F,'Summary Rollforward'!$B51) -> 0 | EG51: =SUMIFS('Contract Data'!IW:IW,'Contract Data'!$C:$C,'Summary Rollforward'!$B51) -> 4821.76 | EI51: =+DZ51+EE51+EF51 -> 4821.76 | EJ51: =+EK51-EI51 -> 217558.58 | EK51: =+EB51+ED51+EF51+EE51 -> 222380.34
B52: Olympus Cosmetic Group | C52: VSS Capital | DC52: =DF52-DD52 -> -19875 | DD52: =SUMIFS('Sep 25 Inv'!H:H,'Sep 25 Inv'!E:E,'Summary Rollforward'!$B52) -> 31500 | DE52: =-SUMIFS('Sep25 Dep'!J:J,'Sep25 Dep'!F:F,'Summary Rollforward'!$B52) -> -31500 | DF52: =SUMIFS('Contract Data'!IT:IT,'Contract Data'!$C:$C,'Summary Rollforward'!$B52) -> 11625 | DH52: =+CY52+DD52+DE52 -> 0 | DI52: =+DJ52-DH52 -> -19875 | DJ52: =+DA52+DC52+DE52+DD52 -> -19875 | DL52: =DO52-DM52 -> -8250 | DM52: =SUMIFS('Oct 25 Inv'!H:H,'Oct 25 Inv'!E:E,'Summary Rollforward'!$B52) -> 31500 | DN52: =-SUMIFS('Oct25 Dep'!J:J,'Oct25 Dep'!F:F,'Summary Rollforward'!$B52) -> -31500 | DO52: =SUMIFS('Contract Data'!IU:IU,'Contract Data'!$C:$C,'Summary Rollforward'!$B52) -> 23250 | DQ52: =+DH52+DM52+DN52 -> 0 | DR52: =+DS52-DQ52 -> -28125 | DS52: =+DJ52+DL52+DN52+DM52 -> -28125 | DU52: =DX52-DV52 -> -12500 | DV52: =SUMIFS('Nov 25 Inv'!H:H,'Nov 25 Inv'!E:E,'Summary Rollforward'!$B52) -> 31500 | DW52: =-SUMIFS('Nov25 Dep'!J:J,'Nov25 Dep'!F:F,'Summary Rollforward'!$B52) -> 0 | DX52: =SUMIFS('Contract Data'!IV:IV,'Contract Data'!$C:$C,'Summary Rollforward'!$B52) -> 19000 | DZ52: =+DQ52+DV52+DW52 -> 31500 | EA52: =+EB52-DZ52 -> -40625 | EB52: =+DS52+DU52+DW52+DV52 -> -9125 | ED52: =EG52-EE52 -> -2500 | EE52: =SUMIFS('Dec 25 Inv'!H:H,'Dec 25 Inv'!E:E,'Summary Rollforward'!$B52) -> 31500 | EF52: =-SUMIFS('Dec25 Dep'!I:I,'Dec25 Dep'!F:F,'Summary Rollforward'!$B52) -> 0 | EG52: =SUMIFS('Contract Data'!IW:IW,'Contract Data'!$C:$C,'Summary Rollforward'!$B52) -> 29000 | EI52: =+DZ52+EE52+EF52 -> 63000 | EJ52: =+EK52-EI52 -> -43125 | EK52: =+EB52+ED52+EF52+EE52 -> 19875
B53: Open Road Collision | C53: Trivest Partners | W53: =+'AR Calculation - Service'!AP333 -> 17437.5 | Z53: =+'Nov 30'!G15 -> 45000 | AA53: =+AB53-Z53 -> -27562.5 | AB53: =+U53+W53+X53 -> 17437.5 | AD53: =+'AR Calculation - Service'!AQ333-AE53 -> -10125 | AE53: =+'Dec Invoicing'!I17 -> 45000 | AG53: =+'AR Calculation - Service'!AQ332 -> -45000 | AI53: =+'Dec 31'!G15 -> 45000 | AJ53: =+AK53-AI53 -> -37687.5 | AK53: =+AB53+AD53+AG53+AF53+AE53 -> 7312.5 | AM53: =+'AR Calculation - Service'!AR333-'Summary Rollforward'!AN53 -> -10125 | AN53: =+'Jan Invoicing'!G11 -> 45000 | AO53: =-'Oct Collections'!AF27-'Oct Collections'!AF28 -> 0 | AQ53: =+AI53+AN53+AO53 -> 90000 | AR53: =+AS53-AQ53 -> -47812.5 | AS53: =+AK53+AM53+AO53+AN53 -> 42187.5 | AU53: =+'AR Calculation - Service'!AS333-'Summary Rollforward'!AV53 -> 39328 | AV53: =+'Jan Invoicing'!O11 -> 0 | AW53: =-'Oct Collections'!AN27-'Oct Collections'!AN28 -> 0 | AY53: =+AQ53+AV53+AW53 -> 90000 | AZ53: =+BA53-AY53 -> -8484.5 | BA53: =+AS53+AU53+AW53+AV53 -> 81515.5 | BC53: =+'AR Calculation - Service'!AT333-'Summary Rollforward'!BD53 -> -10125 | BD53: =+'Mar Invoices'!G11 -> 45000 | BG53: =+AY53+BD53+BE53 -> 135000 | BH53: =+BI53-BG53 -> -18609.5 | BI53: =+BA53+BC53+BE53+BD53 -> 116390.5 | BK53: =+'AR Calculation - Service'!AU333-'Summary Rollforward'!BL53 -> -14107 | BL53: =+'Apr Invoices'!G8 -> 48982 | BO53: =+BG53+BL53+BM53 -> 183982 | BP53: =+BQ53-BO53 -> -32716.5 | BQ53: =+BI53+BK53+BM53+BL53 -> 151265.5 | BS53: =BV53-BT53 -> 28702 | BT53: 0 | BU53: -93982 | BV53: =SUMIFS('Contract Data'!IP:IP,'Contract Data'!C:C,'Summary Rollforward'!B53) -> 28702 | BX53: =+BO53+BT53+BU53 -> 90000 | BY53: =+BZ53-BX53 -> -4014.5 | BZ53: =+BQ53+BS53+BU53+BT53 -> 85985.5 | CB53: =CE53-CC53 -> 4014.5 | CC53: =SUMIFS('June 25 Inv'!G:G,'June 25 Inv'!D:D,'Summary Rollforward'!$B53) -> 0 | CD53: =-SUMIFS('Jun25 Dep'!I:I,'Jun25 Dep'!F:F,'Summary Rollforward'!$B53) -> -90000 | CE53: =SUMIFS('Contract Data'!IQ:IQ,'Contract Data'!$C:$C,'Summary Rollforward'!$B53) -> 4014.5 | CG53: =+BX53+CC53+CD53 -> 0 | CH53: =+CI53-CG53 -> 0 | CI53: =+BZ53+CB53+CD53+CC53 -> 0 | CK53: =CN53-CL53 -> 0 | CL53: =SUMIFS('Jul 25 Inv'!H:H,'Jul 25 Inv'!E:E,'Summary Rollforward'!$B53) -> 0 | CM53: =-SUMIFS('Jul25 Dep'!J:J,'Jul25 Dep'!F:F,'Summary Rollforward'!$B53) -> 0 | CN53: =SUMIFS('Contract Data'!IR:IR,'Contract Data'!$C:$C,'Summary Rollforward'!$B53) -> 0 | CP53: =+CG53+CL53+CM53 -> 0 | CQ53: =+CR53-CP53 -> 0 | CR53: =+CI53+CK53+CM53+CL53 -> 0 | CT53: =CW53-CU53 -> 7869.25 | CU53: =SUMIFS('Aug 25 Inv'!H:H,'Aug 25 Inv'!E:E,'Summary Rollforward'!$B53) -> 0 | CV53: =-SUMIFS('Aug25 Dep'!J:J,'Aug25 Dep'!F:F,'Summary Rollforward'!$B53) -> 0 | CW53: =SUMIFS('Contract Data'!IS:IS,'Contract Data'!$C:$C,'Summary Rollforward'!$B53) -> 7869.25 | CY53: =+CP53+CU53+CV53 -> 0 | CZ53: =+DA53-CY53 -> 7869.25 | DA53: =+CR53+CT53+CV53+CU53 -> 7869.25 | DC53: =DF53-DD53 -> 7869.25 | DD53: =SUMIFS('Sep 25 Inv'!H:H,'Sep 25 Inv'!E:E,'Summary Rollforward'!$B53) -> 0 | DE53: =-SUMIFS('Sep25 Dep'!J:J,'Sep25 Dep'!F:F,'Summary Rollforward'!$B53) -> 0 | DF53: =SUMIFS('Contract Data'!IT:IT,'Contract Data'!$C:$C,'Summary Rollforward'!$B53) -> 7869.25 | DH53: =+CY53+DD53+DE53 -> 0 | DI53: =+DJ53-DH53 -> 15738.5 | DJ53: =+DA53+DC53+DE53+DD53 -> 15738.5 | DL53: =DO53-DM53 -> 7869.25 | DM53: =SUMIFS('Oct 25 Inv'!H:H,'Oct 25 Inv'!E:E,'Summary Rollforward'!$B53) -> 0 | DN53: =-SUMIFS('Oct25 Dep'!J:J,'Oct25 Dep'!F:F,'Summary Rollforward'!$B53) -> 0 | DO53: =SUMIFS('Contract Data'!IU:IU,'Contract Data'!$C:$C,'Summary Rollforward'!$B53) -> 7869.25 | DQ53: =+DH53+DM53+DN53 -> 0 | DR53: =+DS53-DQ53 -> 23607.75 | DS53: =+DJ53+DL53+DN53+DM53 -> 23607.75 | DU53: =DX53-DV53 -> 3934.625 | DV53: =SUMIFS('Nov 25 Inv'!H:H,'Nov 25 Inv'!E:E,'Summary Rollforward'!$B53) -> 0 | DW53: =-SUMIFS('Nov25 Dep'!J:J,'Nov25 Dep'!F:F,'Summary Rollforward'!$B53) -> 0 | DX53: =SUMIFS('Contract Data'!IV:IV,'Contract Data'!$C:$C,'Summary Rollforward'!$B53) -> 3934.625 | DZ53: =+DQ53+DV53+DW53 -> 0 | EA53: =+EB53-DZ53 -> 27542.375 | EB53: =+DS53+DU53+DW53+DV53 -> 27542.375 | ED53: =EG53-EE53 -> 3934.625 | EE53: =SUMIFS('Dec 25 Inv'!H:H,'Dec 25 Inv'!E:E,'Summary Rollforward'!$B53) -> 0 | EF53: =-SUMIFS('Dec25 Dep'!I:I,'Dec25 Dep'!F:F,'Summary Rollforward'!$B53) -> 0 | EG53: =SUMIFS('Contract Data'!IW:IW,'Contract Data'!$C:$C,'Summary Rollforward'!$B53) -> 3934.625 | EI53: =+DZ53+EE53+EF53 -> 0 | EJ53: =+EK53-EI53 -> 31477 | EK53: =+EB53+ED53+EF53+EE53 -> 31477
B54: Pacesetter Health | C54: VSS Capital | CB54: =CE54-CC54 -> 10200 | CC54: =SUMIFS('June 25 Inv'!G:G,'June 25 Inv'!D:D,'Summary Rollforward'!$B54) -> 0 | CD54: =-SUMIFS('Jun25 Dep'!I:I,'Jun25 Dep'!F:F,'Summary Rollforward'!$B54) -> 0 | CE54: =SUMIFS('Contract Data'!IQ:IQ,'Contract Data'!$C:$C,'Summary Rollforward'!$B54) -> 10200 | CG54: =+BX54+CC54+CD54 -> 0 | CH54: =+CI54-CG54 -> 10200 | CI54: =+BZ54+CB54+CD54+CC54 -> 10200 | CK54: =CN54-CL54 -> 20400 | CL54: =SUMIFS('Jul 25 Inv'!H:H,'Jul 25 Inv'!E:E,'Summary Rollforward'!$B54) -> 0 | CM54: =-SUMIFS('Jul25 Dep'!J:J,'Jul25 Dep'!F:F,'Summary Rollforward'!$B54) -> 0 | CN54: =SUMIFS('Contract Data'!IR:IR,'Contract Data'!$C:$C,'Summary Rollforward'!$B54) -> 20400 | CP54: =+CG54+CL54+CM54 -> 0 | CQ54: =+CR54-CP54 -> 30600 | CR54: =+CI54+CK54+CM54+CL54 -> 30600 | CT54: =CW54-CU54 -> 20400 | CU54: =SUMIFS('Aug 25 Inv'!H:H,'Aug 25 Inv'!E:E,'Summary Rollforward'!$B54) -> 0 | CV54: =-SUMIFS('Aug25 Dep'!J:J,'Aug25 Dep'!F:F,'Summary Rollforward'!$B54) -> 0 | CW54: =SUMIFS('Contract Data'!IS:IS,'Contract Data'!$C:$C,'Summary Rollforward'!$B54) -> 20400 | CY54: =+CP54+CU54+CV54 -> 0 | CZ54: =+DA54-CY54 -> 51000 | DA54: =+CR54+CT54+CV54+CU54 -> 51000 | DC54: =DF54-DD54 -> 20400 | DD54: =SUMIFS('Sep 25 Inv'!H:H,'Sep 25 Inv'!E:E,'Summary Rollforward'!$B54) -> 0 | DE54: =-SUMIFS('Sep25 Dep'!J:J,'Sep25 Dep'!F:F,'Summary Rollforward'!$B54) -> 0 | DF54: =SUMIFS('Contract Data'!IT:IT,'Contract Data'!$C:$C,'Summary Rollforward'!$B54) -> 20400 | DH54: =+CY54+DD54+DE54 -> 0 | DI54: =+DJ54-DH54 -> 71400 | DJ54: =+DA54+DC54+DE54+DD54 -> 71400 | DL54: =DO54-DM54 -> 5100 | DM54: =SUMIFS('Oct 25 Inv'!H:H,'Oct 25 Inv'!E:E,'Summary Rollforward'!$B54) -> 0 | DN54: =-SUMIFS('Oct25 Dep'!J:J,'Oct25 Dep'!F:F,'Summary Rollforward'!$B54) -> 0 | DO54: =SUMIFS('Contract Data'!IU:IU,'Contract Data'!$C:$C,'Summary Rollforward'!$B54) -> 5100 | DQ54: =+DH54+DM54+DN54 -> 0 | DR54: =+DS54-DQ54 -> 76500 | DS54: =+DJ54+DL54+DN54+DM54 -> 76500 | DU54: =DX54-DV54 -> 5100 | DV54: =SUMIFS('Nov 25 Inv'!H:H,'Nov 25 Inv'!E:E,'Summary Rollforward'!$B54) -> 0 | DW54: =-SUMIFS('Nov25 Dep'!J:J,'Nov25 Dep'!F:F,'Summary Rollforward'!$B54) -> 0 | DX54: =SUMIFS('Contract Data'!IV:IV,'Contract Data'!$C:$C,'Summary Rollforward'!$B54) -> 5100 | DZ54: =+DQ54+DV54+DW54 -> 0 | EA54: =+EB54-DZ54 -> 81600 | EB54: =+DS54+DU54+DW54+DV54 -> 81600 | ED54: =EG54-EE54 -> 8000 | EE54: =SUMIFS('Dec 25 Inv'!H:H,'Dec 25 Inv'!E:E,'Summary Rollforward'!$B54) -> 0 | EF54: =-SUMIFS('Dec25 Dep'!I:I,'Dec25 Dep'!F:F,'Summary Rollforward'!$B54) -> 0 | EG54: =SUMIFS('Contract Data'!IW:IW,'Contract Data'!$C:$C,'Summary Rollforward'!$B54) -> 8000 | EI54: =+DZ54+EE54+EF54 -> 0 | EJ54: =+EK54-EI54 -> 89600 | EK54: =+EB54+ED54+EF54+EE54 -> 89600
B55: PATCO Products | C55: Kingswood Capital Management | AU55: =+'AR Calculation - Service'!AS345 -> 21700 | AY55: =+AQ55+AV55+AW55 -> 0 | AZ55: =+BA55-AY55 -> 21700 | BA55: =+AS55+AU55+AW55+AV55 -> 21700 | BC55: =+'AR Calculation - Service'!AT345-'Summary Rollforward'!BD55 -> 18400 | BD55: =+'Mar Invoices'!G19 -> 25000 | BG55: =+AY55+BD55+BE55 -> 25000 | BH55: =+BI55-BG55 -> 40100 | BI55: =+BA55+BC55+BE55+BD55 -> 65100 | BK55: =+'AR Calculation - Service'!AU345-'Summary Rollforward'!BL55 -> 43400 | BL55: 0 | BO55: =+BG55+BL55+BM55 -> 25000 | BP55: =+BQ55-BO55 -> 83500 | BQ55: =+BI55+BK55+BM55+BL55 -> 108500 | BS55: =BV55-BT55 -> 43400 | BT55: 0 | BU55: 0 | BV55: =SUMIFS('Contract Data'!IP:IP,'Contract Data'!C:C,'Summary Rollforward'!B55) -> 43400 | BX55: =+BO55+BT55+BU55 -> 25000 | BY55: =+BZ55-BX55 -> 126900 | BZ55: =+BQ55+BS55+BU55+BT55 -> 151900 | CB55: =CE55-CC55 -> -7600 | CC55: =SUMIFS('June 25 Inv'!G:G,'June 25 Inv'!D:D,'Summary Rollforward'!$B55) -> 51000 | CD55: =-SUMIFS('Jun25 Dep'!I:I,'Jun25 Dep'!F:F,'Summary Rollforward'!$B55) -> 0 | CE55: =SUMIFS('Contract Data'!IQ:IQ,'Contract Data'!$C:$C,'Summary Rollforward'!$B55) -> 43400 | CG55: =+BX55+CC55+CD55 -> 76000 | CH55: =+CI55-CG55 -> 119300 | CI55: =+BZ55+CB55+CD55+CC55 -> 195300 | CK55: =CN55-CL55 -> -7600 | CL55: =SUMIFS('Jul 25 Inv'!H:H,'Jul 25 Inv'!E:E,'Summary Rollforward'!$B55) -> 51000 | CM55: =-SUMIFS('Jul25 Dep'!J:J,'Jul25 Dep'!F:F,'Summary Rollforward'!$B55) -> 0 | CN55: =SUMIFS('Contract Data'!IR:IR,'Contract Data'!$C:$C,'Summary Rollforward'!$B55) -> 43400 | CP55: =+CG55+CL55+CM55 -> 127000 | CQ55: =+CR55-CP55 -> 111700 | CR55: =+CI55+CK55+CM55+CL55 -> 238700 | CT55: =CW55-CU55 -> -29300 | CU55: =SUMIFS('Aug 25 Inv'!H:H,'Aug 25 Inv'!E:E,'Summary Rollforward'!$B55) -> 51000 | CV55: =-SUMIFS('Aug25 Dep'!J:J,'Aug25 Dep'!F:F,'Summary Rollforward'!$B55) -> -25000 | CW55: =SUMIFS('Contract Data'!IS:IS,'Contract Data'!$C:$C,'Summary Rollforward'!$B55) -> 21700 | CY55: =+CP55+CU55+CV55 -> 153000 | CZ55: =+DA55-CY55 -> 82400 | DA55: =+CR55+CT55+CV55+CU55 -> 235400 | DC55: =DF55-DD55 -> -41000 | DD55: =SUMIFS('Sep 25 Inv'!H:H,'Sep 25 Inv'!E:E,'Summary Rollforward'!$B55) -> 51000 | DE55: =-SUMIFS('Sep25 Dep'!J:J,'Sep25 Dep'!F:F,'Summary Rollforward'!$B55) -> -102000 | DF55: =SUMIFS('Contract Data'!IT:IT,'Contract Data'!$C:$C,'Summary Rollforward'!$B55) -> 10000 | DH55: =+CY55+DD55+DE55 -> 102000 | DI55: =+DJ55-DH55 -> 41400 | DJ55: =+DA55+DC55+DE55+DD55 -> 143400 | DL55: =DO55-DM55 -> -41400 | DM55: =SUMIFS('Oct 25 Inv'!H:H,'Oct 25 Inv'!E:E,'Summary Rollforward'!$B55) -> 51000 | DN55: =-SUMIFS('Oct25 Dep'!J:J,'Oct25 Dep'!F:F,'Summary Rollforward'!$B55) -> -51000 | DO55: =SUMIFS('Contract Data'!IU:IU,'Contract Data'!$C:$C,'Summary Rollforward'!$B55) -> 9600 | DQ55: =+DH55+DM55+DN55 -> 102000 | DR55: =+DS55-DQ55 -> 0 | DS55: =+DJ55+DL55+DN55+DM55 -> 102000 | DU55: =DX55-DV55 -> 0 | DV55: =SUMIFS('Nov 25 Inv'!H:H,'Nov 25 Inv'!E:E,'Summary Rollforward'!$B55) -> 0 | DW55: =-SUMIFS('Nov25 Dep'!J:J,'Nov25 Dep'!F:F,'Summary Rollforward'!$B55) -> -51000 | DX55: =SUMIFS('Contract Data'!IV:IV,'Contract Data'!$C:$C,'Summary Rollforward'!$B55) -> 0 | DZ55: =+DQ55+DV55+DW55 -> 51000 | EA55: =+EB55-DZ55 -> 0 | EB55: =+DS55+DU55+DW55+DV55 -> 51000 | ED55: =EG55-EE55 -> 0 | EE55: =SUMIFS('Dec 25 Inv'!H:H,'Dec 25 Inv'!E:E,'Summary Rollforward'!$B55) -> 5680.45 | EF55: =-SUMIFS('Dec25 Dep'!I:I,'Dec25 Dep'!F:F,'Summary Rollforward'!$B55) -> -51000 | EG55: =SUMIFS('Contract Data'!IW:IW,'Contract Data'!$C:$C,'Summary Rollforward'!$B55) -> 5680.45 | EI55: =+DZ55+EE55+EF55 -> 5680.45 | EJ55: =+EK55-EI55 -> 0 | EK55: =+EB55+ED55+EF55+EE55 -> 5680.45
B56: Pertronix | C56: Charger Investment Partners | E56: =+'Aug 31'!G10 -> 75000 | F56: =+G56-E56 -> 68750 | G56: =+'AR Calculation - Service'!AM153+'AR Calculation - Service'!AM294 -> 143750 | I56: =+'AR Calculation - Service'!AN293 -> 58125 | J56: =+'AR Calculation - Service'!AN292 -> -75000 | L56: =+'Sep 30'!G14 -> 75000 | M56: =+N56-L56 -> 51875 | N56: =+G56+I56+J56 -> 126875 | P56: 58125 | S56: =+'Oct 31'!G14 -> 150000 | T56: =+U56-S56 -> 35000 | U56: =+N56+P56+Q56 -> 185000 | W56: =+'AR Calculation - Service'!AP293 -> 40000 | X56: =+'Nov Collections'!I15 -> -75000 | Z56: =+'Nov 30'!G16 -> 150000 | AA56: =+AB56-Z56 -> 0 | AB56: =+U56+W56+X56 -> 150000 | AD56: =+'AR Calculation - Service'!AQ293 -> 4993 | AG56: =+'AR Calculation - Service'!AQ292 -> -75000 | AI56: =+'Dec 31'!G16 -> 75000 | AJ56: =+AK56-AI56 -> 4993 | AK56: =+AB56+AD56+AG56+AF56+AE56 -> 79993 | AM56: 0 | AO56: =-'Oct Collections'!AF28-'Oct Collections'!AF29 -> 0 | AQ56: =+AI56+AN56+AO56 -> 75000 | AR56: =+AS56-AQ56 -> 4993 | AS56: =+AK56+AM56+AO56+AN56 -> 79993 | AU56: =-AV56 -> -4992 | AV56: =+'Feb Invoices'!G7 -> 4992 | AW56: =-'Oct Collections'!AN28-'Oct Collections'!AN29 -> 0 | AY56: =+AQ56+AV56+AW56 -> 79992 | AZ56: =+BA56-AY56 -> 1 | BA56: =+AS56+AU56+AW56+AV56 -> 79993 | BC56: 0 | BD56: =+'Feb Invoices'!O7 -> 0 | BG56: =+AY56+BD56+BE56 -> 79992 | BH56: =+BI56-BG56 -> 1 | BI56: =+BA56+BC56+BE56+BD56 -> 79993 | BO56: =+BG56+BL56+BM56 -> 79992 | BP56: =+BQ56-BO56 -> 1 | BQ56: =+BI56+BK56+BM56+BL56 -> 79993 | BS56: =BV56-BT56 -> 0 | BT56: 0 | BU56: -4992 | BV56: =SUMIFS('Contract Data'!IP:IP,'Contract Data'!C:C,'Summary Rollforward'!B56) -> 0 | BX56: =+BO56+BT56+BU56 -> 75000 | BY56: =+BZ56-BX56 -> 1 | BZ56: =+BQ56+BS56+BU56+BT56 -> 75001 | CB56: =CE56-CC56 -> 0 | CC56: =SUMIFS('June 25 Inv'!G:G,'June 25 Inv'!D:D,'Summary Rollforward'!$B56) -> 0 | CD56: =-SUMIFS('Jun25 Dep'!I:I,'Jun25 Dep'!F:F,'Summary Rollforward'!$B56) -> 0 | CE56: =SUMIFS('Contract Data'!IQ:IQ,'Contract Data'!$C:$C,'Summary Rollforward'!$B56) -> 0 | CG56: =+BX56+CC56+CD56 -> 75000 | CH56: =+CI56-CG56 -> 1 | CI56: =+BZ56+CB56+CD56+CC56 -> 75001 | CK56: =CN56-CL56 -> -1 | CL56: =SUMIFS('Jul 25 Inv'!H:H,'Jul 25 Inv'!E:E,'Summary Rollforward'!$B56) -> 0 | CM56: =-SUMIFS('Jul25 Dep'!J:J,'Jul25 Dep'!F:F,'Summary Rollforward'!$B56) -> -75000 | CN56: =SUMIFS('Contract Data'!IR:IR,'Contract Data'!$C:$C,'Summary Rollforward'!$B56) -> -1 | CP56: =+CG56+CL56+CM56 -> 0 | CQ56: =+CR56-CP56 -> 0 | CR56: =+CI56+CK56+CM56+CL56 -> 0 | CT56: =CW56-CU56 -> 0 | CU56: =SUMIFS('Aug 25 Inv'!H:H,'Aug 25 Inv'!E:E,'Summary Rollforward'!$B56) -> 0 | CV56: =-SUMIFS('Aug25 Dep'!J:J,'Aug25 Dep'!F:F,'Summary Rollforward'!$B56) -> 0 | CW56: =SUMIFS('Contract Data'!IS:IS,'Contract Data'!$C:$C,'Summary Rollforward'!$B56) -> 0 | CY56: =+CP56+CU56+CV56 -> 0 | CZ56: =+DA56-CY56 -> 0 | DA56: =+CR56+CT56+CV56+CU56 -> 0 | DC56: =DF56-DD56 -> 0 | DD56: =SUMIFS('Sep 25 Inv'!H:H,'Sep 25 Inv'!E:E,'Summary Rollforward'!$B56) -> 0 | DE56: =-SUMIFS('Sep25 Dep'!J:J,'Sep25 Dep'!F:F,'Summary Rollforward'!$B56) -> 0 | DF56: =SUMIFS('Contract Data'!IT:IT,'Contract Data'!$C:$C,'Summary Rollforward'!$B56) -> 0 | DH56: =+CY56+DD56+DE56 -> 0 | DI56: =+DJ56-DH56 -> 0 | DJ56: =+DA56+DC56+DE56+DD56 -> 0 | DL56: =DO56-DM56 -> 0 | DM56: =SUMIFS('Oct 25 Inv'!H:H,'Oct 25 Inv'!E:E,'Summary Rollforward'!$B56) -> 0 | DN56: =-SUMIFS('Oct25 Dep'!J:J,'Oct25 Dep'!F:F,'Summary Rollforward'!$B56) -> 0 | DO56: =SUMIFS('Contract Data'!IU:IU,'Contract Data'!$C:$C,'Summary Rollforward'!$B56) -> 0 | DQ56: =+DH56+DM56+DN56 -> 0 | DR56: =+DS56-DQ56 -> 0 | DS56: =+DJ56+DL56+DN56+DM56 -> 0 | DU56: =DX56-DV56 -> 0 | DV56: =SUMIFS('Nov 25 Inv'!H:H,'Nov 25 Inv'!E:E,'Summary Rollforward'!$B56) -> 0 | DW56: =-SUMIFS('Nov25 Dep'!J:J,'Nov25 Dep'!F:F,'Summary Rollforward'!$B56) -> 0 | DX56: =SUMIFS('Contract Data'!IV:IV,'Contract Data'!$C:$C,'Summary Rollforward'!$B56) -> 0 | DZ56: =+DQ56+DV56+DW56 -> 0 | EA56: =+EB56-DZ56 -> 0 | EB56: =+DS56+DU56+DW56+DV56 -> 0 | ED56: =EG56-EE56 -> 0 | EE56: =SUMIFS('Dec 25 Inv'!H:H,'Dec 25 Inv'!E:E,'Summary Rollforward'!$B56) -> 0 | EF56: =-SUMIFS('Dec25 Dep'!I:I,'Dec25 Dep'!F:F,'Summary Rollforward'!$B56) -> 0 | EG56: =SUMIFS('Contract Data'!IW:IW,'Contract Data'!$C:$C,'Summary Rollforward'!$B56) -> 0 | EI56: =+DZ56+EE56+EF56 -> 0 | EJ56: =+EK56-EI56 -> 0 | EK56: =+EB56+ED56+EF56+EE56 -> 0
B57: Platinum Dermatology | C57: Sun Capital | E57: =+'Aug 31'!G11 -> 148000 | F57: =+G57-E57 -> 2077.77 | G57: =+'AR Calculation - Service'!AM157 -> 150077.77 | L57: =+'Sep 30'!G15 -> 148000 | M57: =+N57-L57 -> 2077.77 | N57: =+G57+I57+J57 -> 150077.77 | S57: =+'Oct 31'!G15 -> 118400 | T57: =+U57-S57 -> 31677.77 | U57: =+N57+P57+Q57 -> 150077.77 | X57: =+'Nov Collections'!I27+'Nov Collections'!I30 -> -118400 | Z57: =+'Oct 31'!N15 -> 0 | AA57: =+AB57-Z57 -> 31677.77 | AB57: =+U57+W57+X57 -> 31677.77 | AF57: -31678 | AG57: =+'Nov Collections'!P27+'Nov Collections'!P30 -> 0 | AI57: =+'Oct 31'!R15 -> 0 | AJ57: =+AK57-AI57 -> -0.23 | AK57: =+AB57+AD57+AG57+AF57+AE57 -> -0.23 | AM57: 0 | AO57: =-'Oct Collections'!AF29-'Oct Collections'!AF30 -> 0 | AQ57: =+AI57+AN57+AO57 -> 0 | AR57: =+AS57-AQ57 -> -0.23 | AS57: =+AK57+AM57+AO57+AN57 -> -0.23 | AU57: 0 | AW57: =-'Oct Collections'!AN29-'Oct Collections'!AN30 -> 0 | AY57: =+AQ57+AV57+AW57 -> 0 | AZ57: =+BA57-AY57 -> -0.23 | BA57: =+AS57+AU57+AW57+AV57 -> -0.23 | BC57: 0 | BG57: =+AY57+BD57+BE57 -> 0 | BH57: =+BI57-BG57 -> -0.23 | BI57: =+BA57+BC57+BE57+BD57 -> -0.23 | BO57: =+BG57+BL57+BM57 -> 0 | BP57: =+BQ57-BO57 -> -0.23 | BQ57: =+BI57+BK57+BM57+BL57 -> -0.23 | BS57: =BV57-BT57 -> 0 | BT57: 0 | BU57: 0 | BV57: =SUMIFS('Contract Data'!IP:IP,'Contract Data'!C:C,'Summary Rollforward'!B57) -> 0 | BX57: =+BO57+BT57+BU57 -> 0 | BY57: =+BZ57-BX57 -> -0.23 | BZ57: =+BQ57+BS57+BU57+BT57 -> -0.23 | CB57: =CE57-CC57 -> 0 | CC57: =SUMIFS('June 25 Inv'!G:G,'June 25 Inv'!D:D,'Summary Rollforward'!$B57) -> 0 | CD57: =-SUMIFS('Jun25 Dep'!I:I,'Jun25 Dep'!F:F,'Summary Rollforward'!$B57) -> 0 | CE57: =SUMIFS('Contract Data'!IQ:IQ,'Contract Data'!$C:$C,'Summary Rollforward'!$B57) -> 0 | CG57: =+BX57+CC57+CD57 -> 0 | CH57: =+CI57-CG57 -> -0.23 | CI57: =+BZ57+CB57+CD57+CC57 -> -0.23 | CK57: =CN57-CL57 -> 0 | CL57: =SUMIFS('Jul 25 Inv'!H:H,'Jul 25 Inv'!E:E,'Summary Rollforward'!$B57) -> 0 | CM57: =-SUMIFS('Jul25 Dep'!J:J,'Jul25 Dep'!F:F,'Summary Rollforward'!$B57) -> 0 | CN57: =SUMIFS('Contract Data'!IR:IR,'Contract Data'!$C:$C,'Summary Rollforward'!$B57) -> 0 | CP57: =+CG57+CL57+CM57 -> 0 | CQ57: =+CR57-CP57 -> -0.23 | CR57: =+CI57+CK57+CM57+CL57 -> -0.23 | CT57: =CW57-CU57 -> 0 | CU57: =SUMIFS('Aug 25 Inv'!H:H,'Aug 25 Inv'!E:E,'Summary Rollforward'!$B57) -> 0 | CV57: =-SUMIFS('Aug25 Dep'!J:J,'Aug25 Dep'!F:F,'Summary Rollforward'!$B57) -> 0 | CW57: =SUMIFS('Contract Data'!IS:IS,'Contract Data'!$C:$C,'Summary Rollforward'!$B57) -> 0 | CY57: =+CP57+CU57+CV57 -> 0 | CZ57: =+DA57-CY57 -> -0.23 | DA57: =+CR57+CT57+CV57+CU57 -> -0.23 | DC57: =DF57-DD57 -> 0 | DD57: =SUMIFS('Sep 25 Inv'!H:H,'Sep 25 Inv'!E:E,'Summary Rollforward'!$B57) -> 0 | DE57: =-SUMIFS('Sep25 Dep'!J:J,'Sep25 Dep'!F:F,'Summary Rollforward'!$B57) -> 0 | DF57: =SUMIFS('Contract Data'!IT:IT,'Contract Data'!$C:$C,'Summary Rollforward'!$B57) -> 0 | DH57: =+CY57+DD57+DE57 -> 0 | DI57: =+DJ57-DH57 -> -0.23 | DJ57: =+DA57+DC57+DE57+DD57 -> -0.23 | DL57: =DO57-DM57 -> 0 | DM57: =SUMIFS('Oct 25 Inv'!H:H,'Oct 25 Inv'!E:E,'Summary Rollforward'!$B57) -> 0 | DN57: =-SUMIFS('Oct25 Dep'!J:J,'Oct25 Dep'!F:F,'Summary Rollforward'!$B57) -> 0 | DO57: =SUMIFS('Contract Data'!IU:IU,'Contract Data'!$C:$C,'Summary Rollforward'!$B57) -> 0 | DQ57: =+DH57+DM57+DN57 -> 0 | DR57: =+DS57-DQ57 -> -0.23 | DS57: =+DJ57+DL57+DN57+DM57 -> -0.23 | DU57: =DX57-DV57 -> 0 | DV57: =SUMIFS('Nov 25 Inv'!H:H,'Nov 25 Inv'!E:E,'Summary Rollforward'!$B57) -> 0 | DW57: =-SUMIFS('Nov25 Dep'!J:J,'Nov25 Dep'!F:F,'Summary Rollforward'!$B57) -> 0 | DX57: =SUMIFS('Contract Data'!IV:IV,'Contract Data'!$C:$C,'Summary Rollforward'!$B57) -> 0 | DZ57: =+DQ57+DV57+DW57 -> 0 | EA57: =+EB57-DZ57 -> -0.23 | EB57: =+DS57+DU57+DW57+DV57 -> -0.23 | ED57: =EG57-EE57 -> 0 | EE57: =SUMIFS('Dec 25 Inv'!H:H,'Dec 25 Inv'!E:E,'Summary Rollforward'!$B57) -> 0 | EF57: =-SUMIFS('Dec25 Dep'!I:I,'Dec25 Dep'!F:F,'Summary Rollforward'!$B57) -> 0 | EG57: =SUMIFS('Contract Data'!IW:IW,'Contract Data'!$C:$C,'Summary Rollforward'!$B57) -> 0 | EI57: =+DZ57+EE57+EF57 -> 0 | EJ57: =+EK57-EI57 -> -0.23 | EK57: =+EB57+ED57+EF57+EE57 -> -0.23
B58: Premium Guard | C58: Trive | E58: =+'Aug 31'!G12 -> 66000 | F58: =+G58-E58 -> -60500 | G58: =+'AR Calculation - Service'!AM270 -> 5500 | I58: =+'AR Calculation - Service'!AN269 -> 51150 | J58: =+'AR Calculation - Service'!AN268 -> -66000 | L58: =+'Sep 30'!G16 -> 66000 | M58: =+N58-L58 -> -75350 | N58: =+G58+I58+J58 -> -9350 | P58: 51150 | Q58: =-'Oct Collections'!J17 -> -66000 | S58: 0 | T58: =+U58-S58 -> -24200 | U58: =+N58+P58+Q58 -> -24200 | W58: =+'AR Calculation - Service'!AP269 -> 51150 | X58: =-'Oct Collections'!Q17 -> 0 | Z58: 0 | AA58: =+AB58-Z58 -> 26950 | AB58: =+U58+W58+X58 -> 26950 | AD58: =+'AR Calculation - Service'!AQ269-AE58 -> -22345 | AE58: =+'Dec Invoicing'!I13 -> 66000 | AG58: =-'Oct Collections'!X17 -> 0 | AI58: =+'Dec 31'!G17 -> 66000 | AJ58: =+AK58-AI58 -> 4605 | AK58: =+AB58+AD58+AG58+AF58+AE58 -> 70605 | AM58: 0 | AN58: =+'Dec Invoicing'!Q13 -> 0 | AO58: =-'Oct Collections'!AF30-'Oct Collections'!AF31 -> 0 | AQ58: =+AI58+AN58+AO58 -> 66000 | AR58: =+AS58-AQ58 -> 4605 | AS58: =+AK58+AM58+AO58+AN58 -> 70605 | AU58: ='AR Calculation - Service'!AS269-AV58 -> -2817 | AV58: =+'Feb Invoices'!G9 -> 4605 | AW58: =-'Oct Collections'!AN30-'Oct Collections'!AN31 -> 0 | AY58: =+AQ58+AV58+AW58 -> 70605 | AZ58: =+BA58-AY58 -> 1788 | BA58: =+AS58+AU58+AW58+AV58 -> 72393 | BC58: 0 | BD58: =+'Feb Invoices'!O9 -> 0 | BE58: =+'AR Calculation - Service'!AT268 -> -66000 | BG58: =+AY58+BD58+BE58 -> 4605 | BH58: =+BI58-BG58 -> 1788 | BI58: =+BA58+BC58+BE58+BD58 -> 6393 | BM58: =+'AR Calculation - Service'!AU268 -> -4605 | BO58: =+BG58+BL58+BM58 -> 0 | BP58: =+BQ58-BO58 -> 1788 | BQ58: =+BI58+BK58+BM58+BL58 -> 1788 | BS58: =BV58-BT58 -> 0 | BT58: 0 | BU58: 0 | BV58: =SUMIFS('Contract Data'!IP:IP,'Contract Data'!C:C,'Summary Rollforward'!B58) -> 0 | BX58: =+BO58+BT58+BU58 -> 0 | BY58: =+BZ58-BX58 -> 1788 | BZ58: =+BQ58+BS58+BU58+BT58 -> 1788 | CB58: =CE58-CC58 -> 0 | CC58: =SUMIFS('June 25 Inv'!G:G,'June 25 Inv'!D:D,'Summary Rollforward'!$B58) -> 0 | CD58: =-SUMIFS('Jun25 Dep'!I:I,'Jun25 Dep'!F:F,'Summary Rollforward'!$B58) -> 0 | CE58: =SUMIFS('Contract Data'!IQ:IQ,'Contract Data'!$C:$C,'Summary Rollforward'!$B58) -> 0 | CG58: =+BX58+CC58+CD58 -> 0 | CH58: =+CI58-CG58 -> 1788 | CI58: =+BZ58+CB58+CD58+CC58 -> 1788 | CK58: =CN58-CL58 -> 0 | CL58: =SUMIFS('Jul 25 Inv'!H:H,'Jul 25 Inv'!E:E,'Summary Rollforward'!$B58) -> 0 | CM58: =-SUMIFS('Jul25 Dep'!J:J,'Jul25 Dep'!F:F,'Summary Rollforward'!$B58) -> 0 | CN58: =SUMIFS('Contract Data'!IR:IR,'Contract Data'!$C:$C,'Summary Rollforward'!$B58) -> 0 | CP58: =+CG58+CL58+CM58 -> 0 | CQ58: =+CR58-CP58 -> 1788 | CR58: =+CI58+CK58+CM58+CL58 -> 1788 | CT58: =CW58-CU58 -> 0 | CU58: =SUMIFS('Aug 25 Inv'!H:H,'Aug 25 Inv'!E:E,'Summary Rollforward'!$B58) -> 0 | CV58: =-SUMIFS('Aug25 Dep'!J:J,'Aug25 Dep'!F:F,'Summary Rollforward'!$B58) -> 0 | CW58: =SUMIFS('Contract Data'!IS:IS,'Contract Data'!$C:$C,'Summary Rollforward'!$B58) -> 0 | CY58: =+CP58+CU58+CV58 -> 0 | CZ58: =+DA58-CY58 -> 1788 | DA58: =+CR58+CT58+CV58+CU58 -> 1788 | DC58: =DF58-DD58 -> 0 | DD58: =SUMIFS('Sep 25 Inv'!H:H,'Sep 25 Inv'!E:E,'Summary Rollforward'!$B58) -> 0 | DE58: =-SUMIFS('Sep25 Dep'!J:J,'Sep25 Dep'!F:F,'Summary Rollforward'!$B58) -> 0 | DF58: =SUMIFS('Contract Data'!IT:IT,'Contract Data'!$C:$C,'Summary Rollforward'!$B58) -> 0 | DH58: =+CY58+DD58+DE58 -> 0 | DI58: =+DJ58-DH58 -> 1788 | DJ58: =+DA58+DC58+DE58+DD58 -> 1788 | DL58: =DO58-DM58 -> 0 | DM58: =SUMIFS('Oct 25 Inv'!H:H,'Oct 25 Inv'!E:E,'Summary Rollforward'!$B58) -> 0 | DN58: =-SUMIFS('Oct25 Dep'!J:J,'Oct25 Dep'!F:F,'Summary Rollforward'!$B58) -> 0 | DO58: =SUMIFS('Contract Data'!IU:IU,'Contract Data'!$C:$C,'Summary Rollforward'!$B58) -> 0 | DQ58: =+DH58+DM58+DN58 -> 0 | DR58: =+DS58-DQ58 -> 1788 | DS58: =+DJ58+DL58+DN58+DM58 -> 1788 | DU58: =DX58-DV58 -> 0 | DV58: =SUMIFS('Nov 25 Inv'!H:H,'Nov 25 Inv'!E:E,'Summary Rollforward'!$B58) -> 0 | DW58: =-SUMIFS('Nov25 Dep'!J:J,'Nov25 Dep'!F:F,'Summary Rollforward'!$B58) -> 0 | DX58: =SUMIFS('Contract Data'!IV:IV,'Contract Data'!$C:$C,'Summary Rollforward'!$B58) -> 0 | DZ58: =+DQ58+DV58+DW58 -> 0 | EA58: =+EB58-DZ58 -> 1788 | EB58: =+DS58+DU58+DW58+DV58 -> 1788 | ED58: =EG58-EE58 -> 0 | EE58: =SUMIFS('Dec 25 Inv'!H:H,'Dec 25 Inv'!E:E,'Summary Rollforward'!$B58) -> 1263.24 | EF58: =-SUMIFS('Dec25 Dep'!I:I,'Dec25 Dep'!F:F,'Summary Rollforward'!$B58) -> 0 | EG58: =SUMIFS('Contract Data'!IW:IW,'Contract Data'!$C:$C,'Summary Rollforward'!$B58) -> 1263.24 | EI58: =+DZ58+EE58+EF58 -> 1263.24 | EJ58: =+EK58-EI58 -> 1788 | EK58: =+EB58+ED58+EF58+EE58 -> 3051.24
B59: Printful | C59: Bregal Sagemount | DL59: =DO59-DM59 -> -36787.5 | DM59: =SUMIFS('Oct 25 Inv'!H:H,'Oct 25 Inv'!E:E,'Summary Rollforward'!$B59) -> 47250 | DN59: =-SUMIFS('Oct25 Dep'!J:J,'Oct25 Dep'!F:F,'Summary Rollforward'!$B59) -> 0 | DO59: =SUMIFS('Contract Data'!IU:IU,'Contract Data'!$C:$C,'Summary Rollforward'!$B59) -> 10462.5 | DQ59: =+DH59+DM59+DN59 -> 47250 | DR59: =+DS59-DQ59 -> -36787.5 | DS59: =+DJ59+DL59+DN59+DM59 -> 10462.5 | DU59: =DX59-DV59 -> 20925 | DV59: =SUMIFS('Nov 25 Inv'!H:H,'Nov 25 Inv'!E:E,'Summary Rollforward'!$B59) -> 0 | DW59: =-SUMIFS('Nov25 Dep'!J:J,'Nov25 Dep'!F:F,'Summary Rollforward'!$B59) -> 0 | DX59: =SUMIFS('Contract Data'!IV:IV,'Contract Data'!$C:$C,'Summary Rollforward'!$B59) -> 20925 | DZ59: =+DQ59+DV59+DW59 -> 47250 | EA59: =+EB59-DZ59 -> -15862.5 | EB59: =+DS59+DU59+DW59+DV59 -> 31387.5 | ED59: =EG59-EE59 -> 20925 | EE59: =SUMIFS('Dec 25 Inv'!H:H,'Dec 25 Inv'!E:E,'Summary Rollforward'!$B59) -> 0 | EF59: =-SUMIFS('Dec25 Dep'!I:I,'Dec25 Dep'!F:F,'Summary Rollforward'!$B59) -> -47250 | EG59: =SUMIFS('Contract Data'!IW:IW,'Contract Data'!$C:$C,'Summary Rollforward'!$B59) -> 20925 | EI59: =+DZ59+EE59+EF59 -> 0 | EJ59: =+EK59-EI59 -> 5062.5 | EK59: =+EB59+ED59+EF59+EE59 -> 5062.5
B60: Qualderm Partners LLC | C60: Baypine | F60: =+G60-E60 -> 156600 | G60: =+'AR Calculation - Service'!AM161 -> 156600 | I60: =+'AR Calculation - Service'!AN160 -> 64183 | M60: =+N60-L60 -> 220783 | N60: =+G60+I60+J60 -> 220783 | P60: 40436.1 | S60: =+'Oct 31'!G16 -> 68100 | T60: =+U60-S60 -> 193119.1 | U60: =+N60+P60+Q60 -> 261219.1 | W60: =+'AR Calculation - Service'!AP160 -> 78386.4 | Z60: =+'Nov 30'!G17 -> 68100 | AA60: =+AB60-Z60 -> 271505.5 | AB60: =+U60+W60+X60 -> 339605.5 | AD60: =+'AR Calculation - Service'!AQ160 -> -27000 | AI60: =+'Dec 31'!G18 -> 68100 | AJ60: =+AK60-AI60 -> 244505.5 | AK60: =+AB60+AD60+AG60+AF60+AE60 -> 312605.5 | AM60: 0 | AO60: =-'Oct Collections'!AF31-'Oct Collections'!AF32 -> 0 | AQ60: =+AI60+AN60+AO60 -> 68100 | AR60: =+AS60-AQ60 -> 244505.5 | AS60: =+AK60+AM60+AO60+AN60 -> 312605.5 | AU60: =+'AR Calculation - Service'!AS160-'Summary Rollforward'!AV60 -> 37299 | AW60: =-'Oct Collections'!AN31-'Oct Collections'!AN32 -> 0 | AY60: =+AQ60+AV60+AW60 -> 68100 | AZ60: =+BA60-AY60 -> 281804.5 | BA60: =+AS60+AU60+AW60+AV60 -> 349904.5 | BC60: =-BD60 -> -281804 | BD60: =+'Mar Invoices'!G7 -> 281804 | BG60: =+AY60+BD60+BE60 -> 349904 | BH60: =+BI60-BG60 -> 0.5 | BI60: =+BA60+BC60+BE60+BD60 -> 349904.5 | BM60: =+'AR Calculation - Service'!AU159 -> -68100 | BO60: =+BG60+BL60+BM60 -> 281804 | BP60: =+BQ60-BO60 -> 0.5 | BQ60: =+BI60+BK60+BM60+BL60 -> 281804.5 | BS60: =BV60-BT60 -> 0 | BT60: 0 | BU60: 0 | BV60: =SUMIFS('Contract Data'!IP:IP,'Contract Data'!C:C,'Summary Rollforward'!B60) -> 0 | BX60: =+BO60+BT60+BU60 -> 281804 | BY60: =+BZ60-BX60 -> 0.5 | BZ60: =+BQ60+BS60+BU60+BT60 -> 281804.5 | CB60: =CE60-CC60 -> 0 | CC60: =SUMIFS('June 25 Inv'!G:G,'June 25 Inv'!D:D,'Summary Rollforward'!$B60) -> 16543 | CD60: =-SUMIFS('Jun25 Dep'!I:I,'Jun25 Dep'!F:F,'Summary Rollforward'!$B60) -> -281804 | CE60: =SUMIFS('Contract Data'!IQ:IQ,'Contract Data'!$C:$C,'Summary Rollforward'!$B60) -> 16543 | CG60: =+BX60+CC60+CD60 -> 16543 | CH60: =+CI60-CG60 -> 0.5 | CI60: =+BZ60+CB60+CD60+CC60 -> 16543.5 | CK60: =CN60-CL60 -> -0.5 | CL60: =SUMIFS('Jul 25 Inv'!H:H,'Jul 25 Inv'!E:E,'Summary Rollforward'!$B60) -> 0 | CM60: =-SUMIFS('Jul25 Dep'!J:J,'Jul25 Dep'!F:F,'Summary Rollforward'!$B60) -> 0 | CN60: =SUMIFS('Contract Data'!IR:IR,'Contract Data'!$C:$C,'Summary Rollforward'!$B60) -> -0.5 | CP60: =+CG60+CL60+CM60 -> 16543 | CQ60: =+CR60-CP60 -> 0 | CR60: =+CI60+CK60+CM60+CL60 -> 16543 | CT60: =CW60-CU60 -> 0 | CU60: =SUMIFS('Aug 25 Inv'!H:H,'Aug 25 Inv'!E:E,'Summary Rollforward'!$B60) -> 0 | CV60: =-SUMIFS('Aug25 Dep'!J:J,'Aug25 Dep'!F:F,'Summary Rollforward'!$B60) -> 0 | CW60: =SUMIFS('Contract Data'!IS:IS,'Contract Data'!$C:$C,'Summary Rollforward'!$B60) -> 0 | CY60: =+CP60+CU60+CV60 -> 16543 | CZ60: =+DA60-CY60 -> 0 | DA60: =+CR60+CT60+CV60+CU60 -> 16543 | DC60: =DF60-DD60 -> 76973.1 | DD60: =SUMIFS('Sep 25 Inv'!H:H,'Sep 25 Inv'!E:E,'Summary Rollforward'!$B60) -> 0 | DE60: =-SUMIFS('Sep25 Dep'!J:J,'Sep25 Dep'!F:F,'Summary Rollforward'!$B60) -> 0 | DF60: =SUMIFS('Contract Data'!IT:IT,'Contract Data'!$C:$C,'Summary Rollforward'!$B60) -> 76973.1 | DH60: =+CY60+DD60+DE60 -> 16543 | DI60: =+DJ60-DH60 -> 76973.1 | DJ60: =+DA60+DC60+DE60+DD60 -> 93516.1 | DL60: =DO60-DM60 -> 0 | DM60: =SUMIFS('Oct 25 Inv'!H:H,'Oct 25 Inv'!E:E,'Summary Rollforward'!$B60) -> 0 | DN60: =-SUMIFS('Oct25 Dep'!J:J,'Oct25 Dep'!F:F,'Summary Rollforward'!$B60) -> 0 | DO60: =SUMIFS('Contract Data'!IU:IU,'Contract Data'!$C:$C,'Summary Rollforward'!$B60) -> 0 | DQ60: =+DH60+DM60+DN60 -> 16543 | DR60: =+DS60-DQ60 -> 76973.1 | DS60: =+DJ60+DL60+DN60+DM60 -> 93516.1 | DU60: =DX60-DV60 -> 0 | DV60: =SUMIFS('Nov 25 Inv'!H:H,'Nov 25 Inv'!E:E,'Summary Rollforward'!$B60) -> 0 | DW60: =-SUMIFS('Nov25 Dep'!J:J,'Nov25 Dep'!F:F,'Summary Rollforward'!$B60) -> -16543 | DX60: =SUMIFS('Contract Data'!IV:IV,'Contract Data'!$C:$C,'Summary Rollforward'!$B60) -> 0 | DZ60: =+DQ60+DV60+DW60 -> 0 | EA60: =+EB60-DZ60 -> 76973.1 | EB60: =+DS60+DU60+DW60+DV60 -> 76973.1 | ED60: =EG60-EE60 -> 0 | EE60: =SUMIFS('Dec 25 Inv'!H:H,'Dec 25 Inv'!E:E,'Summary Rollforward'!$B60) -> 0 | EF60: =-SUMIFS('Dec25 Dep'!I:I,'Dec25 Dep'!F:F,'Summary Rollforward'!$B60) -> 0 | EG60: =SUMIFS('Contract Data'!IW:IW,'Contract Data'!$C:$C,'Summary Rollforward'!$B60) -> 0 | EI60: =+DZ60+EE60+EF60 -> 0 | EJ60: =+EK60-EI60 -> 76973.1 | EK60: =+EB60+ED60+EF60+EE60 -> 76973.1
B61: Reaction Biology Corp. | C61: Copeba | F61: =+G61-E61 -> 10000 | G61: =+'AR Calculation - Service'!AM169 -> 10000 | M61: =+N61-L61 -> 10000 | N61: =+G61+I61+J61 -> 10000 | S61: 0 | T61: =+U61-S61 -> 10000 | U61: =+N61+P61+Q61 -> 10000 | Z61: 0 | AA61: =+AB61-Z61 -> 10000 | AB61: =+U61+W61+X61 -> 10000 | AF61: -10000 | AI61: 0 | AJ61: =+AK61-AI61 -> 2.1827873e-11 | AK61: =+AB61+AD61+AG61+AF61+AE61 -> 2.1827873e-11 | AM61: 0 | AO61: =-'Oct Collections'!AF32-'Oct Collections'!AF33 -> 0 | AQ61: =+AI61+AN61+AO61 -> 0 | AR61: =+AS61-AQ61 -> 2.1827873e-11 | AS61: =+AK61+AM61+AO61+AN61 -> 2.1827873e-11 | AU61: 0 | AW61: =-'Oct Collections'!AN32-'Oct Collections'!AN33 -> 0 | AY61: =+AQ61+AV61+AW61 -> 0 | AZ61: =+BA61-AY61 -> 2.1827873e-11 | BA61: =+AS61+AU61+AW61+AV61 -> 2.1827873e-11 | BC61: 0 | BG61: =+AY61+BD61+BE61 -> 0 | BH61: =+BI61-BG61 -> 2.1827873e-11 | BI61: =+BA61+BC61+BE61+BD61 -> 2.1827873e-11 | BO61: =+BG61+BL61+BM61 -> 0 | BP61: =+BQ61-BO61 -> 2.1827873e-11 | BQ61: =+BI61+BK61+BM61+BL61 -> 2.1827873e-11 | BS61: =BV61-BT61 -> 0 | BT61: 0 | BU61: 0 | BV61: =SUMIFS('Contract Data'!IP:IP,'Contract Data'!C:C,'Summary Rollforward'!B61) -> 0 | BX61: =+BO61+BT61+BU61 -> 0 | BY61: =+BZ61-BX61 -> 2.1827873e-11 | BZ61: =+BQ61+BS61+BU61+BT61 -> 2.1827873e-11 | CB61: =CE61-CC61 -> 0 | CC61: =SUMIFS('June 25 Inv'!G:G,'June 25 Inv'!D:D,'Summary Rollforward'!$B61) -> 0 | CD61: =-SUMIFS('Jun25 Dep'!I:I,'Jun25 Dep'!F:F,'Summary Rollforward'!$B61) -> 0 | CE61: =SUMIFS('Contract Data'!IQ:IQ,'Contract Data'!$C:$C,'Summary Rollforward'!$B61) -> 0 | CG61: =+BX61+CC61+CD61 -> 0 | CH61: =+CI61-CG61 -> 2.1827873e-11 | CI61: =+BZ61+CB61+CD61+CC61 -> 2.1827873e-11 | CK61: =CN61-CL61 -> 0 | CL61: =SUMIFS('Jul 25 Inv'!H:H,'Jul 25 Inv'!E:E,'Summary Rollforward'!$B61) -> 0 | CM61: =-SUMIFS('Jul25 Dep'!J:J,'Jul25 Dep'!F:F,'Summary Rollforward'!$B61) -> 0 | CN61: =SUMIFS('Contract Data'!IR:IR,'Contract Data'!$C:$C,'Summary Rollforward'!$B61) -> 0 | CP61: =+CG61+CL61+CM61 -> 0 | CQ61: =+CR61-CP61 -> 2.1827873e-11 | CR61: =+CI61+CK61+CM61+CL61 -> 2.1827873e-11 | CT61: =CW61-CU61 -> 0 | CU61: =SUMIFS('Aug 25 Inv'!H:H,'Aug 25 Inv'!E:E,'Summary Rollforward'!$B61) -> 0 | CV61: =-SUMIFS('Aug25 Dep'!J:J,'Aug25 Dep'!F:F,'Summary Rollforward'!$B61) -> 0 | CW61: =SUMIFS('Contract Data'!IS:IS,'Contract Data'!$C:$C,'Summary Rollforward'!$B61) -> 0 | CY61: =+CP61+CU61+CV61 -> 0 | CZ61: =+DA61-CY61 -> 2.1827873e-11 | DA61: =+CR61+CT61+CV61+CU61 -> 2.1827873e-11 | DC61: =DF61-DD61 -> 0 | DD61: =SUMIFS('Sep 25 Inv'!H:H,'Sep 25 Inv'!E:E,'Summary Rollforward'!$B61) -> 0 | DE61: =-SUMIFS('Sep25 Dep'!J:J,'Sep25 Dep'!F:F,'Summary Rollforward'!$B61) -> 0 | DF61: =SUMIFS('Contract Data'!IT:IT,'Contract Data'!$C:$C,'Summary Rollforward'!$B61) -> 0 | DH61: =+CY61+DD61+DE61 -> 0 | DI61: =+DJ61-DH61 -> 2.1827873e-11 | DJ61: =+DA61+DC61+DE61+DD61 -> 2.1827873e-11 | DL61: =DO61-DM61 -> 0 | DM61: =SUMIFS('Oct 25 Inv'!H:H,'Oct 25 Inv'!E:E,'Summary Rollforward'!$B61) -> 0 | DN61: =-SUMIFS('Oct25 Dep'!J:J,'Oct25 Dep'!F:F,'Summary Rollforward'!$B61) -> 0 | DO61: =SUMIFS('Contract Data'!IU:IU,'Contract Data'!$C:$C,'Summary Rollforward'!$B61) -> 0 | DQ61: =+DH61+DM61+DN61 -> 0 | DR61: =+DS61-DQ61 -> 2.1827873e-11 | DS61: =+DJ61+DL61+DN61+DM61 -> 2.1827873e-11 | DU61: =DX61-DV61 -> 0 | DV61: =SUMIFS('Nov 25 Inv'!H:H,'Nov 25 Inv'!E:E,'Summary Rollforward'!$B61) -> 0 | DW61: =-SUMIFS('Nov25 Dep'!J:J,'Nov25 Dep'!F:F,'Summary Rollforward'!$B61) -> 0 | DX61: =SUMIFS('Contract Data'!IV:IV,'Contract Data'!$C:$C,'Summary Rollforward'!$B61) -> 0 | DZ61: =+DQ61+DV61+DW61 -> 0 | EA61: =+EB61-DZ61 -> 2.1827873e-11 | EB61: =+DS61+DU61+DW61+DV61 -> 2.1827873e-11 | ED61: =EG61-EE61 -> 0 | EE61: =SUMIFS('Dec 25 Inv'!H:H,'Dec 25 Inv'!E:E,'Summary Rollforward'!$B61) -> 0 | EF61: =-SUMIFS('Dec25 Dep'!I:I,'Dec25 Dep'!F:F,'Summary Rollforward'!$B61) -> 0 | EG61: =SUMIFS('Contract Data'!IW:IW,'Contract Data'!$C:$C,'Summary Rollforward'!$B61) -> 0 | EI61: =+DZ61+EE61+EF61 -> 0 | EJ61: =+EK61-EI61 -> 2.1827873e-11 | EK61: =+EB61+ED61+EF61+EE61 -> 2.1827873e-11
B62: ReFocus Management Services, LLC | C62: Zenyth Partners | CT62: =CW62-CU62 -> 9300 | CU62: =SUMIFS('Aug 25 Inv'!H:H,'Aug 25 Inv'!E:E,'Summary Rollforward'!$B62) -> 0 | CV62: =-SUMIFS('Aug25 Dep'!J:J,'Aug25 Dep'!F:F,'Summary Rollforward'!$B62) -> 0 | CW62: =SUMIFS('Contract Data'!IS:IS,'Contract Data'!$C:$C,'Summary Rollforward'!$B62) -> 9300 | CY62: =+CP62+CU62+CV62 -> 0 | CZ62: =+DA62-CY62 -> 9300 | DA62: =+CR62+CT62+CV62+CU62 -> 9300 | DC62: =DF62-DD62 -> 8600 | DD62: =SUMIFS('Sep 25 Inv'!H:H,'Sep 25 Inv'!E:E,'Summary Rollforward'!$B62) -> 10000 | DE62: =-SUMIFS('Sep25 Dep'!J:J,'Sep25 Dep'!F:F,'Summary Rollforward'!$B62) -> 0 | DF62: =SUMIFS('Contract Data'!IT:IT,'Contract Data'!$C:$C,'Summary Rollforward'!$B62) -> 18600 | DH62: =+CY62+DD62+DE62 -> 10000 | DI62: =+DJ62-DH62 -> 17900 | DJ62: =+DA62+DC62+DE62+DD62 -> 27900 | DL62: =DO62-DM62 -> 8600 | DM62: =SUMIFS('Oct 25 Inv'!H:H,'Oct 25 Inv'!E:E,'Summary Rollforward'!$B62) -> 10000 | DN62: =-SUMIFS('Oct25 Dep'!J:J,'Oct25 Dep'!F:F,'Summary Rollforward'!$B62) -> -10000 | DO62: =SUMIFS('Contract Data'!IU:IU,'Contract Data'!$C:$C,'Summary Rollforward'!$B62) -> 18600 | DQ62: =+DH62+DM62+DN62 -> 10000 | DR62: =+DS62-DQ62 -> 26500 | DS62: =+DJ62+DL62+DN62+DM62 -> 36500 | DU62: =DX62-DV62 -> 12158.205 | DV62: =SUMIFS('Nov 25 Inv'!H:H,'Nov 25 Inv'!E:E,'Summary Rollforward'!$B62) -> 12980 | DW62: =-SUMIFS('Nov25 Dep'!J:J,'Nov25 Dep'!F:F,'Summary Rollforward'!$B62) -> 0 | DX62: =SUMIFS('Contract Data'!IV:IV,'Contract Data'!$C:$C,'Summary Rollforward'!$B62) -> 25138.205 | DZ62: =+DQ62+DV62+DW62 -> 22980 | EA62: =+EB62-DZ62 -> 38658.205 | EB62: =+DS62+DU62+DW62+DV62 -> 61638.205 | ED62: =EG62-EE62 -> 48600 | EE62: =SUMIFS('Dec 25 Inv'!H:H,'Dec 25 Inv'!E:E,'Summary Rollforward'!$B62) -> 10000 | EF62: =-SUMIFS('Dec25 Dep'!I:I,'Dec25 Dep'!F:F,'Summary Rollforward'!$B62) -> -20000 | EG62: =SUMIFS('Contract Data'!IW:IW,'Contract Data'!$C:$C,'Summary Rollforward'!$B62) -> 58600 | EI62: =+DZ62+EE62+EF62 -> 12980 | EJ62: =+EK62-EI62 -> 87258.205 | EK62: =+EB62+ED62+EF62+EE62 -> 100238.21
B63: Remedi8 | C63: VSS Capital | CT63: =CW63-CU63 -> 38351.8 | CU63: =SUMIFS('Aug 25 Inv'!H:H,'Aug 25 Inv'!E:E,'Summary Rollforward'!$B63) -> 0 | CV63: =-SUMIFS('Aug25 Dep'!J:J,'Aug25 Dep'!F:F,'Summary Rollforward'!$B63) -> 0 | CW63: =SUMIFS('Contract Data'!IS:IS,'Contract Data'!$C:$C,'Summary Rollforward'!$B63) -> 38351.8 | CY63: =+CP63+CU63+CV63 -> 0 | CZ63: =+DA63-CY63 -> 38351.8 | DA63: =+CR63+CT63+CV63+CU63 -> 38351.8 | DC63: =DF63-DD63 -> 76703.6 | DD63: =SUMIFS('Sep 25 Inv'!H:H,'Sep 25 Inv'!E:E,'Summary Rollforward'!$B63) -> 0 | DE63: =-SUMIFS('Sep25 Dep'!J:J,'Sep25 Dep'!F:F,'Summary Rollforward'!$B63) -> 0 | DF63: =SUMIFS('Contract Data'!IT:IT,'Contract Data'!$C:$C,'Summary Rollforward'!$B63) -> 76703.6 | DH63: =+CY63+DD63+DE63 -> 0 | DI63: =+DJ63-DH63 -> 115055.4 | DJ63: =+DA63+DC63+DE63+DD63 -> 115055.4 | DL63: =DO63-DM63 -> 76703.6 | DM63: =SUMIFS('Oct 25 Inv'!H:H,'Oct 25 Inv'!E:E,'Summary Rollforward'!$B63) -> 0 | DN63: =-SUMIFS('Oct25 Dep'!J:J,'Oct25 Dep'!F:F,'Summary Rollforward'!$B63) -> 0 | DO63: =SUMIFS('Contract Data'!IU:IU,'Contract Data'!$C:$C,'Summary Rollforward'!$B63) -> 76703.6 | DQ63: =+DH63+DM63+DN63 -> 0 | DR63: =+DS63-DQ63 -> 191759 | DS63: =+DJ63+DL63+DN63+DM63 -> 191759 | DU63: =DX63-DV63 -> 38351.8 | DV63: =SUMIFS('Nov 25 Inv'!H:H,'Nov 25 Inv'!E:E,'Summary Rollforward'!$B63) -> 0 | DW63: =-SUMIFS('Nov25 Dep'!J:J,'Nov25 Dep'!F:F,'Summary Rollforward'!$B63) -> 0 | DX63: =SUMIFS('Contract Data'!IV:IV,'Contract Data'!$C:$C,'Summary Rollforward'!$B63) -> 38351.8 | DZ63: =+DQ63+DV63+DW63 -> 0 | EA63: =+EB63-DZ63 -> 230110.8 | EB63: =+DS63+DU63+DW63+DV63 -> 230110.8 | ED63: =EG63-EE63 -> 10000 | EE63: =SUMIFS('Dec 25 Inv'!H:H,'Dec 25 Inv'!E:E,'Summary Rollforward'!$B63) -> 0 | EF63: =-SUMIFS('Dec25 Dep'!I:I,'Dec25 Dep'!F:F,'Summary Rollforward'!$B63) -> 0 | EG63: =SUMIFS('Contract Data'!IW:IW,'Contract Data'!$C:$C,'Summary Rollforward'!$B63) -> 10000 | EI63: =+DZ63+EE63+EF63 -> 0 | EJ63: =+EK63-EI63 -> 240110.8 | EK63: =+EB63+ED63+EF63+EE63 -> 240110.8
B64: Revature | C64: Investcorp | P64: 3875 | S64: =+'Oct 31'!G17 -> 25000 | T64: =+U64-S64 -> -21125 | U64: =+N64+P64+Q64 -> 3875 | W64: =+'AR Calculation - Service'!AP329 -> 23250 | Z64: =+'Nov 30'!G18 -> 25000 | AA64: =+AB64-Z64 -> 2125 | AB64: =+U64+W64+X64 -> 27125 | AD64: =+'AR Calculation - Service'!AQ329-AE64 -> 22875 | AE64: =+'Dec Invoicing'!I19 -> 25000 | AI64: =+'Dec 31'!G19 -> 50000 | AJ64: =+AK64-AI64 -> 25000 | AK64: =+AB64+AD64+AG64+AF64+AE64 -> 75000 | AM64: =+'AR Calculation - Service'!AR329-'Summary Rollforward'!AN64 -> -25000 | AN64: =+'Jan Invoicing'!G13 -> 25000 | AO64: =-'Oct Collections'!AF33-'Oct Collections'!AF34 -> 0 | AQ64: =+AI64+AN64+AO64 -> 75000 | AR64: =+AS64-AQ64 -> 0 | AS64: =+AK64+AM64+AO64+AN64 -> 75000 | AU64: =+'AR Calculation - Service'!BB329-'Summary Rollforward'!AV64 -> 0 | AV64: =+'Jan Invoicing'!O13 -> 0 | AW64: =-'Oct Collections'!AN33-'Oct Collections'!AN34 -> 0 | AY64: =+AQ64+AV64+AW64 -> 75000 | AZ64: =+BA64-AY64 -> 0 | BA64: =+AS64+AU64+AW64+AV64 -> 75000 | BC64: 0 | BD64: =+'Jan Invoicing'!W13 -> 0 | BG64: =+AY64+BD64+BE64 -> 75000 | BH64: =+BI64-BG64 -> 0 | BI64: =+BA64+BC64+BE64+BD64 -> 75000 | BO64: =+BG64+BL64+BM64 -> 75000 | BP64: =+BQ64-BO64 -> 0 | BQ64: =+BI64+BK64+BM64+BL64 -> 75000 | BS64: =BV64-BT64 -> 0 | BT64: 0 | BU64: -75000 | BV64: =SUMIFS('Contract Data'!IP:IP,'Contract Data'!C:C,'Summary Rollforward'!B64) -> 0 | BX64: =+BO64+BT64+BU64 -> 0 | BY64: =+BZ64-BX64 -> 0 | BZ64: =+BQ64+BS64+BU64+BT64 -> 0 | CB64: =CE64-CC64 -> 0 | CC64: =SUMIFS('June 25 Inv'!G:G,'June 25 Inv'!D:D,'Summary Rollforward'!$B64) -> 0 | CD64: =-SUMIFS('Jun25 Dep'!I:I,'Jun25 Dep'!F:F,'Summary Rollforward'!$B64) -> 0 | CE64: =SUMIFS('Contract Data'!IQ:IQ,'Contract Data'!$C:$C,'Summary Rollforward'!$B64) -> 0 | CG64: =+BX64+CC64+CD64 -> 0 | CH64: =+CI64-CG64 -> 0 | CI64: =+BZ64+CB64+CD64+CC64 -> 0 | CK64: =CN64-CL64 -> 0 | CL64: =SUMIFS('Jul 25 Inv'!H:H,'Jul 25 Inv'!E:E,'Summary Rollforward'!$B64) -> 0 | CM64: =-SUMIFS('Jul25 Dep'!J:J,'Jul25 Dep'!F:F,'Summary Rollforward'!$B64) -> 0 | CN64: =SUMIFS('Contract Data'!IR:IR,'Contract Data'!$C:$C,'Summary Rollforward'!$B64) -> 0 | CP64: =+CG64+CL64+CM64 -> 0 | CQ64: =+CR64-CP64 -> 0 | CR64: =+CI64+CK64+CM64+CL64 -> 0 | CT64: =CW64-CU64 -> 0 | CU64: =SUMIFS('Aug 25 Inv'!H:H,'Aug 25 Inv'!E:E,'Summary Rollforward'!$B64) -> 0 | CV64: =-SUMIFS('Aug25 Dep'!J:J,'Aug25 Dep'!F:F,'Summary Rollforward'!$B64) -> 0 | CW64: =SUMIFS('Contract Data'!IS:IS,'Contract Data'!$C:$C,'Summary Rollforward'!$B64) -> 0 | CY64: =+CP64+CU64+CV64 -> 0 | CZ64: =+DA64-CY64 -> 0 | DA64: =+CR64+CT64+CV64+CU64 -> 0 | DC64: =DF64-DD64 -> 0 | DD64: =SUMIFS('Sep 25 Inv'!H:H,'Sep 25 Inv'!E:E,'Summary Rollforward'!$B64) -> 0 | DE64: =-SUMIFS('Sep25 Dep'!J:J,'Sep25 Dep'!F:F,'Summary Rollforward'!$B64) -> 0 | DF64: =SUMIFS('Contract Data'!IT:IT,'Contract Data'!$C:$C,'Summary Rollforward'!$B64) -> 0 | DH64: =+CY64+DD64+DE64 -> 0 | DI64: =+DJ64-DH64 -> 0 | DJ64: =+DA64+DC64+DE64+DD64 -> 0 | DL64: =DO64-DM64 -> 0 | DM64: =SUMIFS('Oct 25 Inv'!H:H,'Oct 25 Inv'!E:E,'Summary Rollforward'!$B64) -> 0 | DN64: =-SUMIFS('Oct25 Dep'!J:J,'Oct25 Dep'!F:F,'Summary Rollforward'!$B64) -> 0 | DO64: =SUMIFS('Contract Data'!IU:IU,'Contract Data'!$C:$C,'Summary Rollforward'!$B64) -> 0 | DQ64: =+DH64+DM64+DN64 -> 0 | DR64: =+DS64-DQ64 -> 0 | DS64: =+DJ64+DL64+DN64+DM64 -> 0 | DU64: =DX64-DV64 -> 0 | DV64: =SUMIFS('Nov 25 Inv'!H:H,'Nov 25 Inv'!E:E,'Summary Rollforward'!$B64) -> 0 | DW64: =-SUMIFS('Nov25 Dep'!J:J,'Nov25 Dep'!F:F,'Summary Rollforward'!$B64) -> 0 | DX64: =SUMIFS('Contract Data'!IV:IV,'Contract Data'!$C:$C,'Summary Rollforward'!$B64) -> 0 | DZ64: =+DQ64+DV64+DW64 -> 0 | EA64: =+EB64-DZ64 -> 0 | EB64: =+DS64+DU64+DW64+DV64 -> 0 | ED64: =EG64-EE64 -> 0 | EE64: =SUMIFS('Dec 25 Inv'!H:H,'Dec 25 Inv'!E:E,'Summary Rollforward'!$B64) -> 0 | EF64: =-SUMIFS('Dec25 Dep'!I:I,'Dec25 Dep'!F:F,'Summary Rollforward'!$B64) -> 0 | EG64: =SUMIFS('Contract Data'!IW:IW,'Contract Data'!$C:$C,'Summary Rollforward'!$B64) -> 0 | EI64: =+DZ64+EE64+EF64 -> 0 | EJ64: =+EK64-EI64 -> 0 | EK64: =+EB64+ED64+EF64+EE64 -> 0
B65: RoadSafe Traffic Systems | C65: Investcorp | E65: =+'Aug 31'!G13 -> 56666.67 | F65: =+G65-E65 -> -22666.67 | G65: =+'AR Calculation - Service'!AM173 -> 34000 | I65: =+'AR Calculation - Service'!AN172 -> 31620 | J65: =+'AR Calculation - Service'!AN171 -> -56666.67 | M65: =+N65-L65 -> 8953.33 | N65: =+G65+I65+J65 -> 8953.33 | P65: 31620 | S65: =+'Oct 31'!G18 -> 56666.67 | T65: =+U65-S65 -> -16093.34 | U65: =+N65+P65+Q65 -> 40573.33 | W65: =+'AR Calculation - Service'!AP172 -> 31620 | X65: =+'Nov Collections'!I62 -> -56666.67 | Z65: =+'Nov 30'!G19 -> 56666.67 | AA65: =+AB65-Z65 -> -41140.01 | AB65: =+U65+W65+X65 -> 15526.66 | AD65: =+'AR Calculation - Service'!AQ172 -> 116140 | AG65: =+'AR Calculation - Service'!AQ171 -> -56666.67 | AI65: =+'Nov 30'!K19 -> 0 | AJ65: =+AK65-AI65 -> 74999.99 | AK65: =+AB65+AD65+AG65+AF65+AE65 -> 74999.99 | AM65: 0 | AO65: =-'Oct Collections'!AF34-'Oct Collections'!AF35 -> 0 | AQ65: =+AI65+AN65+AO65 -> 0 | AR65: =+AS65-AQ65 -> 74999.99 | AS65: =+AK65+AM65+AO65+AN65 -> 74999.99 | AU65: 0 | AW65: =-'Oct Collections'!AN34-'Oct Collections'!AN35 -> 0 | AY65: =+AQ65+AV65+AW65 -> 0 | AZ65: =+BA65-AY65 -> 74999.99 | BA65: =+AS65+AU65+AW65+AV65 -> 74999.99 | BC65: =-BD65 -> -75000 | BD65: =+'Mar Invoices'!G17 -> 75000 | BG65: =+AY65+BD65+BE65 -> 75000 | BH65: =+BI65-BG65 -> -0.01 | BI65: =+BA65+BC65+BE65+BD65 -> 74999.99 | BO65: =+BG65+BL65+BM65 -> 75000 | BP65: =+BQ65-BO65 -> -0.01 | BQ65: =+BI65+BK65+BM65+BL65 -> 74999.99 | BS65: =BV65-BT65 -> 0 | BT65: 0 | BU65: 0 | BV65: =SUMIFS('Contract Data'!IP:IP,'Contract Data'!C:C,'Summary Rollforward'!B65) -> 0 | BX65: =+BO65+BT65+BU65 -> 75000 | BY65: =+BZ65-BX65 -> -0.01 | BZ65: =+BQ65+BS65+BU65+BT65 -> 74999.99 | CB65: =CE65-CC65 -> 0 | CC65: =SUMIFS('June 25 Inv'!G:G,'June 25 Inv'!D:D,'Summary Rollforward'!$B65) -> 0 | CD65: =-SUMIFS('Jun25 Dep'!I:I,'Jun25 Dep'!F:F,'Summary Rollforward'!$B65) -> 0 | CE65: =SUMIFS('Contract Data'!IQ:IQ,'Contract Data'!$C:$C,'Summary Rollforward'!$B65) -> 0 | CG65: =+BX65+CC65+CD65 -> 75000 | CH65: =+CI65-CG65 -> -0.01 | CI65: =+BZ65+CB65+CD65+CC65 -> 74999.99 | CK65: =CN65-CL65 -> 25000 | CL65: =SUMIFS('Jul 25 Inv'!H:H,'Jul 25 Inv'!E:E,'Summary Rollforward'!$B65) -> 0 | CM65: =-SUMIFS('Jul25 Dep'!J:J,'Jul25 Dep'!F:F,'Summary Rollforward'!$B65) -> 0 | CN65: =SUMIFS('Contract Data'!IR:IR,'Contract Data'!$C:$C,'Summary Rollforward'!$B65) -> 25000 | CP65: =+CG65+CL65+CM65 -> 75000 | CQ65: =+CR65-CP65 -> 24999.99 | CR65: =+CI65+CK65+CM65+CL65 -> 99999.99 | CT65: =CW65-CU65 -> -25000 | CU65: =SUMIFS('Aug 25 Inv'!H:H,'Aug 25 Inv'!E:E,'Summary Rollforward'!$B65) -> 25000 | CV65: =-SUMIFS('Aug25 Dep'!J:J,'Aug25 Dep'!F:F,'Summary Rollforward'!$B65) -> 0 | CW65: =SUMIFS('Contract Data'!IS:IS,'Contract Data'!$C:$C,'Summary Rollforward'!$B65) -> 0 | CY65: =+CP65+CU65+CV65 -> 100000 | CZ65: =+DA65-CY65 -> -0.01 | DA65: =+CR65+CT65+CV65+CU65 -> 99999.99 | DC65: =DF65-DD65 -> 0 | DD65: =SUMIFS('Sep 25 Inv'!H:H,'Sep 25 Inv'!E:E,'Summary Rollforward'!$B65) -> 0 | DE65: =-SUMIFS('Sep25 Dep'!J:J,'Sep25 Dep'!F:F,'Summary Rollforward'!$B65) -> -100000 | DF65: =SUMIFS('Contract Data'!IT:IT,'Contract Data'!$C:$C,'Summary Rollforward'!$B65) -> 0 | DH65: =+CY65+DD65+DE65 -> 0 | DI65: =+DJ65-DH65 -> -0.01 | DJ65: =+DA65+DC65+DE65+DD65 -> -0.01 | DL65: =DO65-DM65 -> 0 | DM65: =SUMIFS('Oct 25 Inv'!H:H,'Oct 25 Inv'!E:E,'Summary Rollforward'!$B65) -> 0 | DN65: =-SUMIFS('Oct25 Dep'!J:J,'Oct25 Dep'!F:F,'Summary Rollforward'!$B65) -> 0 | DO65: =SUMIFS('Contract Data'!IU:IU,'Contract Data'!$C:$C,'Summary Rollforward'!$B65) -> 0 | DQ65: =+DH65+DM65+DN65 -> 0 | DR65: =+DS65-DQ65 -> -0.01 | DS65: =+DJ65+DL65+DN65+DM65 -> -0.01 | DU65: =DX65-DV65 -> 0 | DV65: =SUMIFS('Nov 25 Inv'!H:H,'Nov 25 Inv'!E:E,'Summary Rollforward'!$B65) -> 0 | DW65: =-SUMIFS('Nov25 Dep'!J:J,'Nov25 Dep'!F:F,'Summary Rollforward'!$B65) -> 0 | DX65: =SUMIFS('Contract Data'!IV:IV,'Contract Data'!$C:$C,'Summary Rollforward'!$B65) -> 0 | DZ65: =+DQ65+DV65+DW65 -> 0 | EA65: =+EB65-DZ65 -> -0.01 | EB65: =+DS65+DU65+DW65+DV65 -> -0.01 | ED65: =EG65-EE65 -> 0 | EE65: =SUMIFS('Dec 25 Inv'!H:H,'Dec 25 Inv'!E:E,'Summary Rollforward'!$B65) -> 0 | EF65: =-SUMIFS('Dec25 Dep'!I:I,'Dec25 Dep'!F:F,'Summary Rollforward'!$B65) -> 0 | EG65: =SUMIFS('Contract Data'!IW:IW,'Contract Data'!$C:$C,'Summary Rollforward'!$B65) -> 0 | EI65: =+DZ65+EE65+EF65 -> 0 | EJ65: =+EK65-EI65 -> -0.01 | EK65: =+EB65+ED65+EF65+EE65 -> -0.01
B66: Robinson Helicopter Co | C66: Trive Capital | E66: =+'Aug 31'!G14 -> 213000 | F66: =+G66-E66 -> -5916.6667 | G66: =+'AR Calculation - Service'!AM177 -> 207083.33 | L66: =+'Sep 30'!G17 -> 213000 | M66: =+N66-L66 -> -5916.6667 | N66: =+G66+I66+J66 -> 207083.33 | S66: =+'Oct 31'!G19 -> 71000 | T66: 0 | U66: =+N66+P66+Q66-142000 -> 65083.333 | Z66: =+'Oct 31'!N19 -> 0 | AA66: =+AB66-Z66 -> 0 | AB66: 0 | AI66: =+'Oct 31'!R19 -> 0 | AJ66: =+AK66-AI66 -> 0 | AK66: =+AB66+AD66+AG66+AF66+AE66 -> 0 | AM66: 0 | AO66: =-'Oct Collections'!AF35-'Oct Collections'!AF36 -> 0 | AQ66: =+AI66+AN66+AO66 -> 0 | AR66: =+AS66-AQ66 -> 0 | AS66: =+AK66+AM66+AO66+AN66 -> 0 | AU66: 0 | AW66: =-'Oct Collections'!AN35-'Oct Collections'!AN36 -> 0 | AY66: =+AQ66+AV66+AW66 -> 0 | AZ66: =+BA66-AY66 -> 0 | BA66: =+AS66+AU66+AW66+AV66 -> 0 | BC66: 0 | BG66: =+AY66+BD66+BE66 -> 0 | BH66: =+BI66-BG66 -> 0 | BI66: =+BA66+BC66+BE66+BD66 -> 0 | BO66: =+BG66+BL66+BM66 -> 0 | BP66: =+BQ66-BO66 -> 0 | BQ66: =+BI66+BK66+BM66+BL66 -> 0 | BS66: =BV66-BT66 -> 0 | BT66: 0 | BU66: 0 | BV66: =SUMIFS('Contract Data'!IP:IP,'Contract Data'!C:C,'Summary Rollforward'!B66) -> 0 | BX66: =+BO66+BT66+BU66 -> 0 | BY66: =+BZ66-BX66 -> 0 | BZ66: =+BQ66+BS66+BU66+BT66 -> 0 | CB66: =CE66-CC66 -> 0 | CC66: =SUMIFS('June 25 Inv'!G:G,'June 25 Inv'!D:D,'Summary Rollforward'!$B66) -> 0 | CD66: =-SUMIFS('Jun25 Dep'!I:I,'Jun25 Dep'!F:F,'Summary Rollforward'!$B66) -> 0 | CE66: =SUMIFS('Contract Data'!IQ:IQ,'Contract Data'!$C:$C,'Summary Rollforward'!$B66) -> 0 | CG66: =+BX66+CC66+CD66 -> 0 | CH66: =+CI66-CG66 -> 0 | CI66: =+BZ66+CB66+CD66+CC66 -> 0 | CK66: =CN66-CL66 -> 0 | CL66: =SUMIFS('Jul 25 Inv'!H:H,'Jul 25 Inv'!E:E,'Summary Rollforward'!$B66) -> 0 | CM66: =-SUMIFS('Jul25 Dep'!J:J,'Jul25 Dep'!F:F,'Summary Rollforward'!$B66) -> 0 | CN66: =SUMIFS('Contract Data'!IR:IR,'Contract Data'!$C:$C,'Summary Rollforward'!$B66) -> 0 | CP66: =+CG66+CL66+CM66 -> 0 | CQ66: =+CR66-CP66 -> 0 | CR66: =+CI66+CK66+CM66+CL66 -> 0 | CT66: =CW66-CU66 -> 0 | CU66: =SUMIFS('Aug 25 Inv'!H:H,'Aug 25 Inv'!E:E,'Summary Rollforward'!$B66) -> 0 | CV66: =-SUMIFS('Aug25 Dep'!J:J,'Aug25 Dep'!F:F,'Summary Rollforward'!$B66) -> 0 | CW66: =SUMIFS('Contract Data'!IS:IS,'Contract Data'!$C:$C,'Summary Rollforward'!$B66) -> 0 | CY66: =+CP66+CU66+CV66 -> 0 | CZ66: =+DA66-CY66 -> 0 | DA66: =+CR66+CT66+CV66+CU66 -> 0 | DC66: =DF66-DD66 -> 0 | DD66: =SUMIFS('Sep 25 Inv'!H:H,'Sep 25 Inv'!E:E,'Summary Rollforward'!$B66) -> 0 | DE66: =-SUMIFS('Sep25 Dep'!J:J,'Sep25 Dep'!F:F,'Summary Rollforward'!$B66) -> 0 | DF66: =SUMIFS('Contract Data'!IT:IT,'Contract Data'!$C:$C,'Summary Rollforward'!$B66) -> 0 | DH66: =+CY66+DD66+DE66 -> 0 | DI66: =+DJ66-DH66 -> 0 | DJ66: =+DA66+DC66+DE66+DD66 -> 0 | DL66: =DO66-DM66 -> 0 | DM66: =SUMIFS('Oct 25 Inv'!H:H,'Oct 25 Inv'!E:E,'Summary Rollforward'!$B66) -> 0 | DN66: =-SUMIFS('Oct25 Dep'!J:J,'Oct25 Dep'!F:F,'Summary Rollforward'!$B66) -> 0 | DO66: =SUMIFS('Contract Data'!IU:IU,'Contract Data'!$C:$C,'Summary Rollforward'!$B66) -> 0 | DQ66: =+DH66+DM66+DN66 -> 0 | DR66: =+DS66-DQ66 -> 0 | DS66: =+DJ66+DL66+DN66+DM66 -> 0 | DU66: =DX66-DV66 -> 0 | DV66: =SUMIFS('Nov 25 Inv'!H:H,'Nov 25 Inv'!E:E,'Summary Rollforward'!$B66) -> 0 | DW66: =-SUMIFS('Nov25 Dep'!J:J,'Nov25 Dep'!F:F,'Summary Rollforward'!$B66) -> 0 | DX66: =SUMIFS('Contract Data'!IV:IV,'Contract Data'!$C:$C,'Summary Rollforward'!$B66) -> 0 | DZ66: =+DQ66+DV66+DW66 -> 0 | EA66: =+EB66-DZ66 -> 0 | EB66: =+DS66+DU66+DW66+DV66 -> 0 | ED66: =EG66-EE66 -> 0 | EE66: =SUMIFS('Dec 25 Inv'!H:H,'Dec 25 Inv'!E:E,'Summary Rollforward'!$B66) -> 0 | EF66: =-SUMIFS('Dec25 Dep'!I:I,'Dec25 Dep'!F:F,'Summary Rollforward'!$B66) -> 0 | EG66: =SUMIFS('Contract Data'!IW:IW,'Contract Data'!$C:$C,'Summary Rollforward'!$B66) -> 0 | EI66: =+DZ66+EE66+EF66 -> 0 | EJ66: =+EK66-EI66 -> 0 | EK66: =+EB66+ED66+EF66+EE66 -> 0
B67: Royal Foods | C67: Trilantic | P67: 32162.19 | Q67: =-'Oct Collections'!J16 -> -83000 | S67: 0 | U67: =+N67+P67+Q67 -> -50837.81 | W67: =+'AR Calculation - Service'!AP309 -> 64325 | X67: =+'Nov Collections'!I36 -> -83000 | Z67: 0 | AA67: =+AB67-Z67 -> -69512.81 | AB67: =+U67+W67+X67 -> -69512.81 | AD67: =+'AR Calculation - Service'!AQ309-AE67 -> 29474.81 | AE67: =+'Dec Invoicing'!I20 -> 83000 | AG67: =+'Nov Collections'!P36 -> 0 | AI67: =+'Dec 31'!G20 -> 83000 | AJ67: =+AK67-AI67 -> -40038 | AK67: =+AB67+AD67+AG67+AF67+AE67 -> 42962 | AM67: =+'AR Calculation - Service'!AR309-'Summary Rollforward'!AN67 -> -15294 | AN67: =+'Jan Invoicing'!G14 -> 84461 | AO67: =+'AR Calculation - Service'!AR308 -> -83000 | AQ67: =+AI67+AN67+AO67 -> 84461 | AR67: =+AS67-AQ67 -> -55332 | AS67: =+AK67+AM67+AO67+AN67 -> 29129 | AU67: =+'AR Calculation - Service'!AS309-'Summary Rollforward'!AV67 -> 69167 | AV67: =+'Jan Invoicing'!O14 -> 0 | AW67: =+'AR Calculation - Service'!AS308 -> -84461 | AY67: =+AQ67+AV67+AW67 -> 0 | AZ67: =+BA67-AY67 -> 13835 | BA67: =+AS67+AU67+AW67+AV67 -> 13835 | BC67: =+'AR Calculation - Service'!AT309-'Summary Rollforward'!BD67 -> -13833 | BD67: =+'Mar Invoices'!G13 -> 83000 | BG67: =+AY67+BD67+BE67 -> 83000 | BH67: =+BI67-BG67 -> 2 | BI67: =+BA67+BC67+BE67+BD67 -> 83002 | BM67: =+'AR Calculation - Service'!AU308 -> -83000 | BO67: =+BG67+BL67+BM67 -> 0 | BP67: =+BQ67-BO67 -> 2 | BQ67: =+BI67+BK67+BM67+BL67 -> 2 | BS67: =BV67-BT67 -> 0 | BT67: 0 | BU67: 0 | BV67: =SUMIFS('Contract Data'!IP:IP,'Contract Data'!C:C,'Summary Rollforward'!B67) -> 0 | BX67: =+BO67+BT67+BU67 -> 0 | BY67: =+BZ67-BX67 -> 2 | BZ67: =+BQ67+BS67+BU67+BT67 -> 2 | CB67: =CE67-CC67 -> 0 | CC67: =SUMIFS('June 25 Inv'!G:G,'June 25 Inv'!D:D,'Summary Rollforward'!$B67) -> 0 | CD67: =-SUMIFS('Jun25 Dep'!I:I,'Jun25 Dep'!F:F,'Summary Rollforward'!$B67) -> 0 | CE67: =SUMIFS('Contract Data'!IQ:IQ,'Contract Data'!$C:$C,'Summary Rollforward'!$B67) -> 0 | CG67: =+BX67+CC67+CD67 -> 0 | CH67: =+CI67-CG67 -> 2 | CI67: =+BZ67+CB67+CD67+CC67 -> 2 | CK67: =CN67-CL67 -> -2 | CL67: =SUMIFS('Jul 25 Inv'!H:H,'Jul 25 Inv'!E:E,'Summary Rollforward'!$B67) -> 0 | CM67: =-SUMIFS('Jul25 Dep'!J:J,'Jul25 Dep'!F:F,'Summary Rollforward'!$B67) -> 0 | CN67: =SUMIFS('Contract Data'!IR:IR,'Contract Data'!$C:$C,'Summary Rollforward'!$B67) -> -2 | CP67: =+CG67+CL67+CM67 -> 0 | CQ67: =+CR67-CP67 -> 0 | CR67: =+CI67+CK67+CM67+CL67 -> 0 | CT67: =CW67-CU67 -> 0 | CU67: =SUMIFS('Aug 25 Inv'!H:H,'Aug 25 Inv'!E:E,'Summary Rollforward'!$B67) -> 0 | CV67: =-SUMIFS('Aug25 Dep'!J:J,'Aug25 Dep'!F:F,'Summary Rollforward'!$B67) -> 0 | CW67: =SUMIFS('Contract Data'!IS:IS,'Contract Data'!$C:$C,'Summary Rollforward'!$B67) -> 0 | CY67: =+CP67+CU67+CV67 -> 0 | CZ67: =+DA67-CY67 -> 0 | DA67: =+CR67+CT67+CV67+CU67 -> 0 | DC67: =DF67-DD67 -> 0 | DD67: =SUMIFS('Sep 25 Inv'!H:H,'Sep 25 Inv'!E:E,'Summary Rollforward'!$B67) -> 0 | DE67: =-SUMIFS('Sep25 Dep'!J:J,'Sep25 Dep'!F:F,'Summary Rollforward'!$B67) -> 0 | DF67: =SUMIFS('Contract Data'!IT:IT,'Contract Data'!$C:$C,'Summary Rollforward'!$B67) -> 0 | DH67: =+CY67+DD67+DE67 -> 0 | DI67: =+DJ67-DH67 -> 0 | DJ67: =+DA67+DC67+DE67+DD67 -> 0 | DL67: =DO67-DM67 -> 0 | DM67: =SUMIFS('Oct 25 Inv'!H:H,'Oct 25 Inv'!E:E,'Summary Rollforward'!$B67) -> 0 | DN67: =-SUMIFS('Oct25 Dep'!J:J,'Oct25 Dep'!F:F,'Summary Rollforward'!$B67) -> 0 | DO67: =SUMIFS('Contract Data'!IU:IU,'Contract Data'!$C:$C,'Summary Rollforward'!$B67) -> 0 | DQ67: =+DH67+DM67+DN67 -> 0 | DR67: =+DS67-DQ67 -> 0 | DS67: =+DJ67+DL67+DN67+DM67 -> 0 | DU67: =DX67-DV67 -> 0 | DV67: =SUMIFS('Nov 25 Inv'!H:H,'Nov 25 Inv'!E:E,'Summary Rollforward'!$B67) -> 0 | DW67: =-SUMIFS('Nov25 Dep'!J:J,'Nov25 Dep'!F:F,'Summary Rollforward'!$B67) -> 0 | DX67: =SUMIFS('Contract Data'!IV:IV,'Contract Data'!$C:$C,'Summary Rollforward'!$B67) -> 0 | DZ67: =+DQ67+DV67+DW67 -> 0 | EA67: =+EB67-DZ67 -> 0 | EB67: =+DS67+DU67+DW67+DV67 -> 0 | ED67: =EG67-EE67 -> 0 | EE67: =SUMIFS('Dec 25 Inv'!H:H,'Dec 25 Inv'!E:E,'Summary Rollforward'!$B67) -> 0 | EF67: =-SUMIFS('Dec25 Dep'!I:I,'Dec25 Dep'!F:F,'Summary Rollforward'!$B67) -> 0 | EG67: =SUMIFS('Contract Data'!IW:IW,'Contract Data'!$C:$C,'Summary Rollforward'!$B67) -> 0 | EI67: =+DZ67+EE67+EF67 -> 0 | EJ67: =+EK67-EI67 -> 0 | EK67: =+EB67+ED67+EF67+EE67 -> 0
